Workbook

Sheet 0. Como Alimentar
A1: 0. COMO ALIMENTAR — VERSÃO MULTI-MÊS CONSOLIDADA
A2: Alimente as bases transacionais (1, 2, 3, 10, 12 e 13) e deixe os relatórios recalcularem. Não edite manualmente as abas analíticas.
A4: CONTROLES
A5: Saldo inicial do fluxo de caixa | B5: 0 | C5: Valor usado na aba 4. Fluxo de Caixa.
A6: Ano-base da DRE mensal | B6: 2026 | C6: Muda a aba 7 para o ano desejado.
A7: Mês de análise (1º dia do mês) | B7: 46082 | C7: Muda as abas 8 e 9 para o mês selecionado.
A8: Último mês no CR | B8: =MAX('2. Contas a Receber'!$N$8:$N$1000) | C8: Leitura automática da base de CR.
A9: Último mês no CP | B9: =MAX('3. Contas a Pagar'!$B$6:$B$1000) | C9: Leitura automática da base de CP.
A12: PASSO A PASSO
A13: 1) Lance novos meses em 2. Contas a Receber e 3. Contas a Pagar nas primeiras linhas vazias.
A14: 2) Se surgir cliente novo, cadastre em 10. Cadastro de Clientes.
A15: 3) Se surgir serviço novo, cadastre em 11. Cadastro de Serviços.
A16: 4) Se surgir contrato recorrente ou OS nova, cadastre em 12. Contratos_OS.
A17: 5) Para rastrear ponta a ponta, espelhe cada novo título em 13. Mapa Títulos-Receita.
A18: 6) Revise 14. Consolidado Mensal, 7. DRE Gerencial Mensal, 8. DRE por Centro de Custo e 9. DRE por Linha de Serviço.
A21: CAMPOS MÍNIMOS PARA NOVO CR
A22: ID título, Cliente, Emissão, Vencimento, Valor e Tipo receita DRE são o mínimo para a DRE funcionar.
A23: Recebimento, Valor recebido e Status permitem fechar o caixa e a carteira.
A24: Cliente mestre, Contrato/OS, Serviço e Centro de resultado dão rastreabilidade ERP.
A28: CAMPOS MÍNIMOS PARA NOVO CP
... A31: A classificação DRE agora é automática por grupo/natureza via 17. Mapa DRE CP; revise quando aparecer "Revisar".

Sheet Catálogo de Serviços
A1: CATÁLOGO DE SERVIÇOS — BASE DE PREÇO PISO EXTRAÍDA DA PLANILHA ORIGINAL
A2: Use este catálogo como referência comercial no bloco 1. Valores baseados na aba "Tabela de Serviços" da planilha enviada.
A4: Serviço | B4: Horas estimadas | C4: Km base | D4: Retrabalho | E4: Piso base | F4: Piso c/ margem 20% | G4: Fator risco ART
A5: PCMSO (até 10 funcionários) | B5: 12 | C5: 50 | D5: 0.12 | E5: 4558 | F5: 5890 | G5: 15–30%
A6: PCMSO (11–30 funcionários) | B6: 16 | C6: 50 | D6: 0.14 | E6: 6381 | F6: 8246 | G6: 15–30%
A7: PCMSO (31–100 funcionários) | B7: 22 | C7: 60 | D7: 0.15 | E7: 8660 | F7: 11191 | G7: 15–30%
A8: PGR — Grau I (até 10 func.) | B8: 14 | C8: 70 | D8: 0.15 | E8: 5557 | F8: 7280 | G8: 15–30%
A9: PGR — Grau II (até 10 func.) | B9: 16 | C9: 70 | D9: 0.16 | E9: 6668 | F9: 8736 | G9: 15–30%
A10: PGR — Grau III (até 10 func.) | B10: 20 | C10: 80 | D10: 0.18 | E10: 8057 | F10: 10556 | G10: 15–30%
A11: LTCAT — físicos simples | B11: 18 | C11: 80 | D11: 0.18 | E11: 7465 | F11: 9870 | G11: 15–30%
A12: LTCAT — físicos + químicos | B12: 24 | C12: 80 | D12: 0.2 | E12: 9332 | F12: 13318 | G12: 15–30%
A13: Laudo insalub. — 1 agente | B13: 12 | C13: 60 | D13: 0.2 | E13: 5104 | F13: 6620 | G13: 15–30%
A14: Laudo insalub. — 2–3 agentes | B14: 16 | C14: 60 | D14: 0.22 | E14: 6380 | F14: 8276 | G14: 15–30%
A15: Treinamento NR — até 20 pessoas | B15: 8 | C15: 50 | D15: 0.05 | E15: 2915 | F15: 3680 | G15: +30% noturno
A16: Treinamento NR12 / NR10 | B16: 12 | C16: 50 | D16: 0.08 | E16: 4372 | F16: 5520 | G16: +30%
... A20: Perícia — c/ laudos compl. | B20: 24 | C20: 60 | D20: 0.2 | E20: 9817 | F20: 11688 | G20: +R$1.400/diária
A21: REGRAS DE APLICAÇÃO RÁPIDA
A22: Preço piso | B22: Chão absoluto. Nenhuma proposta pode sair abaixo deste valor. É o custo real + overhead + tributo + margem 20%.
A23: Preço alvo | B23: Deve ficar entre 120% e 150% do piso para garantir EBITDA saudável e margem para negociação.
A24: Renovação PGR | B24: Desconto máximo de 20% sobre o piso — base já levantada, menos horas necessárias.
A25: Deslocamento | B25: Até 30km de Uberlândia: incluso. 31–100km: +R$1,20/km. Acima de 100km: diária técnica de R$1.400.
A26: Urgência | B26: 7–14 dias: +15%. Menos de 7 dias: +30%. Menos de 48h: +50% ou recusa.
A27: Múltiplas unidades | B27: 2ª e 3ª unidade: fator 0,85 por unidade. 4ª em diante: orçamento específico.

Sheet Diagnóstico 5 Blocos
A1: HIGILABOR — DIAGNÓSTICO CONSOLIDADO DOS 5 BLOCOS
A2: Leitura técnica consolidada após carga do CR/CP de março e inclusão da base de custos do CSV da planilha de precificação.
A4: STATUS DOS 5 BLOCOS
A5: Bloco | B5: Status | C5: O que já existe na planilha enviada | D5: O que falta para gestão real | E5: Próxima base necessária | F5: Prioridade | G5: Leitura executiva
A6: 1. Receita | B6: PARCIAL | C6: Catálogo de serviços e política de preço piso; ainda sem histórico comercial completo por venda. | D6: Histórico real por cliente, data, preço fechado, quantidade, recorrência e desconto. | E6: Planilha/relatório comercial com vendas emitidas. | F6: ALTA | G6: A base econômica está pronta, mas o transacional de vendas ainda precisa ser consolidado.
A7: 2. Contas a Receber | B7: OPERACIONAL | C7: Carteira de março lançada, com títulos, vencimentos, recebimentos, abertos e aging. | D7: Ampliar para histórico contínuo e vincular cada título à venda-mãe. | E7: CR mensal recorrente + chave de venda/pedido. | F7: ALTA | G7: Já mede conversão em caixa; falta histórico e reconciliação com vendas.
A8: 3. Contas a Pagar | B8: OPERACIONAL | C8: CP de março lançado, reconciliado com a base de custos da precificação e agora classificado por centro de custo real e grupo gerencial. | D8: Adicionar datas reais de pagamento e histórico mensal contínuo para sair do retrato pontual. | E8: CP mensal recorrente com data efetiva de pagamento. | F8: ALTA | G8: O bloco já sustenta leitura de saída, caixa e estrutura por grupo de custo.
A9: 4. Fluxo de Caixa | B9: OPERACIONAL | C9: Fluxo mensal já calculado a partir do CR e do CP lançados. | D9: Passar do recorte mensal para rotina semanal e saldo inicial real de caixa. | E9: Saldo inicial + movimentação bancária + CR/CP contínuos. | F9: CRÍTICA | G9: Já mostra pressão de caixa; próximo salto é granularidade semanal e projeção contínua.
A10: 5. Indicadores | B10: PARCIAL | C10: Painel já consolida CR, CP, fluxo e agora a estrutura base do CSV (UEP, custo estrutural e rateio). | D10: Completar com KPIs de receita real, margem por serviço, PMR e concentração por cliente. | E10: Bloco 1 completo + histórico de operações. | F10: ALTA | G10: O painel já é gerencial; falta fechar a camada comercial para virar painel diretivo completo.
A13: BASES INCORPORADAS: Mar/2026 | CR 35.862,39 | CP 38.149,72 | Realizado do mês (recebido-pago): -12.442,03.
A14: BASES INCORPORADAS: Mar/2026 | CR 35.862,39 | CP 38.149,72 | Realizado do mês (recebido-pago): -12.442,03 | CP classificado por grupo gerencial. | B14: 35862.39 | C14: Recebido 25.338,89 | Aberto 10.523,50 | D14: Bloco 2 alimentado | E14: PDF CR | F14: ALTA | G14: Carteira, recebimento e aging já mensuráveis.
A15: Contas a pagar | B15: 38149.72 | C15: Pago 37.780,92 | Aberto 368,80 | D15: Bloco 3 alimentado | E15: PDF CP | F15: ALTA | G15: Saídas e obrigações já estruturadas.
A16: Fluxo de caixa | B16: -12442.03 | C16: Realizado do mês | D16: Bloco 4 operacional | E16: CR + CP | F16: ALTA | G16: Houve aperto de caixa relevante em março.
A17: Receita | C17: Continua parcial | D17: CR mostra títulos, não vendas consolidadas | E17: Base comercial | F17: CRÍTICA | G17: Sem relatório comercial, bloco 1 fica incompleto.
A18: EBITDA mínimo alvo | B18: 0.2 | C18: A política comercial parte de um alvo de margem operacional.
A19: Preço piso PCMSO padrão | B19: 6104.42 | C19: Valor observado na calculadora para o serviço selecionado no arquivo original.

Sheet 1. Receita
A1: 1. RECEITA — LANÇAMENTO COMERCIAL / FATURAMENTO
A2: Lançe cada venda/proposta fechada. O preço piso de referência é puxado do catálogo de serviços.
A4: BASE OPERACIONAL
A5: Data venda | B5: Competência | C5: Cliente | D5: Serviço | E5: Qtd | F5: Preço unitário cotado | G5: Preço piso ref. | H5: Receita bruta | I5: Gap unit. vs piso | J5: Status | K5: Observação
B7: =IF(A7="","",DATE(YEAR(A7),MONTH(A7),1)) | G7: =IFERROR(VLOOKUP(D7,'Catálogo de Serviços'!$A$5:$F$100,6,FALSE),0) | H7: =IFERROR(E7*F7,0) | I7: =IFERROR(F7-G7,0)
B8: =IF(A8="","",DATE(YEAR(A8),MONTH(A8),1)) | G8: =IFERROR(VLOOKUP(D8,'Catálogo de Serviços'!$A$5:$F$100,6,FALSE),0) | H8: =IFERROR(E8*F8,0) | I8: =IFERROR(F8-G8,0)
B9: =IF(A9="","",DATE(YEAR(A9),MONTH(A9),1)) | G9: =IFERROR(VLOOKUP(D9,'Catálogo de Serviços'!$A$5:$F$100,6,FALSE),0) | H9: =IFERROR(E9*F9,0) | I9: =IFERROR(F9-G9,0)
B10: =IF(A10="","",DATE(YEAR(A10),MONTH(A10),1)) | G10: =IFERROR(VLOOKUP(D10,'Catálogo de Serviços'!$A$5:$F$100,6,FALSE),0) | H10: =IFERROR(E10*F10,0) | I10: =IFERROR(F10-G10,0)
B11: =IF(A11="","",DATE(YEAR(A11),MONTH(A11),1)) | G11: =IFERROR(VLOOKUP(D11,'Catálogo de Serviços'!$A$5:$F$100,6,FALSE),0) | H11: =IFERROR(E11*F11,0) | I11: =IFERROR(F11-G11,0)
B12: =IF(A12="","",DATE(YEAR(A12),MONTH(A12),1)) | G12: =IFERROR(VLOOKUP(D12,'Catálogo de Serviços'!$A$5:$F$100,6,FALSE),0) | H12: =IFERROR(E12*F12,0) | I12: =IFERROR(F12-G12,0)
B13: =IF(A13="","",DATE(YEAR(A13),MONTH(A13),1)) | G13: =IFERROR(VLOOKUP(D13,'Catálogo de Serviços'!$A$5:$F$100,6,FALSE),0) | H13: =IFERROR(E13*F13,0) | I13: =IFERROR(F13-G13,0)
B14: =IF(A14="","",DATE(YEAR(A14),MONTH(A14),1)) | G14: =IFERROR(VLOOKUP(D14,'Catálogo de Serviços'!$A$5:$F$100,6,FALSE),0) | H14: =IFERROR(E14*F14,0) | I14: =IFERROR(F14-G14,0)
B15: =IF(A15="","",DATE(YEAR(A15),MONTH(A15),1)) | G15: =IFERROR(VLOOKUP(D15,'Catálogo de Serviços'!$A$5:$F$100,6,FALSE),0) | H15: =IFERROR(E15*F15,0) | I15: =IFERROR(F15-G15,0)
B16: =IF(A16="","",DATE(YEAR(A16),MONTH(A16),1)) | G16: =IFERROR(VLOOKUP(D16,'Catálogo de Serviços'!$A$5:$F$100,6,FALSE),0) | H16: =IFERROR(E16*F16,0) | I16: =IFERROR(F16-G16,0)
B17: =IF(A17="","",DATE(YEAR(A17),MONTH(A17),1)) | G17: =IFERROR(VLOOKUP(D17,'Catálogo de Serviços'!$A$5:$F$100,6,FALSE),0) | H17: =IFERROR(E17*F17,0) | I17: =IFERROR(F17-G17,0)
B18: =IF(A18="","",DATE(YEAR(A18),MONTH(A18),1)) | G18: =IFERROR(VLOOKUP(D18,'Catálogo de Serviços'!$A$5:$F$100,6,FALSE),0) | H18: =IFERROR(E18*F18,0) | I18: =IFERROR(F18-G18,0)
... B1000: =IF(A1000="","",DATE(YEAR(A1000),MONTH(A1000),1)) | G1000: =IFERROR(VLOOKUP(D1000,'Catálogo de Serviços'!$A$5:$F$100,6,FALSE),0) | H1000: =IFERROR(E1000*F1000,0) | I1000: =IFERROR(F1000-G1000,0)
A1001: Bloco 1 continua parcial: CR mensal mostra títulos, não vendas consolidadas. Use relatório de vendas/pedidos.
A1003: RESUMO DO BLOCO 1
A1004: Vendas lançadas | B1004: =COUNTIF(C7:C1000,"<>")
A1005: Receita bruta | B1005: =SUM(H7:H1000)
A1006: Ticket médio | B1006: =IFERROR(B1005/B1004,0)
A1007: Gap médio unitário | B1007: =IFERROR(AVERAGE(I7:I1000),0)

Sheet 2. Contas a Receber
A1: 2. CONTAS A RECEBER — CARTEIRA DE TÍTULOS
A2: Cada linha representa um título/parcela. Agora o CR também está amarrado a cliente mestre, contrato/OS, serviço e centro de resultado.
A4: Data-base da análise | B4: =EOMONTH('0. Como Alimentar'!$B$7,0)
A6: BASE OPERACIONAL
A7: ID título | B7: ID venda | C7: Cliente | D7: Emissão | E7: Vencimento | F7: Recebimento | G7: Parcela | H7: Valor | I7: Valor recebido | J7: Status | K7: Dias atraso | L7: Faixa aging | M7: Observação | N7: Competência gerencial | O7: Tipo receita DRE | P7: Linha de serviço inferida | Q7: Centro de resultado | R7: Critério de classificação | S7: Cliente mestre | T7: Unidade / escopo | U7: Chave contrato/OS | V7: Contrato/OS ID | W7: Tipo vínculo ERP | X7: Cliente ID | Y7: Serviço ID | Z7: Serviço padronizado | AA7: Linha DRE rastreável | AB7: Centro de resultado rastreável | AC7: Parcela rastreada | AD7: Status rastreabilidade | AE7: Nota de rastreio
A8: CR-001 | B8: NIVALMAG - MATRIZ | C8: NIVALMAG - MATRIZ | D8: 46086 | E8: 46086 | F8: 46087 | H8: 1348 | I8: 1348 | J8: Recebido | K8: =IF(J8="","",IF(OR(J8="Recebido",F8=""),MAX(0,F8-E8),MAX(0,$B$4-E8))) | L8: =IF(K8="","",IF(K8=0,"Em dia",IF(K8<=30,"1-30 dias",IF(K8<=60,"31-60 dias",IF(K8<=90,"61-90 dias",">90 dias"))))) | M8: Origem: CR mar/2026. Tipo original: Fixo. Doc/NF: 83. | N8: 46082 | O8: Receita recorrente | P8: =IF(C8="","",IF(ISNUMBER(SEARCH("PCMSO",C8)),"PCMSO",IF(OR(ISNUMBER(SEARCH("E-SOCIAL",C8)),ISNUMBER(SEARCH("PSICOSOCIAL",C8))),"eSocial / Psicossocial",IF(O8="Receita recorrente","Carteira recorrente","Projetos / Laudos / Avulsos")))) | Q8: =IF(P8="","",IF(P8="Carteira recorrente","Operação recorrente",IF(P8="PCMSO","Projetos PCMSO",IF(P8="eSocial / Psicossocial","Projetos eSocial/Psicossocial","Projetos / Laudos / Avulsos")))) | R8: =IF(C8="","",IF(ISNUMBER(SEARCH("PCMSO",C8)),"Título com PCMSO no nome",IF(OR(ISNUMBER(SEARCH("E-SOCIAL",C8)),ISNUMBER(SEARCH("PSICOSOCIAL",C8))),"Título com eSocial/Psicossocial no nome",IF(O8="Receita recorrente","Tipo DRE recorrente","Extra sem palavra-chave específica")))) | S8: =IFERROR(VLOOKUP($A8,'13. Mapa Títulos-Receita'!$A$8:$P$1000,4,FALSE),"") | T8: =IFERROR(VLOOKUP($A8,'13. Mapa Títulos-Receita'!$A$8:$P$1000,5,FALSE),"") | U8: =IFERROR(VLOOKUP($A8,'13. Mapa Títulos-Receita'!$A$8:$P$1000,6,FALSE),"") | V8: =IFERROR(VLOOKUP($A8,'13. Mapa Títulos-Receita'!$A$8:$P$1000,7,FALSE),"") | W8: =IFERROR(VLOOKUP($A8,'13. Mapa Títulos-Receita'!$A$8:$P$1000,8,FALSE),"") | X8: =IFERROR(VLOOKUP($A8,'13. Mapa Títulos-Receita'!$A$8:$P$1000,9,FALSE),"") | Y8: =IFERROR(VLOOKUP($A8,'13. Mapa Títulos-Receita'!$A$8:$P$1000,10,FALSE),"") | Z8: =IFERROR(VLOOKUP($A8,'13. Mapa Títulos-Receita'!$A$8:$P$1000,11,FALSE),"") | AA8: =IFERROR(VLOOKUP($A8,'13. Mapa Títulos-Receita'!$A$8:$P$1000,12,FALSE),"") | AB8: =IFERROR(VLOOKUP($A8,'13. Mapa Títulos-Receita'!$A$8:$P$1000,13,FALSE),"") | AC8: =IFERROR(VLOOKUP($A8,'13. Mapa Títulos-Receita'!$A$8:$P$1000,14,FALSE),"") | AD8: =IFERROR(VLOOKUP($A8,'13. Mapa Títulos-Receita'!$A$8:$P$1000,15,FALSE),"") | AE8: =IFERROR(VLOOKUP($A8,'13. Mapa Títulos-Receita'!$A$8:$P$1000,16,FALSE),"")
A9: CR-002 | B9: NIVALMAG - FAZENDA | C9: NIVALMAG - FAZENDA | D9: 46086 | E9: 46086 | F9: 46087 | H9: 284 | I9: 284 | J9: Recebido | K9: =IF(J9="","",IF(OR(J9="Recebido",F9=""),MAX(0,F9-E9),MAX(0,$B$4-E9))) | L9: =IF(K9="","",IF(K9=0,"Em dia",IF(K9<=30,"1-30 dias",IF(K9<=60,"31-60 dias",IF(K9<=90,"61-90 dias",">90 dias"))))) | M9: Origem: CR mar/2026. Tipo original: Fixo. Doc/NF: 84. | N9: 46082 | O9: Receita recorrente | P9: =IF(C9="","",IF(ISNUMBER(SEARCH("PCMSO",C9)),"PCMSO",IF(OR(ISNUMBER(SEARCH("E-SOCIAL",C9)),ISNUMBER(SEARCH("PSICOSOCIAL",C9))),"eSocial / Psicossocial",IF(O9="Receita recorrente","Carteira recorrente","Projetos / Laudos / Avulsos")))) | Q9: =IF(P9="","",IF(P9="Carteira recorrente","Operação recorrente",IF(P9="PCMSO","Projetos PCMSO",IF(P9="eSocial / Psicossocial","Projetos eSocial/Psicossocial","Projetos / Laudos / Avulsos")))) | R9: =IF(C9="","",IF(ISNUMBER(SEARCH("PCMSO",C9)),"Título com PCMSO no nome",IF(OR(ISNUMBER(SEARCH("E-SOCIAL",C9)),ISNUMBER(SEARCH("PSICOSOCIAL",C9))),"Título com eSocial/Psicossocial no nome",IF(O9="Receita recorrente","Tipo DRE recorrente","Extra sem palavra-chave específica")))) | S9: =IFERROR(VLOOKUP($A9,'13. Mapa Títulos-Receita'!$A$8:$P$1000,4,FALSE),"") | T9: =IFERROR(VLOOKUP($A9,'13. Mapa Títulos-Receita'!$A$8:$P$1000,5,FALSE),"") | U9: =IFERROR(VLOOKUP($A9,'13. Mapa Títulos-Receita'!$A$8:$P$1000,6,FALSE),"") | V9: =IFERROR(VLOOKUP($A9,'13. Mapa Títulos-Receita'!$A$8:$P$1000,7,FALSE),"") | W9: =IFERROR(VLOOKUP($A9,'13. Mapa Títulos-Receita'!$A$8:$P$1000,8,FALSE),"") | X9: =IFERROR(VLOOKUP($A9,'13. Mapa Títulos-Receita'!$A$8:$P$1000,9,FALSE),"") | Y9: =IFERROR(VLOOKUP($A9,'13. Mapa Títulos-Receita'!$A$8:$P$1000,10,FALSE),"") | Z9: =IFERROR(VLOOKUP($A9,'13. Mapa Títulos-Receita'!$A$8:$P$1000,11,FALSE),"") | AA9: =IFERROR(VLOOKUP($A9,'13. Mapa Títulos-Receita'!$A$8:$P$1000,12,FALSE),"") | AB9: =IFERROR(VLOOKUP($A9,'13. Mapa Títulos-Receita'!$A$8:$P$1000,13,FALSE),"") | AC9: =IFERROR(VLOOKUP($A9,'13. Mapa Títulos-Receita'!$A$8:$P$1000,14,FALSE),"") | AD9: =IFERROR(VLOOKUP($A9,'13. Mapa Títulos-Receita'!$A$8:$P$1000,15,FALSE),"") | AE9: =IFERROR(VLOOKUP($A9,'13. Mapa Títulos-Receita'!$A$8:$P$1000,16,FALSE),"")
A10: CR-003 | B10: SONDOTEC | C10: SONDOTEC | D10: 46086 | E10: 46086 | F10: 46087 | H10: 960 | I10: 960 | J10: Recebido | K10: =IF(J10="","",IF(OR(J10="Recebido",F10=""),MAX(0,F10-E10),MAX(0,$B$4-E10))) | L10: =IF(K10="","",IF(K10=0,"Em dia",IF(K10<=30,"1-30 dias",IF(K10<=60,"31-60 dias",IF(K10<=90,"61-90 dias",">90 dias"))))) | M10: Origem: CR mar/2026. Tipo original: Fixo. Doc/NF: 81. | N10: 46082 | O10: Receita recorrente | P10: =IF(C10="","",IF(ISNUMBER(SEARCH("PCMSO",C10)),"PCMSO",IF(OR(ISNUMBER(SEARCH("E-SOCIAL",C10)),ISNUMBER(SEARCH("PSICOSOCIAL",C10))),"eSocial / Psicossocial",IF(O10="Receita recorrente","Carteira recorrente","Projetos / Laudos / Avulsos")))) | Q10: =IF(P10="","",IF(P10="Carteira recorrente","Operação recorrente",IF(P10="PCMSO","Projetos PCMSO",IF(P10="eSocial / Psicossocial","Projetos eSocial/Psicossocial","Projetos / Laudos / Avulsos")))) | R10: =IF(C10="","",IF(ISNUMBER(SEARCH("PCMSO",C10)),"Título com PCMSO no nome",IF(OR(ISNUMBER(SEARCH("E-SOCIAL",C10)),ISNUMBER(SEARCH("PSICOSOCIAL",C10))),"Título com eSocial/Psicossocial no nome",IF(O10="Receita recorrente","Tipo DRE recorrente","Extra sem palavra-chave específica")))) | S10: =IFERROR(VLOOKUP($A10,'13. Mapa Títulos-Receita'!$A$8:$P$1000,4,FALSE),"") | T10: =IFERROR(VLOOKUP($A10,'13. Mapa Títulos-Receita'!$A$8:$P$1000,5,FALSE),"") | U10: =IFERROR(VLOOKUP($A10,'13. Mapa Títulos-Receita'!$A$8:$P$1000,6,FALSE),"") | V10: =IFERROR(VLOOKUP($A10,'13. Mapa Títulos-Receita'!$A$8:$P$1000,7,FALSE),"") | W10: =IFERROR(VLOOKUP($A10,'13. Mapa Títulos-Receita'!$A$8:$P$1000,8,FALSE),"") | X10: =IFERROR(VLOOKUP($A10,'13. Mapa Títulos-Receita'!$A$8:$P$1000,9,FALSE),"") | Y10: =IFERROR(VLOOKUP($A10,'13. Mapa Títulos-Receita'!$A$8:$P$1000,10,FALSE),"") | Z10: =IFERROR(VLOOKUP($A10,'13. Mapa Títulos-Receita'!$A$8:$P$1000,11,FALSE),"") | AA10: =IFERROR(VLOOKUP($A10,'13. Mapa Títulos-Receita'!$A$8:$P$1000,12,FALSE),"") | AB10: =IFERROR(VLOOKUP($A10,'13. Mapa Títulos-Receita'!$A$8:$P$1000,13,FALSE),"") | AC10: =IFERROR(VLOOKUP($A10,'13. Mapa Títulos-Receita'!$A$8:$P$1000,14,FALSE),"") | AD10: =IFERROR(VLOOKUP($A10,'13. Mapa Títulos-Receita'!$A$8:$P$1000,15,FALSE),"") | AE10: =IFERROR(VLOOKUP($A10,'13. Mapa Títulos-Receita'!$A$8:$P$1000,16,FALSE),"")
A11: CR-004 | B11: TRIÂNGULO SERVIÇOS | C11: TRIÂNGULO SERVIÇOS | D11: 46086 | E11: 46086 | F11: 46087 | H11: 477 | I11: 477 | J11: Recebido | K11: =IF(J11="","",IF(OR(J11="Recebido",F11=""),MAX(0,F11-E11),MAX(0,$B$4-E11))) | L11: =IF(K11="","",IF(K11=0,"Em dia",IF(K11<=30,"1-30 dias",IF(K11<=60,"31-60 dias",IF(K11<=90,"61-90 dias",">90 dias"))))) | M11: Origem: CR mar/2026. Tipo original: Fixo. Doc/NF: 80. | N11: 46082 | O11: Receita recorrente | P11: =IF(C11="","",IF(ISNUMBER(SEARCH("PCMSO",C11)),"PCMSO",IF(OR(ISNUMBER(SEARCH("E-SOCIAL",C11)),ISNUMBER(SEARCH("PSICOSOCIAL",C11))),"eSocial / Psicossocial",IF(O11="Receita recorrente","Carteira recorrente","Projetos / Laudos / Avulsos")))) | Q11: =IF(P11="","",IF(P11="Carteira recorrente","Operação recorrente",IF(P11="PCMSO","Projetos PCMSO",IF(P11="eSocial / Psicossocial","Projetos eSocial/Psicossocial","Projetos / Laudos / Avulsos")))) | R11: =IF(C11="","",IF(ISNUMBER(SEARCH("PCMSO",C11)),"Título com PCMSO no nome",IF(OR(ISNUMBER(SEARCH("E-SOCIAL",C11)),ISNUMBER(SEARCH("PSICOSOCIAL",C11))),"Título com eSocial/Psicossocial no nome",IF(O11="Receita recorrente","Tipo DRE recorrente","Extra sem palavra-chave específica")))) | S11: =IFERROR(VLOOKUP($A11,'13. Mapa Títulos-Receita'!$A$8:$P$1000,4,FALSE),"") | T11: =IFERROR(VLOOKUP($A11,'13. Mapa Títulos-Receita'!$A$8:$P$1000,5,FALSE),"") | U11: =IFERROR(VLOOKUP($A11,'13. Mapa Títulos-Receita'!$A$8:$P$1000,6,FALSE),"") | V11: =IFERROR(VLOOKUP($A11,'13. Mapa Títulos-Receita'!$A$8:$P$1000,7,FALSE),"") | W11: =IFERROR(VLOOKUP($A11,'13. Mapa Títulos-Receita'!$A$8:$P$1000,8,FALSE),"") | X11: =IFERROR(VLOOKUP($A11,'13. Mapa Títulos-Receita'!$A$8:$P$1000,9,FALSE),"") | Y11: =IFERROR(VLOOKUP($A11,'13. Mapa Títulos-Receita'!$A$8:$P$1000,10,FALSE),"") | Z11: =IFERROR(VLOOKUP($A11,'13. Mapa Títulos-Receita'!$A$8:$P$1000,11,FALSE),"") | AA11: =IFERROR(VLOOKUP($A11,'13. Mapa Títulos-Receita'!$A$8:$P$1000,12,FALSE),"") | AB11: =IFERROR(VLOOKUP($A11,'13. Mapa Títulos-Receita'!$A$8:$P$1000,13,FALSE),"") | AC11: =IFERROR(VLOOKUP($A11,'13. Mapa Títulos-Receita'!$A$8:$P$1000,14,FALSE),"") | AD11: =IFERROR(VLOOKUP($A11,'13. Mapa Títulos-Receita'!$A$8:$P$1000,15,FALSE),"") | AE11: =IFERROR(VLOOKUP($A11,'13. Mapa Títulos-Receita'!$A$8:$P$1000,16,FALSE),"")
A12: CR-005 | B12: CONTROLER | C12: CONTROLER | D12: 46086 | E12: 46086 | F12: 46098 | H12: 374 | I12: 374 | J12: Recebido | K12: =IF(J12="","",IF(OR(J12="Recebido",F12=""),MAX(0,F12-E12),MAX(0,$B$4-E12))) | L12: =IF(K12="","",IF(K12=0,"Em dia",IF(K12<=30,"1-30 dias",IF(K12<=60,"31-60 dias",IF(K12<=90,"61-90 dias",">90 dias"))))) | M12: Origem: CR mar/2026. Tipo original: Fixo. Doc/NF: 82. | N12: 46082 | O12: Receita recorrente | P12: =IF(C12="","",IF(ISNUMBER(SEARCH("PCMSO",C12)),"PCMSO",IF(OR(ISNUMBER(SEARCH("E-SOCIAL",C12)),ISNUMBER(SEARCH("PSICOSOCIAL",C12))),"eSocial / Psicossocial",IF(O12="Receita recorrente","Carteira recorrente","Projetos / Laudos / Avulsos")))) | Q12: =IF(P12="","",IF(P12="Carteira recorrente","Operação recorrente",IF(P12="PCMSO","Projetos PCMSO",IF(P12="eSocial / Psicossocial","Projetos eSocial/Psicossocial","Projetos / Laudos / Avulsos")))) | R12: =IF(C12="","",IF(ISNUMBER(SEARCH("PCMSO",C12)),"Título com PCMSO no nome",IF(OR(ISNUMBER(SEARCH("E-SOCIAL",C12)),ISNUMBER(SEARCH("PSICOSOCIAL",C12))),"Título com eSocial/Psicossocial no nome",IF(O12="Receita recorrente","Tipo DRE recorrente","Extra sem palavra-chave específica")))) | S12: =IFERROR(VLOOKUP($A12,'13. Mapa Títulos-Receita'!$A$8:$P$1000,4,FALSE),"") | T12: =IFERROR(VLOOKUP($A12,'13. Mapa Títulos-Receita'!$A$8:$P$1000,5,FALSE),"") | U12: =IFERROR(VLOOKUP($A12,'13. Mapa Títulos-Receita'!$A$8:$P$1000,6,FALSE),"") | V12: =IFERROR(VLOOKUP($A12,'13. Mapa Títulos-Receita'!$A$8:$P$1000,7,FALSE),"") | W12: =IFERROR(VLOOKUP($A12,'13. Mapa Títulos-Receita'!$A$8:$P$1000,8,FALSE),"") | X12: =IFERROR(VLOOKUP($A12,'13. Mapa Títulos-Receita'!$A$8:$P$1000,9,FALSE),"") | Y12: =IFERROR(VLOOKUP($A12,'13. Mapa Títulos-Receita'!$A$8:$P$1000,10,FALSE),"") | Z12: =IFERROR(VLOOKUP($A12,'13. Mapa Títulos-Receita'!$A$8:$P$1000,11,FALSE),"") | AA12: =IFERROR(VLOOKUP($A12,'13. Mapa Títulos-Receita'!$A$8:$P$1000,12,FALSE),"") | AB12: =IFERROR(VLOOKUP($A12,'13. Mapa Títulos-Receita'!$A$8:$P$1000,13,FALSE),"") | AC12: =IFERROR(VLOOKUP($A12,'13. Mapa Títulos-Receita'!$A$8:$P$1000,14,FALSE),"") | AD12: =IFERROR(VLOOKUP($A12,'13. Mapa Títulos-Receita'!$A$8:$P$1000,15,FALSE),"") | AE12: =IFERROR(VLOOKUP($A12,'13. Mapa Títulos-Receita'!$A$8:$P$1000,16,FALSE),"")
A13: CR-006 | B13: SANTA CASA MT ALEGRE | C13: SANTA CASA MT ALEGRE | D13: 46086 | E13: 46086 | F13: 46085 | H13: 1588 | I13: 1588 | J13: Recebido | K13: =IF(J13="","",IF(OR(J13="Recebido",F13=""),MAX(0,F13-E13),MAX(0,$B$4-E13))) | L13: =IF(K13="","",IF(K13=0,"Em dia",IF(K13<=30,"1-30 dias",IF(K13<=60,"31-60 dias",IF(K13<=90,"61-90 dias",">90 dias"))))) | M13: Origem: CR mar/2026. Tipo original: Fixo. Doc/NF: 92. | N13: 46082 | O13: Receita recorrente | P13: =IF(C13="","",IF(ISNUMBER(SEARCH("PCMSO",C13)),"PCMSO",IF(OR(ISNUMBER(SEARCH("E-SOCIAL",C13)),ISNUMBER(SEARCH("PSICOSOCIAL",C13))),"eSocial / Psicossocial",IF(O13="Receita recorrente","Carteira recorrente","Projetos / Laudos / Avulsos")))) | Q13: =IF(P13="","",IF(P13="Carteira recorrente","Operação recorrente",IF(P13="PCMSO","Projetos PCMSO",IF(P13="eSocial / Psicossocial","Projetos eSocial/Psicossocial","Projetos / Laudos / Avulsos")))) | R13: =IF(C13="","",IF(ISNUMBER(SEARCH("PCMSO",C13)),"Título com PCMSO no nome",IF(OR(ISNUMBER(SEARCH("E-SOCIAL",C13)),ISNUMBER(SEARCH("PSICOSOCIAL",C13))),"Título com eSocial/Psicossocial no nome",IF(O13="Receita recorrente","Tipo DRE recorrente","Extra sem palavra-chave específica")))) | S13: =IFERROR(VLOOKUP($A13,'13. Mapa Títulos-Receita'!$A$8:$P$1000,4,FALSE),"") | T13: =IFERROR(VLOOKUP($A13,'13. Mapa Títulos-Receita'!$A$8:$P$1000,5,FALSE),"") | U13: =IFERROR(VLOOKUP($A13,'13. Mapa Títulos-Receita'!$A$8:$P$1000,6,FALSE),"") | V13: =IFERROR(VLOOKUP($A13,'13. Mapa Títulos-Receita'!$A$8:$P$1000,7,FALSE),"") | W13: =IFERROR(VLOOKUP($A13,'13. Mapa Títulos-Receita'!$A$8:$P$1000,8,FALSE),"") | X13: =IFERROR(VLOOKUP($A13,'13. Mapa Títulos-Receita'!$A$8:$P$1000,9,FALSE),"") | Y13: =IFERROR(VLOOKUP($A13,'13. Mapa Títulos-Receita'!$A$8:$P$1000,10,FALSE),"") | Z13: =IFERROR(VLOOKUP($A13,'13. Mapa Títulos-Receita'!$A$8:$P$1000,11,FALSE),"") | AA13: =IFERROR(VLOOKUP($A13,'13. Mapa Títulos-Receita'!$A$8:$P$1000,12,FALSE),"") | AB13: =IFERROR(VLOOKUP($A13,'13. Mapa Títulos-Receita'!$A$8:$P$1000,13,FALSE),"") | AC13: =IFERROR(VLOOKUP($A13,'13. Mapa Títulos-Receita'!$A$8:$P$1000,14,FALSE),"") | AD13: =IFERROR(VLOOKUP($A13,'13. Mapa Títulos-Receita'!$A$8:$P$1000,15,FALSE),"") | AE13: =IFERROR(VLOOKUP($A13,'13. Mapa Títulos-Receita'!$A$8:$P$1000,16,FALSE),"")
A14: CR-007 | B14: FAZENDA SANTA LUCIA | C14: FAZENDA SANTA LUCIA | D14: 46086 | E14: 46086 | F14: 46087 | H14: 3166 | I14: 3166 | J14: Recebido | K14: =IF(J14="","",IF(OR(J14="Recebido",F14=""),MAX(0,F14-E14),MAX(0,$B$4-E14))) | L14: =IF(K14="","",IF(K14=0,"Em dia",IF(K14<=30,"1-30 dias",IF(K14<=60,"31-60 dias",IF(K14<=90,"61-90 dias",">90 dias"))))) | M14: Origem: CR mar/2026. Tipo original: Fixo. Doc/NF: 85. | N14: 46082 | O14: Receita recorrente | P14: =IF(C14="","",IF(ISNUMBER(SEARCH("PCMSO",C14)),"PCMSO",IF(OR(ISNUMBER(SEARCH("E-SOCIAL",C14)),ISNUMBER(SEARCH("PSICOSOCIAL",C14))),"eSocial / Psicossocial",IF(O14="Receita recorrente","Carteira recorrente","Projetos / Laudos / Avulsos")))) | Q14: =IF(P14="","",IF(P14="Carteira recorrente","Operação recorrente",IF(P14="PCMSO","Projetos PCMSO",IF(P14="eSocial / Psicossocial","Projetos eSocial/Psicossocial","Projetos / Laudos / Avulsos")))) | R14: =IF(C14="","",IF(ISNUMBER(SEARCH("PCMSO",C14)),"Título com PCMSO no nome",IF(OR(ISNUMBER(SEARCH("E-SOCIAL",C14)),ISNUMBER(SEARCH("PSICOSOCIAL",C14))),"Título com eSocial/Psicossocial no nome",IF(O14="Receita recorrente","Tipo DRE recorrente","Extra sem palavra-chave específica")))) | S14: =IFERROR(VLOOKUP($A14,'13. Mapa Títulos-Receita'!$A$8:$P$1000,4,FALSE),"") | T14: =IFERROR(VLOOKUP($A14,'13. Mapa Títulos-Receita'!$A$8:$P$1000,5,FALSE),"") | U14: =IFERROR(VLOOKUP($A14,'13. Mapa Títulos-Receita'!$A$8:$P$1000,6,FALSE),"") | V14: =IFERROR(VLOOKUP($A14,'13. Mapa Títulos-Receita'!$A$8:$P$1000,7,FALSE),"") | W14: =IFERROR(VLOOKUP($A14,'13. Mapa Títulos-Receita'!$A$8:$P$1000,8,FALSE),"") | X14: =IFERROR(VLOOKUP($A14,'13. Mapa Títulos-Receita'!$A$8:$P$1000,9,FALSE),"") | Y14: =IFERROR(VLOOKUP($A14,'13. Mapa Títulos-Receita'!$A$8:$P$1000,10,FALSE),"") | Z14: =IFERROR(VLOOKUP($A14,'13. Mapa Títulos-Receita'!$A$8:$P$1000,11,FALSE),"") | AA14: =IFERROR(VLOOKUP($A14,'13. Mapa Títulos-Receita'!$A$8:$P$1000,12,FALSE),"") | AB14: =IFERROR(VLOOKUP($A14,'13. Mapa Títulos-Receita'!$A$8:$P$1000,13,FALSE),"") | AC14: =IFERROR(VLOOKUP($A14,'13. Mapa Títulos-Receita'!$A$8:$P$1000,14,FALSE),"") | AD14: =IFERROR(VLOOKUP($A14,'13. Mapa Títulos-Receita'!$A$8:$P$1000,15,FALSE),"") | AE14: =IFERROR(VLOOKUP($A14,'13. Mapa Títulos-Receita'!$A$8:$P$1000,16,FALSE),"")
A15: CR-008 | B15: LGA MÁQUINAS | C15: LGA MÁQUINAS | D15: 46091 | E15: 46091 | F15: 46092 | H15: 210 | I15: 210 | J15: Recebido | K15: =IF(J15="","",IF(OR(J15="Recebido",F15=""),MAX(0,F15-E15),MAX(0,$B$4-E15))) | L15: =IF(K15="","",IF(K15=0,"Em dia",IF(K15<=30,"1-30 dias",IF(K15<=60,"31-60 dias",IF(K15<=90,"61-90 dias",">90 dias"))))) | M15: Origem: CR mar/2026. Tipo original: Fixo. Doc/NF: S/N. | N15: 46082 | O15: Receita recorrente | P15: =IF(C15="","",IF(ISNUMBER(SEARCH("PCMSO",C15)),"PCMSO",IF(OR(ISNUMBER(SEARCH("E-SOCIAL",C15)),ISNUMBER(SEARCH("PSICOSOCIAL",C15))),"eSocial / Psicossocial",IF(O15="Receita recorrente","Carteira recorrente","Projetos / Laudos / Avulsos")))) | Q15: =IF(P15="","",IF(P15="Carteira recorrente","Operação recorrente",IF(P15="PCMSO","Projetos PCMSO",IF(P15="eSocial / Psicossocial","Projetos eSocial/Psicossocial","Projetos / Laudos / Avulsos")))) | R15: =IF(C15="","",IF(ISNUMBER(SEARCH("PCMSO",C15)),"Título com PCMSO no nome",IF(OR(ISNUMBER(SEARCH("E-SOCIAL",C15)),ISNUMBER(SEARCH("PSICOSOCIAL",C15))),"Título com eSocial/Psicossocial no nome",IF(O15="Receita recorrente","Tipo DRE recorrente","Extra sem palavra-chave específica")))) | S15: =IFERROR(VLOOKUP($A15,'13. Mapa Títulos-Receita'!$A$8:$P$1000,4,FALSE),"") | T15: =IFERROR(VLOOKUP($A15,'13. Mapa Títulos-Receita'!$A$8:$P$1000,5,FALSE),"") | U15: =IFERROR(VLOOKUP($A15,'13. Mapa Títulos-Receita'!$A$8:$P$1000,6,FALSE),"") | V15: =IFERROR(VLOOKUP($A15,'13. Mapa Títulos-Receita'!$A$8:$P$1000,7,FALSE),"") | W15: =IFERROR(VLOOKUP($A15,'13. Mapa Títulos-Receita'!$A$8:$P$1000,8,FALSE),"") | X15: =IFERROR(VLOOKUP($A15,'13. Mapa Títulos-Receita'!$A$8:$P$1000,9,FALSE),"") | Y15: =IFERROR(VLOOKUP($A15,'13. Mapa Títulos-Receita'!$A$8:$P$1000,10,FALSE),"") | Z15: =IFERROR(VLOOKUP($A15,'13. Mapa Títulos-Receita'!$A$8:$P$1000,11,FALSE),"") | AA15: =IFERROR(VLOOKUP($A15,'13. Mapa Títulos-Receita'!$A$8:$P$1000,12,FALSE),"") | AB15: =IFERROR(VLOOKUP($A15,'13. Mapa Títulos-Receita'!$A$8:$P$1000,13,FALSE),"") | AC15: =IFERROR(VLOOKUP($A15,'13. Mapa Títulos-Receita'!$A$8:$P$1000,14,FALSE),"") | AD15: =IFERROR(VLOOKUP($A15,'13. Mapa Títulos-Receita'!$A$8:$P$1000,15,FALSE),"") | AE15: =IFERROR(VLOOKUP($A15,'13. Mapa Títulos-Receita'!$A$8:$P$1000,16,FALSE),"")
A16: CR-009 | B16: REPET | C16: REPET | D16: 46094 | E16: 46094 | F16: 46097 | H16: 1571.56 | I16: 1571.56 | J16: Recebido | K16: =IF(J16="","",IF(OR(J16="Recebido",F16=""),MAX(0,F16-E16),MAX(0,$B$4-E16))) | L16: =IF(K16="","",IF(K16=0,"Em dia",IF(K16<=30,"1-30 dias",IF(K16<=60,"31-60 dias",IF(K16<=90,"61-90 dias",">90 dias"))))) | M16: Origem: CR mar/2026. Tipo original: Fixo. Doc/NF: 109. | N16: 46082 | O16: Receita recorrente | P16: =IF(C16="","",IF(ISNUMBER(SEARCH("PCMSO",C16)),"PCMSO",IF(OR(ISNUMBER(SEARCH("E-SOCIAL",C16)),ISNUMBER(SEARCH("PSICOSOCIAL",C16))),"eSocial / Psicossocial",IF(O16="Receita recorrente","Carteira recorrente","Projetos / Laudos / Avulsos")))) | Q16: =IF(P16="","",IF(P16="Carteira recorrente","Operação recorrente",IF(P16="PCMSO","Projetos PCMSO",IF(P16="eSocial / Psicossocial","Projetos eSocial/Psicossocial","Projetos / Laudos / Avulsos")))) | R16: =IF(C16="","",IF(ISNUMBER(SEARCH("PCMSO",C16)),"Título com PCMSO no nome",IF(OR(ISNUMBER(SEARCH("E-SOCIAL",C16)),ISNUMBER(SEARCH("PSICOSOCIAL",C16))),"Título com eSocial/Psicossocial no nome",IF(O16="Receita recorrente","Tipo DRE recorrente","Extra sem palavra-chave específica")))) | S16: =IFERROR(VLOOKUP($A16,'13. Mapa Títulos-Receita'!$A$8:$P$1000,4,FALSE),"") | T16: =IFERROR(VLOOKUP($A16,'13. Mapa Títulos-Receita'!$A$8:$P$1000,5,FALSE),"") | U16: =IFERROR(VLOOKUP($A16,'13. Mapa Títulos-Receita'!$A$8:$P$1000,6,FALSE),"") | V16: =IFERROR(VLOOKUP($A16,'13. Mapa Títulos-Receita'!$A$8:$P$1000,7,FALSE),"") | W16: =IFERROR(VLOOKUP($A16,'13. Mapa Títulos-Receita'!$A$8:$P$1000,8,FALSE),"") | X16: =IFERROR(VLOOKUP($A16,'13. Mapa Títulos-Receita'!$A$8:$P$1000,9,FALSE),"") | Y16: =IFERROR(VLOOKUP($A16,'13. Mapa Títulos-Receita'!$A$8:$P$1000,10,FALSE),"") | Z16: =IFERROR(VLOOKUP($A16,'13. Mapa Títulos-Receita'!$A$8:$P$1000,11,FALSE),"") | AA16: =IFERROR(VLOOKUP($A16,'13. Mapa Títulos-Receita'!$A$8:$P$1000,12,FALSE),"") | AB16: =IFERROR(VLOOKUP($A16,'13. Mapa Títulos-Receita'!$A$8:$P$1000,13,FALSE),"") | AC16: =IFERROR(VLOOKUP($A16,'13. Mapa Títulos-Receita'!$A$8:$P$1000,14,FALSE),"") | AD16: =IFERROR(VLOOKUP($A16,'13. Mapa Títulos-Receita'!$A$8:$P$1000,15,FALSE),"") | AE16: =IFERROR(VLOOKUP($A16,'13. Mapa Títulos-Receita'!$A$8:$P$1000,16,FALSE),"")
A17: CR-010 | B17: SKAP KAP | C17: SKAP KAP | D17: 46086 | E17: 46086 | F17: 46083 | H17: 50 | I17: 50 | J17: Recebido | K17: =IF(J17="","",IF(OR(J17="Recebido",F17=""),MAX(0,F17-E17),MAX(0,$B$4-E17))) | L17: =IF(K17="","",IF(K17=0,"Em dia",IF(K17<=30,"1-30 dias",IF(K17<=60,"31-60 dias",IF(K17<=90,"61-90 dias",">90 dias"))))) | M17: Origem: CR mar/2026. Tipo original: Fixo. Doc/NF: 88. | N17: 46082 | O17: Receita recorrente | P17: =IF(C17="","",IF(ISNUMBER(SEARCH("PCMSO",C17)),"PCMSO",IF(OR(ISNUMBER(SEARCH("E-SOCIAL",C17)),ISNUMBER(SEARCH("PSICOSOCIAL",C17))),"eSocial / Psicossocial",IF(O17="Receita recorrente","Carteira recorrente","Projetos / Laudos / Avulsos")))) | Q17: =IF(P17="","",IF(P17="Carteira recorrente","Operação recorrente",IF(P17="PCMSO","Projetos PCMSO",IF(P17="eSocial / Psicossocial","Projetos eSocial/Psicossocial","Projetos / Laudos / Avulsos")))) | R17: =IF(C17="","",IF(ISNUMBER(SEARCH("PCMSO",C17)),"Título com PCMSO no nome",IF(OR(ISNUMBER(SEARCH("E-SOCIAL",C17)),ISNUMBER(SEARCH("PSICOSOCIAL",C17))),"Título com eSocial/Psicossocial no nome",IF(O17="Receita recorrente","Tipo DRE recorrente","Extra sem palavra-chave específica")))) | S17: =IFERROR(VLOOKUP($A17,'13. Mapa Títulos-Receita'!$A$8:$P$1000,4,FALSE),"") | T17: =IFERROR(VLOOKUP($A17,'13. Mapa Títulos-Receita'!$A$8:$P$1000,5,FALSE),"") | U17: =IFERROR(VLOOKUP($A17,'13. Mapa Títulos-Receita'!$A$8:$P$1000,6,FALSE),"") | V17: =IFERROR(VLOOKUP($A17,'13. Mapa Títulos-Receita'!$A$8:$P$1000,7,FALSE),"") | W17: =IFERROR(VLOOKUP($A17,'13. Mapa Títulos-Receita'!$A$8:$P$1000,8,FALSE),"") | X17: =IFERROR(VLOOKUP($A17,'13. Mapa Títulos-Receita'!$A$8:$P$1000,9,FALSE),"") | Y17: =IFERROR(VLOOKUP($A17,'13. Mapa Títulos-Receita'!$A$8:$P$1000,10,FALSE),"") | Z17: =IFERROR(VLOOKUP($A17,'13. Mapa Títulos-Receita'!$A$8:$P$1000,11,FALSE),"") | AA17: =IFERROR(VLOOKUP($A17,'13. Mapa Títulos-Receita'!$A$8:$P$1000,12,FALSE),"") | AB17: =IFERROR(VLOOKUP($A17,'13. Mapa Títulos-Receita'!$A$8:$P$1000,13,FALSE),"") | AC17: =IFERROR(VLOOKUP($A17,'13. Mapa Títulos-Receita'!$A$8:$P$1000,14,FALSE),"") | AD17: =IFERROR(VLOOKUP($A17,'13. Mapa Títulos-Receita'!$A$8:$P$1000,15,FALSE),"") | AE17: =IFERROR(VLOOKUP($A17,'13. Mapa Títulos-Receita'!$A$8:$P$1000,16,FALSE),"")
A18: CR-011 | B18: RUITHER | C18: RUITHER | D18: 46086 | E18: 46086 | F18: 46083 | H18: 50 | I18: 50 | J18: Recebido | K18: =IF(J18="","",IF(OR(J18="Recebido",F18=""),MAX(0,F18-E18),MAX(0,$B$4-E18))) | L18: =IF(K18="","",IF(K18=0,"Em dia",IF(K18<=30,"1-30 dias",IF(K18<=60,"31-60 dias",IF(K18<=90,"61-90 dias",">90 dias"))))) | M18: Origem: CR mar/2026. Tipo original: Fixo. Doc/NF: 89. | N18: 46082 | O18: Receita recorrente | P18: =IF(C18="","",IF(ISNUMBER(SEARCH("PCMSO",C18)),"PCMSO",IF(OR(ISNUMBER(SEARCH("E-SOCIAL",C18)),ISNUMBER(SEARCH("PSICOSOCIAL",C18))),"eSocial / Psicossocial",IF(O18="Receita recorrente","Carteira recorrente","Projetos / Laudos / Avulsos")))) | Q18: =IF(P18="","",IF(P18="Carteira recorrente","Operação recorrente",IF(P18="PCMSO","Projetos PCMSO",IF(P18="eSocial / Psicossocial","Projetos eSocial/Psicossocial","Projetos / Laudos / Avulsos")))) | R18: =IF(C18="","",IF(ISNUMBER(SEARCH("PCMSO",C18)),"Título com PCMSO no nome",IF(OR(ISNUMBER(SEARCH("E-SOCIAL",C18)),ISNUMBER(SEARCH("PSICOSOCIAL",C18))),"Título com eSocial/Psicossocial no nome",IF(O18="Receita recorrente","Tipo DRE recorrente","Extra sem palavra-chave específica")))) | S18: =IFERROR(VLOOKUP($A18,'13. Mapa Títulos-Receita'!$A$8:$P$1000,4,FALSE),"") | T18: =IFERROR(VLOOKUP($A18,'13. Mapa Títulos-Receita'!$A$8:$P$1000,5,FALSE),"") | U18: =IFERROR(VLOOKUP($A18,'13. Mapa Títulos-Receita'!$A$8:$P$1000,6,FALSE),"") | V18: =IFERROR(VLOOKUP($A18,'13. Mapa Títulos-Receita'!$A$8:$P$1000,7,FALSE),"") | W18: =IFERROR(VLOOKUP($A18,'13. Mapa Títulos-Receita'!$A$8:$P$1000,8,FALSE),"") | X18: =IFERROR(VLOOKUP($A18,'13. Mapa Títulos-Receita'!$A$8:$P$1000,9,FALSE),"") | Y18: =IFERROR(VLOOKUP($A18,'13. Mapa Títulos-Receita'!$A$8:$P$1000,10,FALSE),"") | Z18: =IFERROR(VLOOKUP($A18,'13. Mapa Títulos-Receita'!$A$8:$P$1000,11,FALSE),"") | AA18: =IFERROR(VLOOKUP($A18,'13. Mapa Títulos-Receita'!$A$8:$P$1000,12,FALSE),"") | AB18: =IFERROR(VLOOKUP($A18,'13. Mapa Títulos-Receita'!$A$8:$P$1000,13,FALSE),"") | AC18: =IFERROR(VLOOKUP($A18,'13. Mapa Títulos-Receita'!$A$8:$P$1000,14,FALSE),"") | AD18: =IFERROR(VLOOKUP($A18,'13. Mapa Títulos-Receita'!$A$8:$P$1000,15,FALSE),"") | AE18: =IFERROR(VLOOKUP($A18,'13. Mapa Títulos-Receita'!$A$8:$P$1000,16,FALSE),"")
A19: CR-012 | B19: S12 INCORPORAÇÃO | C19: S12 INCORPORAÇÃO | D19: 46086 | E19: 46086 | F19: 46083 | H19: 40 | I19: 40 | J19: Recebido | K19: =IF(J19="","",IF(OR(J19="Recebido",F19=""),MAX(0,F19-E19),MAX(0,$B$4-E19))) | L19: =IF(K19="","",IF(K19=0,"Em dia",IF(K19<=30,"1-30 dias",IF(K19<=60,"31-60 dias",IF(K19<=90,"61-90 dias",">90 dias"))))) | M19: Origem: CR mar/2026. Tipo original: Fixo. Doc/NF: 90. | N19: 46082 | O19: Receita recorrente | P19: =IF(C19="","",IF(ISNUMBER(SEARCH("PCMSO",C19)),"PCMSO",IF(OR(ISNUMBER(SEARCH("E-SOCIAL",C19)),ISNUMBER(SEARCH("PSICOSOCIAL",C19))),"eSocial / Psicossocial",IF(O19="Receita recorrente","Carteira recorrente","Projetos / Laudos / Avulsos")))) | Q19: =IF(P19="","",IF(P19="Carteira recorrente","Operação recorrente",IF(P19="PCMSO","Projetos PCMSO",IF(P19="eSocial / Psicossocial","Projetos eSocial/Psicossocial","Projetos / Laudos / Avulsos")))) | R19: =IF(C19="","",IF(ISNUMBER(SEARCH("PCMSO",C19)),"Título com PCMSO no nome",IF(OR(ISNUMBER(SEARCH("E-SOCIAL",C19)),ISNUMBER(SEARCH("PSICOSOCIAL",C19))),"Título com eSocial/Psicossocial no nome",IF(O19="Receita recorrente","Tipo DRE recorrente","Extra sem palavra-chave específica")))) | S19: =IFERROR(VLOOKUP($A19,'13. Mapa Títulos-Receita'!$A$8:$P$1000,4,FALSE),"") | T19: =IFERROR(VLOOKUP($A19,'13. Mapa Títulos-Receita'!$A$8:$P$1000,5,FALSE),"") | U19: =IFERROR(VLOOKUP($A19,'13. Mapa Títulos-Receita'!$A$8:$P$1000,6,FALSE),"") | V19: =IFERROR(VLOOKUP($A19,'13. Mapa Títulos-Receita'!$A$8:$P$1000,7,FALSE),"") | W19: =IFERROR(VLOOKUP($A19,'13. Mapa Títulos-Receita'!$A$8:$P$1000,8,FALSE),"") | X19: =IFERROR(VLOOKUP($A19,'13. Mapa Títulos-Receita'!$A$8:$P$1000,9,FALSE),"") | Y19: =IFERROR(VLOOKUP($A19,'13. Mapa Títulos-Receita'!$A$8:$P$1000,10,FALSE),"") | Z19: =IFERROR(VLOOKUP($A19,'13. Mapa Títulos-Receita'!$A$8:$P$1000,11,FALSE),"") | AA19: =IFERROR(VLOOKUP($A19,'13. Mapa Títulos-Receita'!$A$8:$P$1000,12,FALSE),"") | AB19: =IFERROR(VLOOKUP($A19,'13. Mapa Títulos-Receita'!$A$8:$P$1000,13,FALSE),"") | AC19: =IFERROR(VLOOKUP($A19,'13. Mapa Títulos-Receita'!$A$8:$P$1000,14,FALSE),"") | AD19: =IFERROR(VLOOKUP($A19,'13. Mapa Títulos-Receita'!$A$8:$P$1000,15,FALSE),"") | AE19: =IFERROR(VLOOKUP($A19,'13. Mapa Títulos-Receita'!$A$8:$P$1000,16,FALSE),"")
... A25: CR-018 | B25: TRANSPORTADORA RODOMEU | C25: TRANSPORTADORA RODOMEU | D25: 46096 | E25: 46096 | F25: 46097 | H25: 100 | I25: 100 | J25: Recebido | K25: =IF(J25="","",IF(OR(J25="Recebido",F25=""),MAX(0,F25-E25),MAX(0,$B$4-E25))) | L25: =IF(K25="","",IF(K25=0,"Em dia",IF(K25<=30,"1-30 dias",IF(K25<=60,"31-60 dias",IF(K25<=90,"61-90 dias",">90 dias"))))) | M25: Origem: CR mar/2026. Tipo original: Fixo. Doc/NF: 111. | N25: 46082 | O25: Receita recorrente | P25: =IF(C25="","",IF(ISNUMBER(SEARCH("PCMSO",C25)),"PCMSO",IF(OR(ISNUMBER(SEARCH("E-SOCIAL",C25)),ISNUMBER(SEARCH("PSICOSOCIAL",C25))),"eSocial / Psicossocial",IF(O25="Receita recorrente","Carteira recorrente","Projetos / Laudos / Avulsos")))) | Q25: =IF(P25="","",IF(P25="Carteira recorrente","Operação recorrente",IF(P25="PCMSO","Projetos PCMSO",IF(P25="eSocial / Psicossocial","Projetos eSocial/Psicossocial","Projetos / Laudos / Avulsos")))) | R25: =IF(C25="","",IF(ISNUMBER(SEARCH("PCMSO",C25)),"Título com PCMSO no nome",IF(OR(ISNUMBER(SEARCH("E-SOCIAL",C25)),ISNUMBER(SEARCH("PSICOSOCIAL",C25))),"Título com eSocial/Psicossocial no nome",IF(O25="Receita recorrente","Tipo DRE recorrente","Extra sem palavra-chave específica")))) | S25: =IFERROR(VLOOKUP($A25,'13. Mapa Títulos-Receita'!$A$8:$P$1000,4,FALSE),"") | T25: =IFERROR(VLOOKUP($A25,'13. Mapa Títulos-Receita'!$A$8:$P$1000,5,FALSE),"") | U25: =IFERROR(VLOOKUP($A25,'13. Mapa Títulos-Receita'!$A$8:$P$1000,6,FALSE),"") | V25: =IFERROR(VLOOKUP($A25,'13. Mapa Títulos-Receita'!$A$8:$P$1000,7,FALSE),"") | W25: =IFERROR(VLOOKUP($A25,'13. Mapa Títulos-Receita'!$A$8:$P$1000,8,FALSE),"") | X25: =IFERROR(VLOOKUP($A25,'13. Mapa Títulos-Receita'!$A$8:$P$1000,9,FALSE),"") | Y25: =IFERROR(VLOOKUP($A25,'13. Mapa Títulos-Receita'!$A$8:$P$1000,10,FALSE),"") | Z25: =IFERROR(VLOOKUP($A25,'13. Mapa Títulos-Receita'!$A$8:$P$1000,11,FALSE),"") | AA25: =IFERROR(VLOOKUP($A25,'13. Mapa Títulos-Receita'!$A$8:$P$1000,12,FALSE),"") | AB25: =IFERROR(VLOOKUP($A25,'13. Mapa Títulos-Receita'!$A$8:$P$1000,13,FALSE),"") | AC25: =IFERROR(VLOOKUP($A25,'13. Mapa Títulos-Receita'!$A$8:$P$1000,14,FALSE),"") | AD25: =IFERROR(VLOOKUP($A25,'13. Mapa Títulos-Receita'!$A$8:$P$1000,15,FALSE),"") | AE25: =IFERROR(VLOOKUP($A25,'13. Mapa Títulos-Receita'!$A$8:$P$1000,16,FALSE),"")
A26: CR-019 | B26: AGROFORTE | C26: AGROFORTE (10/12) | D26: 46086 | E26: 46086 | F26: 46087 | G26: 10/12 | H26: 973 | I26: 973 | J26: Recebido | K26: =IF(J26="","",IF(OR(J26="Recebido",F26=""),MAX(0,F26-E26),MAX(0,$B$4-E26))) | L26: =IF(K26="","",IF(K26=0,"Em dia",IF(K26<=30,"1-30 dias",IF(K26<=60,"31-60 dias",IF(K26<=90,"61-90 dias",">90 dias"))))) | M26: Origem: CR mar/2026. Tipo original: Fixo. Doc/NF: 87. parcela 10/12 | N26: 46082 | O26: Receita recorrente | P26: =IF(C26="","",IF(ISNUMBER(SEARCH("PCMSO",C26)),"PCMSO",IF(OR(ISNUMBER(SEARCH("E-SOCIAL",C26)),ISNUMBER(SEARCH("PSICOSOCIAL",C26))),"eSocial / Psicossocial",IF(O26="Receita recorrente","Carteira recorrente","Projetos / Laudos / Avulsos")))) | Q26: =IF(P26="","",IF(P26="Carteira recorrente","Operação recorrente",IF(P26="PCMSO","Projetos PCMSO",IF(P26="eSocial / Psicossocial","Projetos eSocial/Psicossocial","Projetos / Laudos / Avulsos")))) | R26: =IF(C26="","",IF(ISNUMBER(SEARCH("PCMSO",C26)),"Título com PCMSO no nome",IF(OR(ISNUMBER(SEARCH("E-SOCIAL",C26)),ISNUMBER(SEARCH("PSICOSOCIAL",C26))),"Título com eSocial/Psicossocial no nome",IF(O26="Receita recorrente","Tipo DRE recorrente","Extra sem palavra-chave específica")))) | S26: =IFERROR(VLOOKUP($A26,'13. Mapa Títulos-Receita'!$A$8:$P$1000,4,FALSE),"") | T26: =IFERROR(VLOOKUP($A26,'13. Mapa Títulos-Receita'!$A$8:$P$1000,5,FALSE),"") | U26: =IFERROR(VLOOKUP($A26,'13. Mapa Títulos-Receita'!$A$8:$P$1000,6,FALSE),"") | V26: =IFERROR(VLOOKUP($A26,'13. Mapa Títulos-Receita'!$A$8:$P$1000,7,FALSE),"") | W26: =IFERROR(VLOOKUP($A26,'13. Mapa Títulos-Receita'!$A$8:$P$1000,8,FALSE),"") | X26: =IFERROR(VLOOKUP($A26,'13. Mapa Títulos-Receita'!$A$8:$P$1000,9,FALSE),"") | Y26: =IFERROR(VLOOKUP($A26,'13. Mapa Títulos-Receita'!$A$8:$P$1000,10,FALSE),"") | Z26: =IFERROR(VLOOKUP($A26,'13. Mapa Títulos-Receita'!$A$8:$P$1000,11,FALSE),"") | AA26: =IFERROR(VLOOKUP($A26,'13. Mapa Títulos-Receita'!$A$8:$P$1000,12,FALSE),"") | AB26: =IFERROR(VLOOKUP($A26,'13. Mapa Títulos-Receita'!$A$8:$P$1000,13,FALSE),"") | AC26: =IFERROR(VLOOKUP($A26,'13. Mapa Títulos-Receita'!$A$8:$P$1000,14,FALSE),"") | AD26: =IFERROR(VLOOKUP($A26,'13. Mapa Títulos-Receita'!$A$8:$P$1000,15,FALSE),"") | AE26: =IFERROR(VLOOKUP($A26,'13. Mapa Títulos-Receita'!$A$8:$P$1000,16,FALSE),"")
A27: CR-020 | B27: FAZENDAS GUARACI | C27: FAZENDAS GUARACI | D27: 46098 | E27: 46098 | F27: 46098 | H27: 140 | I27: 140 | J27: Recebido | K27: =IF(J27="","",IF(OR(J27="Recebido",F27=""),MAX(0,F27-E27),MAX(0,$B$4-E27))) | L27: =IF(K27="","",IF(K27=0,"Em dia",IF(K27<=30,"1-30 dias",IF(K27<=60,"31-60 dias",IF(K27<=90,"61-90 dias",">90 dias"))))) | M27: Origem: CR mar/2026. Tipo original: Fixo. Doc/NF: S/N. | N27: 46082 | O27: Receita recorrente | P27: =IF(C27="","",IF(ISNUMBER(SEARCH("PCMSO",C27)),"PCMSO",IF(OR(ISNUMBER(SEARCH("E-SOCIAL",C27)),ISNUMBER(SEARCH("PSICOSOCIAL",C27))),"eSocial / Psicossocial",IF(O27="Receita recorrente","Carteira recorrente","Projetos / Laudos / Avulsos")))) | Q27: =IF(P27="","",IF(P27="Carteira recorrente","Operação recorrente",IF(P27="PCMSO","Projetos PCMSO",IF(P27="eSocial / Psicossocial","Projetos eSocial/Psicossocial","Projetos / Laudos / Avulsos")))) | R27: =IF(C27="","",IF(ISNUMBER(SEARCH("PCMSO",C27)),"Título com PCMSO no nome",IF(OR(ISNUMBER(SEARCH("E-SOCIAL",C27)),ISNUMBER(SEARCH("PSICOSOCIAL",C27))),"Título com eSocial/Psicossocial no nome",IF(O27="Receita recorrente","Tipo DRE recorrente","Extra sem palavra-chave específica")))) | S27: =IFERROR(VLOOKUP($A27,'13. Mapa Títulos-Receita'!$A$8:$P$1000,4,FALSE),"") | T27: =IFERROR(VLOOKUP($A27,'13. Mapa Títulos-Receita'!$A$8:$P$1000,5,FALSE),"") | U27: =IFERROR(VLOOKUP($A27,'13. Mapa Títulos-Receita'!$A$8:$P$1000,6,FALSE),"") | V27: =IFERROR(VLOOKUP($A27,'13. Mapa Títulos-Receita'!$A$8:$P$1000,7,FALSE),"") | W27: =IFERROR(VLOOKUP($A27,'13. Mapa Títulos-Receita'!$A$8:$P$1000,8,FALSE),"") | X27: =IFERROR(VLOOKUP($A27,'13. Mapa Títulos-Receita'!$A$8:$P$1000,9,FALSE),"") | Y27: =IFERROR(VLOOKUP($A27,'13. Mapa Títulos-Receita'!$A$8:$P$1000,10,FALSE),"") | Z27: =IFERROR(VLOOKUP($A27,'13. Mapa Títulos-Receita'!$A$8:$P$1000,11,FALSE),"") | AA27: =IFERROR(VLOOKUP($A27,'13. Mapa Títulos-Receita'!$A$8:$P$1000,12,FALSE),"") | AB27: =IFERROR(VLOOKUP($A27,'13. Mapa Títulos-Receita'!$A$8:$P$1000,13,FALSE),"") | AC27: =IFERROR(VLOOKUP($A27,'13. Mapa Títulos-Receita'!$A$8:$P$1000,14,FALSE),"") | AD27: =IFERROR(VLOOKUP($A27,'13. Mapa Títulos-Receita'!$A$8:$P$1000,15,FALSE),"") | AE27: =IFERROR(VLOOKUP($A27,'13. Mapa Títulos-Receita'!$A$8:$P$1000,16,FALSE),"")
A28: CR-021 | B28: TR. LASER - INCL FUNÇÃO | C28: TR. LASER - INCL FUNÇÃO | D28: 46087 | E28: 46087 | F28: 46084 | H28: 350 | I28: 350 | J28: Recebido | K28: =IF(J28="","",IF(OR(J28="Recebido",F28=""),MAX(0,F28-E28),MAX(0,$B$4-E28))) | L28: =IF(K28="","",IF(K28=0,"Em dia",IF(K28<=30,"1-30 dias",IF(K28<=60,"31-60 dias",IF(K28<=90,"61-90 dias",">90 dias"))))) | M28: Origem: CR mar/2026. Tipo original: Extra. Doc/NF: 78. | N28: 46082 | O28: Receita extra | P28: =IF(C28="","",IF(ISNUMBER(SEARCH("PCMSO",C28)),"PCMSO",IF(OR(ISNUMBER(SEARCH("E-SOCIAL",C28)),ISNUMBER(SEARCH("PSICOSOCIAL",C28))),"eSocial / Psicossocial",IF(O28="Receita recorrente","Carteira recorrente","Projetos / Laudos / Avulsos")))) | Q28: =IF(P28="","",IF(P28="Carteira recorrente","Operação recorrente",IF(P28="PCMSO","Projetos PCMSO",IF(P28="eSocial / Psicossocial","Projetos eSocial/Psicossocial","Projetos / Laudos / Avulsos")))) | R28: =IF(C28="","",IF(ISNUMBER(SEARCH("PCMSO",C28)),"Título com PCMSO no nome",IF(OR(ISNUMBER(SEARCH("E-SOCIAL",C28)),ISNUMBER(SEARCH("PSICOSOCIAL",C28))),"Título com eSocial/Psicossocial no nome",IF(O28="Receita recorrente","Tipo DRE recorrente","Extra sem palavra-chave específica")))) | S28: =IFERROR(VLOOKUP($A28,'13. Mapa Títulos-Receita'!$A$8:$P$1000,4,FALSE),"") | T28: =IFERROR(VLOOKUP($A28,'13. Mapa Títulos-Receita'!$A$8:$P$1000,5,FALSE),"") | U28: =IFERROR(VLOOKUP($A28,'13. Mapa Títulos-Receita'!$A$8:$P$1000,6,FALSE),"") | V28: =IFERROR(VLOOKUP($A28,'13. Mapa Títulos-Receita'!$A$8:$P$1000,7,FALSE),"") | W28: =IFERROR(VLOOKUP($A28,'13. Mapa Títulos-Receita'!$A$8:$P$1000,8,FALSE),"") | X28: =IFERROR(VLOOKUP($A28,'13. Mapa Títulos-Receita'!$A$8:$P$1000,9,FALSE),"") | Y28: =IFERROR(VLOOKUP($A28,'13. Mapa Títulos-Receita'!$A$8:$P$1000,10,FALSE),"") | Z28: =IFERROR(VLOOKUP($A28,'13. Mapa Títulos-Receita'!$A$8:$P$1000,11,FALSE),"") | AA28: =IFERROR(VLOOKUP($A28,'13. Mapa Títulos-Receita'!$A$8:$P$1000,12,FALSE),"") | AB28: =IFERROR(VLOOKUP($A28,'13. Mapa Títulos-Receita'!$A$8:$P$1000,13,FALSE),"") | AC28: =IFERROR(VLOOKUP($A28,'13. Mapa Títulos-Receita'!$A$8:$P$1000,14,FALSE),"") | AD28: =IFERROR(VLOOKUP($A28,'13. Mapa Títulos-Receita'!$A$8:$P$1000,15,FALSE),"") | AE28: =IFERROR(VLOOKUP($A28,'13. Mapa Títulos-Receita'!$A$8:$P$1000,16,FALSE),"")
A29: CR-022 | B29: DPA- HUB UM 593 | C29: DPA- HUB UM 593 | D29: 46094 | E29: 46094 | F29: 46097 | H29: 800 | I29: 800 | J29: Recebido | K29: =IF(J29="","",IF(OR(J29="Recebido",F29=""),MAX(0,F29-E29),MAX(0,$B$4-E29))) | L29: =IF(K29="","",IF(K29=0,"Em dia",IF(K29<=30,"1-30 dias",IF(K29<=60,"31-60 dias",IF(K29<=90,"61-90 dias",">90 dias"))))) | M29: Origem: CR mar/2026. Tipo original: Extra. Doc/NF: 77. | N29: 46082 | O29: Receita extra | P29: =IF(C29="","",IF(ISNUMBER(SEARCH("PCMSO",C29)),"PCMSO",IF(OR(ISNUMBER(SEARCH("E-SOCIAL",C29)),ISNUMBER(SEARCH("PSICOSOCIAL",C29))),"eSocial / Psicossocial",IF(O29="Receita recorrente","Carteira recorrente","Projetos / Laudos / Avulsos")))) | Q29: =IF(P29="","",IF(P29="Carteira recorrente","Operação recorrente",IF(P29="PCMSO","Projetos PCMSO",IF(P29="eSocial / Psicossocial","Projetos eSocial/Psicossocial","Projetos / Laudos / Avulsos")))) | R29: =IF(C29="","",IF(ISNUMBER(SEARCH("PCMSO",C29)),"Título com PCMSO no nome",IF(OR(ISNUMBER(SEARCH("E-SOCIAL",C29)),ISNUMBER(SEARCH("PSICOSOCIAL",C29))),"Título com eSocial/Psicossocial no nome",IF(O29="Receita recorrente","Tipo DRE recorrente","Extra sem palavra-chave específica")))) | S29: =IFERROR(VLOOKUP($A29,'13. Mapa Títulos-Receita'!$A$8:$P$1000,4,FALSE),"") | T29: =IFERROR(VLOOKUP($A29,'13. Mapa Títulos-Receita'!$A$8:$P$1000,5,FALSE),"") | U29: =IFERROR(VLOOKUP($A29,'13. Mapa Títulos-Receita'!$A$8:$P$1000,6,FALSE),"") | V29: =IFERROR(VLOOKUP($A29,'13. Mapa Títulos-Receita'!$A$8:$P$1000,7,FALSE),"") | W29: =IFERROR(VLOOKUP($A29,'13. Mapa Títulos-Receita'!$A$8:$P$1000,8,FALSE),"") | X29: =IFERROR(VLOOKUP($A29,'13. Mapa Títulos-Receita'!$A$8:$P$1000,9,FALSE),"") | Y29: =IFERROR(VLOOKUP($A29,'13. Mapa Títulos-Receita'!$A$8:$P$1000,10,FALSE),"") | Z29: =IFERROR(VLOOKUP($A29,'13. Mapa Títulos-Receita'!$A$8:$P$1000,11,FALSE),"") | AA29: =IFERROR(VLOOKUP($A29,'13. Mapa Títulos-Receita'!$A$8:$P$1000,12,FALSE),"") | AB29: =IFERROR(VLOOKUP($A29,'13. Mapa Títulos-Receita'!$A$8:$P$1000,13,FALSE),"") | AC29: =IFERROR(VLOOKUP($A29,'13. Mapa Títulos-Receita'!$A$8:$P$1000,14,FALSE),"") | AD29: =IFERROR(VLOOKUP($A29,'13. Mapa Títulos-Receita'!$A$8:$P$1000,15,FALSE),"") | AE29: =IFERROR(VLOOKUP($A29,'13. Mapa Títulos-Receita'!$A$8:$P$1000,16,FALSE),"")
A30: CR-023 | B30: LCA - FRIGOPAIVA /FERRO VELHO | C30: LCA - FRIGOPAIVA /FERRO VELHO (1/3) | D30: 46098 | E30: 46098 | F30: 46098 | G30: 1/3 | H30: 733.33 | I30: 733.33 | J30: Recebido | K30: =IF(J30="","",IF(OR(J30="Recebido",F30=""),MAX(0,F30-E30),MAX(0,$B$4-E30))) | L30: =IF(K30="","",IF(K30=0,"Em dia",IF(K30<=30,"1-30 dias",IF(K30<=60,"31-60 dias",IF(K30<=90,"61-90 dias",">90 dias"))))) | M30: Origem: CR mar/2026. Tipo original: Extra. Doc/NF: S/N. parcela 1/3 | N30: 46082 | O30: Receita extra | P30: =IF(C30="","",IF(ISNUMBER(SEARCH("PCMSO",C30)),"PCMSO",IF(OR(ISNUMBER(SEARCH("E-SOCIAL",C30)),ISNUMBER(SEARCH("PSICOSOCIAL",C30))),"eSocial / Psicossocial",IF(O30="Receita recorrente","Carteira recorrente","Projetos / Laudos / Avulsos")))) | Q30: =IF(P30="","",IF(P30="Carteira recorrente","Operação recorrente",IF(P30="PCMSO","Projetos PCMSO",IF(P30="eSocial / Psicossocial","Projetos eSocial/Psicossocial","Projetos / Laudos / Avulsos")))) | R30: =IF(C30="","",IF(ISNUMBER(SEARCH("PCMSO",C30)),"Título com PCMSO no nome",IF(OR(ISNUMBER(SEARCH("E-SOCIAL",C30)),ISNUMBER(SEARCH("PSICOSOCIAL",C30))),"Título com eSocial/Psicossocial no nome",IF(O30="Receita recorrente","Tipo DRE recorrente","Extra sem palavra-chave específica")))) | S30: =IFERROR(VLOOKUP($A30,'13. Mapa Títulos-Receita'!$A$8:$P$1000,4,FALSE),"") | T30: =IFERROR(VLOOKUP($A30,'13. Mapa Títulos-Receita'!$A$8:$P$1000,5,FALSE),"") | U30: =IFERROR(VLOOKUP($A30,'13. Mapa Títulos-Receita'!$A$8:$P$1000,6,FALSE),"") | V30: =IFERROR(VLOOKUP($A30,'13. Mapa Títulos-Receita'!$A$8:$P$1000,7,FALSE),"") | W30: =IFERROR(VLOOKUP($A30,'13. Mapa Títulos-Receita'!$A$8:$P$1000,8,FALSE),"") | X30: =IFERROR(VLOOKUP($A30,'13. Mapa Títulos-Receita'!$A$8:$P$1000,9,FALSE),"") | Y30: =IFERROR(VLOOKUP($A30,'13. Mapa Títulos-Receita'!$A$8:$P$1000,10,FALSE),"") | Z30: =IFERROR(VLOOKUP($A30,'13. Mapa Títulos-Receita'!$A$8:$P$1000,11,FALSE),"") | AA30: =IFERROR(VLOOKUP($A30,'13. Mapa Títulos-Receita'!$A$8:$P$1000,12,FALSE),"") | AB30: =IFERROR(VLOOKUP($A30,'13. Mapa Títulos-Receita'!$A$8:$P$1000,13,FALSE),"") | AC30: =IFERROR(VLOOKUP($A30,'13. Mapa Títulos-Receita'!$A$8:$P$1000,14,FALSE),"") | AD30: =IFERROR(VLOOKUP($A30,'13. Mapa Títulos-Receita'!$A$8:$P$1000,15,FALSE),"") | AE30: =IFERROR(VLOOKUP($A30,'13. Mapa Títulos-Receita'!$A$8:$P$1000,16,FALSE),"")
A31: CR-024 | B31: MDA SOLUÇÕES | C31: MDA SOLUÇÕES (2/3) | D31: 46099 | E31: 46099 | F31: 46101 | G31: 2/3 | H31: 1855 | I31: 1855 | J31: Recebido | K31: =IF(J31="","",IF(OR(J31="Recebido",F31=""),MAX(0,F31-E31),MAX(0,$B$4-E31))) | L31: =IF(K31="","",IF(K31=0,"Em dia",IF(K31<=30,"1-30 dias",IF(K31<=60,"31-60 dias",IF(K31<=90,"61-90 dias",">90 dias"))))) | M31: Origem: CR mar/2026. Tipo original: Extra. Doc/NF: 114. parcela 2/3 | N31: 46082 | O31: Receita extra | P31: =IF(C31="","",IF(ISNUMBER(SEARCH("PCMSO",C31)),"PCMSO",IF(OR(ISNUMBER(SEARCH("E-SOCIAL",C31)),ISNUMBER(SEARCH("PSICOSOCIAL",C31))),"eSocial / Psicossocial",IF(O31="Receita recorrente","Carteira recorrente","Projetos / Laudos / Avulsos")))) | Q31: =IF(P31="","",IF(P31="Carteira recorrente","Operação recorrente",IF(P31="PCMSO","Projetos PCMSO",IF(P31="eSocial / Psicossocial","Projetos eSocial/Psicossocial","Projetos / Laudos / Avulsos")))) | R31: =IF(C31="","",IF(ISNUMBER(SEARCH("PCMSO",C31)),"Título com PCMSO no nome",IF(OR(ISNUMBER(SEARCH("E-SOCIAL",C31)),ISNUMBER(SEARCH("PSICOSOCIAL",C31))),"Título com eSocial/Psicossocial no nome",IF(O31="Receita recorrente","Tipo DRE recorrente","Extra sem palavra-chave específica")))) | S31: =IFERROR(VLOOKUP($A31,'13. Mapa Títulos-Receita'!$A$8:$P$1000,4,FALSE),"") | T31: =IFERROR(VLOOKUP($A31,'13. Mapa Títulos-Receita'!$A$8:$P$1000,5,FALSE),"") | U31: =IFERROR(VLOOKUP($A31,'13. Mapa Títulos-Receita'!$A$8:$P$1000,6,FALSE),"") | V31: =IFERROR(VLOOKUP($A31,'13. Mapa Títulos-Receita'!$A$8:$P$1000,7,FALSE),"") | W31: =IFERROR(VLOOKUP($A31,'13. Mapa Títulos-Receita'!$A$8:$P$1000,8,FALSE),"") | X31: =IFERROR(VLOOKUP($A31,'13. Mapa Títulos-Receita'!$A$8:$P$1000,9,FALSE),"") | Y31: =IFERROR(VLOOKUP($A31,'13. Mapa Títulos-Receita'!$A$8:$P$1000,10,FALSE),"") | Z31: =IFERROR(VLOOKUP($A31,'13. Mapa Títulos-Receita'!$A$8:$P$1000,11,FALSE),"") | AA31: =IFERROR(VLOOKUP($A31,'13. Mapa Títulos-Receita'!$A$8:$P$1000,12,FALSE),"") | AB31: =IFERROR(VLOOKUP($A31,'13. Mapa Títulos-Receita'!$A$8:$P$1000,13,FALSE),"") | AC31: =IFERROR(VLOOKUP($A31,'13. Mapa Títulos-Receita'!$A$8:$P$1000,14,FALSE),"") | AD31: =IFERROR(VLOOKUP($A31,'13. Mapa Títulos-Receita'!$A$8:$P$1000,15,FALSE),"") | AE31: =IFERROR(VLOOKUP($A31,'13. Mapa Títulos-Receita'!$A$8:$P$1000,16,FALSE),"")
A32: CR-025 | B32: CBA - MERC BELA VISTA/ P Olavo | C32: CBA - MERC BELA VISTA/ P Olavo | D32: 46099 | E32: 46099 | F32: 46100 | H32: 560 | I32: 560 | J32: Recebido | K32: =IF(J32="","",IF(OR(J32="Recebido",F32=""),MAX(0,F32-E32),MAX(0,$B$4-E32))) | L32: =IF(K32="","",IF(K32=0,"Em dia",IF(K32<=30,"1-30 dias",IF(K32<=60,"31-60 dias",IF(K32<=90,"61-90 dias",">90 dias"))))) | M32: Origem: CR mar/2026. Tipo original: Extra. Doc/NF: 106. | N32: 46082 | O32: Receita extra | P32: =IF(C32="","",IF(ISNUMBER(SEARCH("PCMSO",C32)),"PCMSO",IF(OR(ISNUMBER(SEARCH("E-SOCIAL",C32)),ISNUMBER(SEARCH("PSICOSOCIAL",C32))),"eSocial / Psicossocial",IF(O32="Receita recorrente","Carteira recorrente","Projetos / Laudos / Avulsos")))) | Q32: =IF(P32="","",IF(P32="Carteira recorrente","Operação recorrente",IF(P32="PCMSO","Projetos PCMSO",IF(P32="eSocial / Psicossocial","Projetos eSocial/Psicossocial","Projetos / Laudos / Avulsos")))) | R32: =IF(C32="","",IF(ISNUMBER(SEARCH("PCMSO",C32)),"Título com PCMSO no nome",IF(OR(ISNUMBER(SEARCH("E-SOCIAL",C32)),ISNUMBER(SEARCH("PSICOSOCIAL",C32))),"Título com eSocial/Psicossocial no nome",IF(O32="Receita recorrente","Tipo DRE recorrente","Extra sem palavra-chave específica")))) | S32: =IFERROR(VLOOKUP($A32,'13. Mapa Títulos-Receita'!$A$8:$P$1000,4,FALSE),"") | T32: =IFERROR(VLOOKUP($A32,'13. Mapa Títulos-Receita'!$A$8:$P$1000,5,FALSE),"") | U32: =IFERROR(VLOOKUP($A32,'13. Mapa Títulos-Receita'!$A$8:$P$1000,6,FALSE),"") | V32: =IFERROR(VLOOKUP($A32,'13. Mapa Títulos-Receita'!$A$8:$P$1000,7,FALSE),"") | W32: =IFERROR(VLOOKUP($A32,'13. Mapa Títulos-Receita'!$A$8:$P$1000,8,FALSE),"") | X32: =IFERROR(VLOOKUP($A32,'13. Mapa Títulos-Receita'!$A$8:$P$1000,9,FALSE),"") | Y32: =IFERROR(VLOOKUP($A32,'13. Mapa Títulos-Receita'!$A$8:$P$1000,10,FALSE),"") | Z32: =IFERROR(VLOOKUP($A32,'13. Mapa Títulos-Receita'!$A$8:$P$1000,11,FALSE),"") | AA32: =IFERROR(VLOOKUP($A32,'13. Mapa Títulos-Receita'!$A$8:$P$1000,12,FALSE),"") | AB32: =IFERROR(VLOOKUP($A32,'13. Mapa Títulos-Receita'!$A$8:$P$1000,13,FALSE),"") | AC32: =IFERROR(VLOOKUP($A32,'13. Mapa Títulos-Receita'!$A$8:$P$1000,14,FALSE),"") | AD32: =IFERROR(VLOOKUP($A32,'13. Mapa Títulos-Receita'!$A$8:$P$1000,15,FALSE),"") | AE32: =IFERROR(VLOOKUP($A32,'13. Mapa Títulos-Receita'!$A$8:$P$1000,16,FALSE),"")
A33: CR-026 | B33: FAZ KUENO/ ADEQ PSICOSOCIAL | C33: FAZ KUENO/ ADEQ PSICOSOCIAL | D33: 46099 | E33: 46099 | F33: 46100 | H33: 360 | I33: 360 | J33: Recebido | K33: =IF(J33="","",IF(OR(J33="Recebido",F33=""),MAX(0,F33-E33),MAX(0,$B$4-E33))) | L33: =IF(K33="","",IF(K33=0,"Em dia",IF(K33<=30,"1-30 dias",IF(K33<=60,"31-60 dias",IF(K33<=90,"61-90 dias",">90 dias"))))) | M33: Origem: CR mar/2026. Tipo original: Extra. Doc/NF: 116. | N33: 46082 | O33: Receita extra | P33: =IF(C33="","",IF(ISNUMBER(SEARCH("PCMSO",C33)),"PCMSO",IF(OR(ISNUMBER(SEARCH("E-SOCIAL",C33)),ISNUMBER(SEARCH("PSICOSOCIAL",C33))),"eSocial / Psicossocial",IF(O33="Receita recorrente","Carteira recorrente","Projetos / Laudos / Avulsos")))) | Q33: =IF(P33="","",IF(P33="Carteira recorrente","Operação recorrente",IF(P33="PCMSO","Projetos PCMSO",IF(P33="eSocial / Psicossocial","Projetos eSocial/Psicossocial","Projetos / Laudos / Avulsos")))) | R33: =IF(C33="","",IF(ISNUMBER(SEARCH("PCMSO",C33)),"Título com PCMSO no nome",IF(OR(ISNUMBER(SEARCH("E-SOCIAL",C33)),ISNUMBER(SEARCH("PSICOSOCIAL",C33))),"Título com eSocial/Psicossocial no nome",IF(O33="Receita recorrente","Tipo DRE recorrente","Extra sem palavra-chave específica")))) | S33: =IFERROR(VLOOKUP($A33,'13. Mapa Títulos-Receita'!$A$8:$P$1000,4,FALSE),"") | T33: =IFERROR(VLOOKUP($A33,'13. Mapa Títulos-Receita'!$A$8:$P$1000,5,FALSE),"") | U33: =IFERROR(VLOOKUP($A33,'13. Mapa Títulos-Receita'!$A$8:$P$1000,6,FALSE),"") | V33: =IFERROR(VLOOKUP($A33,'13. Mapa Títulos-Receita'!$A$8:$P$1000,7,FALSE),"") | W33: =IFERROR(VLOOKUP($A33,'13. Mapa Títulos-Receita'!$A$8:$P$1000,8,FALSE),"") | X33: =IFERROR(VLOOKUP($A33,'13. Mapa Títulos-Receita'!$A$8:$P$1000,9,FALSE),"") | Y33: =IFERROR(VLOOKUP($A33,'13. Mapa Títulos-Receita'!$A$8:$P$1000,10,FALSE),"") | Z33: =IFERROR(VLOOKUP($A33,'13. Mapa Títulos-Receita'!$A$8:$P$1000,11,FALSE),"") | AA33: =IFERROR(VLOOKUP($A33,'13. Mapa Títulos-Receita'!$A$8:$P$1000,12,FALSE),"") | AB33: =IFERROR(VLOOKUP($A33,'13. Mapa Títulos-Receita'!$A$8:$P$1000,13,FALSE),"") | AC33: =IFERROR(VLOOKUP($A33,'13. Mapa Títulos-Receita'!$A$8:$P$1000,14,FALSE),"") | AD33: =IFERROR(VLOOKUP($A33,'13. Mapa Títulos-Receita'!$A$8:$P$1000,15,FALSE),"") | AE33: =IFERROR(VLOOKUP($A33,'13. Mapa Títulos-Receita'!$A$8:$P$1000,16,FALSE),"")
A34: CR-027 | B34: FAZ ROBSON/ ADEQ PSICOSOCIAL | C34: FAZ ROBSON/ ADEQ PSICOSOCIAL | D34: 46099 | E34: 46099 | F34: 46100 | H34: 720 | I34: 720 | J34: Recebido | K34: =IF(J34="","",IF(OR(J34="Recebido",F34=""),MAX(0,F34-E34),MAX(0,$B$4-E34))) | L34: =IF(K34="","",IF(K34=0,"Em dia",IF(K34<=30,"1-30 dias",IF(K34<=60,"31-60 dias",IF(K34<=90,"61-90 dias",">90 dias"))))) | M34: Origem: CR mar/2026. Tipo original: Extra. Doc/NF: 117. | N34: 46082 | O34: Receita extra | P34: =IF(C34="","",IF(ISNUMBER(SEARCH("PCMSO",C34)),"PCMSO",IF(OR(ISNUMBER(SEARCH("E-SOCIAL",C34)),ISNUMBER(SEARCH("PSICOSOCIAL",C34))),"eSocial / Psicossocial",IF(O34="Receita recorrente","Carteira recorrente","Projetos / Laudos / Avulsos")))) | Q34: =IF(P34="","",IF(P34="Carteira recorrente","Operação recorrente",IF(P34="PCMSO","Projetos PCMSO",IF(P34="eSocial / Psicossocial","Projetos eSocial/Psicossocial","Projetos / Laudos / Avulsos")))) | R34: =IF(C34="","",IF(ISNUMBER(SEARCH("PCMSO",C34)),"Título com PCMSO no nome",IF(OR(ISNUMBER(SEARCH("E-SOCIAL",C34)),ISNUMBER(SEARCH("PSICOSOCIAL",C34))),"Título com eSocial/Psicossocial no nome",IF(O34="Receita recorrente","Tipo DRE recorrente","Extra sem palavra-chave específica")))) | S34: =IFERROR(VLOOKUP($A34,'13. Mapa Títulos-Receita'!$A$8:$P$1000,4,FALSE),"") | T34: =IFERROR(VLOOKUP($A34,'13. Mapa Títulos-Receita'!$A$8:$P$1000,5,FALSE),"") | U34: =IFERROR(VLOOKUP($A34,'13. Mapa Títulos-Receita'!$A$8:$P$1000,6,FALSE),"") | V34: =IFERROR(VLOOKUP($A34,'13. Mapa Títulos-Receita'!$A$8:$P$1000,7,FALSE),"") | W34: =IFERROR(VLOOKUP($A34,'13. Mapa Títulos-Receita'!$A$8:$P$1000,8,FALSE),"") | X34: =IFERROR(VLOOKUP($A34,'13. Mapa Títulos-Receita'!$A$8:$P$1000,9,FALSE),"") | Y34: =IFERROR(VLOOKUP($A34,'13. Mapa Títulos-Receita'!$A$8:$P$1000,10,FALSE),"") | Z34: =IFERROR(VLOOKUP($A34,'13. Mapa Títulos-Receita'!$A$8:$P$1000,11,FALSE),"") | AA34: =IFERROR(VLOOKUP($A34,'13. Mapa Títulos-Receita'!$A$8:$P$1000,12,FALSE),"") | AB34: =IFERROR(VLOOKUP($A34,'13. Mapa Títulos-Receita'!$A$8:$P$1000,13,FALSE),"") | AC34: =IFERROR(VLOOKUP($A34,'13. Mapa Títulos-Receita'!$A$8:$P$1000,14,FALSE),"") | AD34: =IFERROR(VLOOKUP($A34,'13. Mapa Títulos-Receita'!$A$8:$P$1000,15,FALSE),"") | AE34: =IFERROR(VLOOKUP($A34,'13. Mapa Títulos-Receita'!$A$8:$P$1000,16,FALSE),"")
A35: CR-028 | B35: DRESTE E-SOCIAL | C35: DRESTE E-SOCIAL | D35: 46099 | E35: 46099 | F35: 46094 | H35: 91 | I35: 91 | J35: Recebido | K35: =IF(J35="","",IF(OR(J35="Recebido",F35=""),MAX(0,F35-E35),MAX(0,$B$4-E35))) | L35: =IF(K35="","",IF(K35=0,"Em dia",IF(K35<=30,"1-30 dias",IF(K35<=60,"31-60 dias",IF(K35<=90,"61-90 dias",">90 dias"))))) | M35: Origem: CR mar/2026. Tipo original: Extra. Doc/NF: 115. | N35: 46082 | O35: Receita extra | P35: =IF(C35="","",IF(ISNUMBER(SEARCH("PCMSO",C35)),"PCMSO",IF(OR(ISNUMBER(SEARCH("E-SOCIAL",C35)),ISNUMBER(SEARCH("PSICOSOCIAL",C35))),"eSocial / Psicossocial",IF(O35="Receita recorrente","Carteira recorrente","Projetos / Laudos / Avulsos")))) | Q35: =IF(P35="","",IF(P35="Carteira recorrente","Operação recorrente",IF(P35="PCMSO","Projetos PCMSO",IF(P35="eSocial / Psicossocial","Projetos eSocial/Psicossocial","Projetos / Laudos / Avulsos")))) | R35: =IF(C35="","",IF(ISNUMBER(SEARCH("PCMSO",C35)),"Título com PCMSO no nome",IF(OR(ISNUMBER(SEARCH("E-SOCIAL",C35)),ISNUMBER(SEARCH("PSICOSOCIAL",C35))),"Título com eSocial/Psicossocial no nome",IF(O35="Receita recorrente","Tipo DRE recorrente","Extra sem palavra-chave específica")))) | S35: =IFERROR(VLOOKUP($A35,'13. Mapa Títulos-Receita'!$A$8:$P$1000,4,FALSE),"") | T35: =IFERROR(VLOOKUP($A35,'13. Mapa Títulos-Receita'!$A$8:$P$1000,5,FALSE),"") | U35: =IFERROR(VLOOKUP($A35,'13. Mapa Títulos-Receita'!$A$8:$P$1000,6,FALSE),"") | V35: =IFERROR(VLOOKUP($A35,'13. Mapa Títulos-Receita'!$A$8:$P$1000,7,FALSE),"") | W35: =IFERROR(VLOOKUP($A35,'13. Mapa Títulos-Receita'!$A$8:$P$1000,8,FALSE),"") | X35: =IFERROR(VLOOKUP($A35,'13. Mapa Títulos-Receita'!$A$8:$P$1000,9,FALSE),"") | Y35: =IFERROR(VLOOKUP($A35,'13. Mapa Títulos-Receita'!$A$8:$P$1000,10,FALSE),"") | Z35: =IFERROR(VLOOKUP($A35,'13. Mapa Títulos-Receita'!$A$8:$P$1000,11,FALSE),"") | AA35: =IFERROR(VLOOKUP($A35,'13. Mapa Títulos-Receita'!$A$8:$P$1000,12,FALSE),"") | AB35: =IFERROR(VLOOKUP($A35,'13. Mapa Títulos-Receita'!$A$8:$P$1000,13,FALSE),"") | AC35: =IFERROR(VLOOKUP($A35,'13. Mapa Títulos-Receita'!$A$8:$P$1000,14,FALSE),"") | AD35: =IFERROR(VLOOKUP($A35,'13. Mapa Títulos-Receita'!$A$8:$P$1000,15,FALSE),"") | AE35: =IFERROR(VLOOKUP($A35,'13. Mapa Títulos-Receita'!$A$8:$P$1000,16,FALSE),"")
A36: CR-029 | B36: AÇOFERGO | C36: AÇOFERGO (2/2) | D36: 46101 | E36: 46101 | F36: 46104 | G36: 2/2 | H36: 2170 | I36: 2170 | J36: Recebido | K36: =IF(J36="","",IF(OR(J36="Recebido",F36=""),MAX(0,F36-E36),MAX(0,$B$4-E36))) | L36: =IF(K36="","",IF(K36=0,"Em dia",IF(K36<=30,"1-30 dias",IF(K36<=60,"31-60 dias",IF(K36<=90,"61-90 dias",">90 dias"))))) | M36: Origem: CR mar/2026. Tipo original: Extra. Doc/NF: 71. parcela 2/2 | N36: 46082 | O36: Receita extra | P36: =IF(C36="","",IF(ISNUMBER(SEARCH("PCMSO",C36)),"PCMSO",IF(OR(ISNUMBER(SEARCH("E-SOCIAL",C36)),ISNUMBER(SEARCH("PSICOSOCIAL",C36))),"eSocial / Psicossocial",IF(O36="Receita recorrente","Carteira recorrente","Projetos / Laudos / Avulsos")))) | Q36: =IF(P36="","",IF(P36="Carteira recorrente","Operação recorrente",IF(P36="PCMSO","Projetos PCMSO",IF(P36="eSocial / Psicossocial","Projetos eSocial/Psicossocial","Projetos / Laudos / Avulsos")))) | R36: =IF(C36="","",IF(ISNUMBER(SEARCH("PCMSO",C36)),"Título com PCMSO no nome",IF(OR(ISNUMBER(SEARCH("E-SOCIAL",C36)),ISNUMBER(SEARCH("PSICOSOCIAL",C36))),"Título com eSocial/Psicossocial no nome",IF(O36="Receita recorrente","Tipo DRE recorrente","Extra sem palavra-chave específica")))) | S36: =IFERROR(VLOOKUP($A36,'13. Mapa Títulos-Receita'!$A$8:$P$1000,4,FALSE),"") | T36: =IFERROR(VLOOKUP($A36,'13. Mapa Títulos-Receita'!$A$8:$P$1000,5,FALSE),"") | U36: =IFERROR(VLOOKUP($A36,'13. Mapa Títulos-Receita'!$A$8:$P$1000,6,FALSE),"") | V36: =IFERROR(VLOOKUP($A36,'13. Mapa Títulos-Receita'!$A$8:$P$1000,7,FALSE),"") | W36: =IFERROR(VLOOKUP($A36,'13. Mapa Títulos-Receita'!$A$8:$P$1000,8,FALSE),"") | X36: =IFERROR(VLOOKUP($A36,'13. Mapa Títulos-Receita'!$A$8:$P$1000,9,FALSE),"") | Y36: =IFERROR(VLOOKUP($A36,'13. Mapa Títulos-Receita'!$A$8:$P$1000,10,FALSE),"") | Z36: =IFERROR(VLOOKUP($A36,'13. Mapa Títulos-Receita'!$A$8:$P$1000,11,FALSE),"") | AA36: =IFERROR(VLOOKUP($A36,'13. Mapa Títulos-Receita'!$A$8:$P$1000,12,FALSE),"") | AB36: =IFERROR(VLOOKUP($A36,'13. Mapa Títulos-Receita'!$A$8:$P$1000,13,FALSE),"") | AC36: =IFERROR(VLOOKUP($A36,'13. Mapa Títulos-Receita'!$A$8:$P$1000,14,FALSE),"") | AD36: =IFERROR(VLOOKUP($A36,'13. Mapa Títulos-Receita'!$A$8:$P$1000,15,FALSE),"") | AE36: =IFERROR(VLOOKUP($A36,'13. Mapa Títulos-Receita'!$A$8:$P$1000,16,FALSE),"")
A37: CR-030 | B37: ASSEME - ROSA GESSO | C37: ASSEME - ROSA GESSO | D37: 46101 | E37: 46101 | F37: 46099 | H37: 380 | I37: 380 | J37: Recebido | K37: =IF(J37="","",IF(OR(J37="Recebido",F37=""),MAX(0,F37-E37),MAX(0,$B$4-E37))) | L37: =IF(K37="","",IF(K37=0,"Em dia",IF(K37<=30,"1-30 dias",IF(K37<=60,"31-60 dias",IF(K37<=90,"61-90 dias",">90 dias"))))) | M37: Origem: CR mar/2026. Tipo original: Extra. Doc/NF: 107. | N37: 46082 | O37: Receita extra | P37: =IF(C37="","",IF(ISNUMBER(SEARCH("PCMSO",C37)),"PCMSO",IF(OR(ISNUMBER(SEARCH("E-SOCIAL",C37)),ISNUMBER(SEARCH("PSICOSOCIAL",C37))),"eSocial / Psicossocial",IF(O37="Receita recorrente","Carteira recorrente","Projetos / Laudos / Avulsos")))) | Q37: =IF(P37="","",IF(P37="Carteira recorrente","Operação recorrente",IF(P37="PCMSO","Projetos PCMSO",IF(P37="eSocial / Psicossocial","Projetos eSocial/Psicossocial","Projetos / Laudos / Avulsos")))) | R37: =IF(C37="","",IF(ISNUMBER(SEARCH("PCMSO",C37)),"Título com PCMSO no nome",IF(OR(ISNUMBER(SEARCH("E-SOCIAL",C37)),ISNUMBER(SEARCH("PSICOSOCIAL",C37))),"Título com eSocial/Psicossocial no nome",IF(O37="Receita recorrente","Tipo DRE recorrente","Extra sem palavra-chave específica")))) | S37: =IFERROR(VLOOKUP($A37,'13. Mapa Títulos-Receita'!$A$8:$P$1000,4,FALSE),"") | T37: =IFERROR(VLOOKUP($A37,'13. Mapa Títulos-Receita'!$A$8:$P$1000,5,FALSE),"") | U37: =IFERROR(VLOOKUP($A37,'13. Mapa Títulos-Receita'!$A$8:$P$1000,6,FALSE),"") | V37: =IFERROR(VLOOKUP($A37,'13. Mapa Títulos-Receita'!$A$8:$P$1000,7,FALSE),"") | W37: =IFERROR(VLOOKUP($A37,'13. Mapa Títulos-Receita'!$A$8:$P$1000,8,FALSE),"") | X37: =IFERROR(VLOOKUP($A37,'13. Mapa Títulos-Receita'!$A$8:$P$1000,9,FALSE),"") | Y37: =IFERROR(VLOOKUP($A37,'13. Mapa Títulos-Receita'!$A$8:$P$1000,10,FALSE),"") | Z37: =IFERROR(VLOOKUP($A37,'13. Mapa Títulos-Receita'!$A$8:$P$1000,11,FALSE),"") | AA37: =IFERROR(VLOOKUP($A37,'13. Mapa Títulos-Receita'!$A$8:$P$1000,12,FALSE),"") | AB37: =IFERROR(VLOOKUP($A37,'13. Mapa Títulos-Receita'!$A$8:$P$1000,13,FALSE),"") | AC37: =IFERROR(VLOOKUP($A37,'13. Mapa Títulos-Receita'!$A$8:$P$1000,14,FALSE),"") | AD37: =IFERROR(VLOOKUP($A37,'13. Mapa Títulos-Receita'!$A$8:$P$1000,15,FALSE),"") | AE37: =IFERROR(VLOOKUP($A37,'13. Mapa Títulos-Receita'!$A$8:$P$1000,16,FALSE),"")
A38: CR-031 | B38: ESTIVA TRANSPORTES | C38: ESTIVA TRANSPORTES (1/2) | D38: 46101 | E38: 46101 | F38: 46104 | G38: 1/2 | H38: 1434 | I38: 1434 | J38: Recebido | K38: =IF(J38="","",IF(OR(J38="Recebido",F38=""),MAX(0,F38-E38),MAX(0,$B$4-E38))) | L38: =IF(K38="","",IF(K38=0,"Em dia",IF(K38<=30,"1-30 dias",IF(K38<=60,"31-60 dias",IF(K38<=90,"61-90 dias",">90 dias"))))) | M38: Origem: CR mar/2026. Tipo original: Extra. Doc/NF: 112. parcela 1/2 | N38: 46082 | O38: Receita extra | P38: =IF(C38="","",IF(ISNUMBER(SEARCH("PCMSO",C38)),"PCMSO",IF(OR(ISNUMBER(SEARCH("E-SOCIAL",C38)),ISNUMBER(SEARCH("PSICOSOCIAL",C38))),"eSocial / Psicossocial",IF(O38="Receita recorrente","Carteira recorrente","Projetos / Laudos / Avulsos")))) | Q38: =IF(P38="","",IF(P38="Carteira recorrente","Operação recorrente",IF(P38="PCMSO","Projetos PCMSO",IF(P38="eSocial / Psicossocial","Projetos eSocial/Psicossocial","Projetos / Laudos / Avulsos")))) | R38: =IF(C38="","",IF(ISNUMBER(SEARCH("PCMSO",C38)),"Título com PCMSO no nome",IF(OR(ISNUMBER(SEARCH("E-SOCIAL",C38)),ISNUMBER(SEARCH("PSICOSOCIAL",C38))),"Título com eSocial/Psicossocial no nome",IF(O38="Receita recorrente","Tipo DRE recorrente","Extra sem palavra-chave específica")))) | S38: =IFERROR(VLOOKUP($A38,'13. Mapa Títulos-Receita'!$A$8:$P$1000,4,FALSE),"") | T38: =IFERROR(VLOOKUP($A38,'13. Mapa Títulos-Receita'!$A$8:$P$1000,5,FALSE),"") | U38: =IFERROR(VLOOKUP($A38,'13. Mapa Títulos-Receita'!$A$8:$P$1000,6,FALSE),"") | V38: =IFERROR(VLOOKUP($A38,'13. Mapa Títulos-Receita'!$A$8:$P$1000,7,FALSE),"") | W38: =IFERROR(VLOOKUP($A38,'13. Mapa Títulos-Receita'!$A$8:$P$1000,8,FALSE),"") | X38: =IFERROR(VLOOKUP($A38,'13. Mapa Títulos-Receita'!$A$8:$P$1000,9,FALSE),"") | Y38: =IFERROR(VLOOKUP($A38,'13. Mapa Títulos-Receita'!$A$8:$P$1000,10,FALSE),"") | Z38: =IFERROR(VLOOKUP($A38,'13. Mapa Títulos-Receita'!$A$8:$P$1000,11,FALSE),"") | AA38: =IFERROR(VLOOKUP($A38,'13. Mapa Títulos-Receita'!$A$8:$P$1000,12,FALSE),"") | AB38: =IFERROR(VLOOKUP($A38,'13. Mapa Títulos-Receita'!$A$8:$P$1000,13,FALSE),"") | AC38: =IFERROR(VLOOKUP($A38,'13. Mapa Títulos-Receita'!$A$8:$P$1000,14,FALSE),"") | AD38: =IFERROR(VLOOKUP($A38,'13. Mapa Títulos-Receita'!$A$8:$P$1000,15,FALSE),"") | AE38: =IFERROR(VLOOKUP($A38,'13. Mapa Títulos-Receita'!$A$8:$P$1000,16,FALSE),"")
A39: CR-032 | B39: CBA - PEDRO | C39: CBA - PEDRO | D39: 46101 | E39: 46101 | F39: 46098 | H39: 120 | I39: 120 | J39: Recebido | K39: =IF(J39="","",IF(OR(J39="Recebido",F39=""),MAX(0,F39-E39),MAX(0,$B$4-E39))) | L39: =IF(K39="","",IF(K39=0,"Em dia",IF(K39<=30,"1-30 dias",IF(K39<=60,"31-60 dias",IF(K39<=90,"61-90 dias",">90 dias"))))) | M39: Origem: CR mar/2026. Tipo original: Extra. Doc/NF: S/N. | N39: 46082 | O39: Receita extra | P39: =IF(C39="","",IF(ISNUMBER(SEARCH("PCMSO",C39)),"PCMSO",IF(OR(ISNUMBER(SEARCH("E-SOCIAL",C39)),ISNUMBER(SEARCH("PSICOSOCIAL",C39))),"eSocial / Psicossocial",IF(O39="Receita recorrente","Carteira recorrente","Projetos / Laudos / Avulsos")))) | Q39: =IF(P39="","",IF(P39="Carteira recorrente","Operação recorrente",IF(P39="PCMSO","Projetos PCMSO",IF(P39="eSocial / Psicossocial","Projetos eSocial/Psicossocial","Projetos / Laudos / Avulsos")))) | R39: =IF(C39="","",IF(ISNUMBER(SEARCH("PCMSO",C39)),"Título com PCMSO no nome",IF(OR(ISNUMBER(SEARCH("E-SOCIAL",C39)),ISNUMBER(SEARCH("PSICOSOCIAL",C39))),"Título com eSocial/Psicossocial no nome",IF(O39="Receita recorrente","Tipo DRE recorrente","Extra sem palavra-chave específica")))) | S39: =IFERROR(VLOOKUP($A39,'13. Mapa Títulos-Receita'!$A$8:$P$1000,4,FALSE),"") | T39: =IFERROR(VLOOKUP($A39,'13. Mapa Títulos-Receita'!$A$8:$P$1000,5,FALSE),"") | U39: =IFERROR(VLOOKUP($A39,'13. Mapa Títulos-Receita'!$A$8:$P$1000,6,FALSE),"") | V39: =IFERROR(VLOOKUP($A39,'13. Mapa Títulos-Receita'!$A$8:$P$1000,7,FALSE),"") | W39: =IFERROR(VLOOKUP($A39,'13. Mapa Títulos-Receita'!$A$8:$P$1000,8,FALSE),"") | X39: =IFERROR(VLOOKUP($A39,'13. Mapa Títulos-Receita'!$A$8:$P$1000,9,FALSE),"") | Y39: =IFERROR(VLOOKUP($A39,'13. Mapa Títulos-Receita'!$A$8:$P$1000,10,FALSE),"") | Z39: =IFERROR(VLOOKUP($A39,'13. Mapa Títulos-Receita'!$A$8:$P$1000,11,FALSE),"") | AA39: =IFERROR(VLOOKUP($A39,'13. Mapa Títulos-Receita'!$A$8:$P$1000,12,FALSE),"") | AB39: =IFERROR(VLOOKUP($A39,'13. Mapa Títulos-Receita'!$A$8:$P$1000,13,FALSE),"") | AC39: =IFERROR(VLOOKUP($A39,'13. Mapa Títulos-Receita'!$A$8:$P$1000,14,FALSE),"") | AD39: =IFERROR(VLOOKUP($A39,'13. Mapa Títulos-Receita'!$A$8:$P$1000,15,FALSE),"") | AE39: =IFERROR(VLOOKUP($A39,'13. Mapa Títulos-Receita'!$A$8:$P$1000,16,FALSE),"")
A40: CR-033 | B40: TRANS DAVI | C40: TRANS DAVI (1/2) | D40: 46104 | E40: 46104 | F40: 46105 | G40: 1/2 | H40: 894 | I40: 894 | J40: Recebido | K40: =IF(J40="","",IF(OR(J40="Recebido",F40=""),MAX(0,F40-E40),MAX(0,$B$4-E40))) | L40: =IF(K40="","",IF(K40=0,"Em dia",IF(K40<=30,"1-30 dias",IF(K40<=60,"31-60 dias",IF(K40<=90,"61-90 dias",">90 dias"))))) | M40: Origem: CR mar/2026. Tipo original: Extra. Doc/NF: 113. parcela 1/2 | N40: 46082 | O40: Receita extra | P40: =IF(C40="","",IF(ISNUMBER(SEARCH("PCMSO",C40)),"PCMSO",IF(OR(ISNUMBER(SEARCH("E-SOCIAL",C40)),ISNUMBER(SEARCH("PSICOSOCIAL",C40))),"eSocial / Psicossocial",IF(O40="Receita recorrente","Carteira recorrente","Projetos / Laudos / Avulsos")))) | Q40: =IF(P40="","",IF(P40="Carteira recorrente","Operação recorrente",IF(P40="PCMSO","Projetos PCMSO",IF(P40="eSocial / Psicossocial","Projetos eSocial/Psicossocial","Projetos / Laudos / Avulsos")))) | R40: =IF(C40="","",IF(ISNUMBER(SEARCH("PCMSO",C40)),"Título com PCMSO no nome",IF(OR(ISNUMBER(SEARCH("E-SOCIAL",C40)),ISNUMBER(SEARCH("PSICOSOCIAL",C40))),"Título com eSocial/Psicossocial no nome",IF(O40="Receita recorrente","Tipo DRE recorrente","Extra sem palavra-chave específica")))) | S40: =IFERROR(VLOOKUP($A40,'13. Mapa Títulos-Receita'!$A$8:$P$1000,4,FALSE),"") | T40: =IFERROR(VLOOKUP($A40,'13. Mapa Títulos-Receita'!$A$8:$P$1000,5,FALSE),"") | U40: =IFERROR(VLOOKUP($A40,'13. Mapa Títulos-Receita'!$A$8:$P$1000,6,FALSE),"") | V40: =IFERROR(VLOOKUP($A40,'13. Mapa Títulos-Receita'!$A$8:$P$1000,7,FALSE),"") | W40: =IFERROR(VLOOKUP($A40,'13. Mapa Títulos-Receita'!$A$8:$P$1000,8,FALSE),"") | X40: =IFERROR(VLOOKUP($A40,'13. Mapa Títulos-Receita'!$A$8:$P$1000,9,FALSE),"") | Y40: =IFERROR(VLOOKUP($A40,'13. Mapa Títulos-Receita'!$A$8:$P$1000,10,FALSE),"") | Z40: =IFERROR(VLOOKUP($A40,'13. Mapa Títulos-Receita'!$A$8:$P$1000,11,FALSE),"") | AA40: =IFERROR(VLOOKUP($A40,'13. Mapa Títulos-Receita'!$A$8:$P$1000,12,FALSE),"") | AB40: =IFERROR(VLOOKUP($A40,'13. Mapa Títulos-Receita'!$A$8:$P$1000,13,FALSE),"") | AC40: =IFERROR(VLOOKUP($A40,'13. Mapa Títulos-Receita'!$A$8:$P$1000,14,FALSE),"") | AD40: =IFERROR(VLOOKUP($A40,'13. Mapa Títulos-Receita'!$A$8:$P$1000,15,FALSE),"") | AE40: =IFERROR(VLOOKUP($A40,'13. Mapa Títulos-Receita'!$A$8:$P$1000,16,FALSE),"")
A41: CR-034 | B41: NDB | C41: NDB (1/3) | D41: 46104 | E41: 46104 | F41: 46105 | G41: 1/3 | H41: 2500 | I41: 2500 | J41: Recebido | K41: =IF(J41="","",IF(OR(J41="Recebido",F41=""),MAX(0,F41-E41),MAX(0,$B$4-E41))) | L41: =IF(K41="","",IF(K41=0,"Em dia",IF(K41<=30,"1-30 dias",IF(K41<=60,"31-60 dias",IF(K41<=90,"61-90 dias",">90 dias"))))) | M41: Origem: CR mar/2026. Tipo original: Extra. Doc/NF: 119. parcela 1/3 | N41: 46082 | O41: Receita extra | P41: =IF(C41="","",IF(ISNUMBER(SEARCH("PCMSO",C41)),"PCMSO",IF(OR(ISNUMBER(SEARCH("E-SOCIAL",C41)),ISNUMBER(SEARCH("PSICOSOCIAL",C41))),"eSocial / Psicossocial",IF(O41="Receita recorrente","Carteira recorrente","Projetos / Laudos / Avulsos")))) | Q41: =IF(P41="","",IF(P41="Carteira recorrente","Operação recorrente",IF(P41="PCMSO","Projetos PCMSO",IF(P41="eSocial / Psicossocial","Projetos eSocial/Psicossocial","Projetos / Laudos / Avulsos")))) | R41: =IF(C41="","",IF(ISNUMBER(SEARCH("PCMSO",C41)),"Título com PCMSO no nome",IF(OR(ISNUMBER(SEARCH("E-SOCIAL",C41)),ISNUMBER(SEARCH("PSICOSOCIAL",C41))),"Título com eSocial/Psicossocial no nome",IF(O41="Receita recorrente","Tipo DRE recorrente","Extra sem palavra-chave específica")))) | S41: =IFERROR(VLOOKUP($A41,'13. Mapa Títulos-Receita'!$A$8:$P$1000,4,FALSE),"") | T41: =IFERROR(VLOOKUP($A41,'13. Mapa Títulos-Receita'!$A$8:$P$1000,5,FALSE),"") | U41: =IFERROR(VLOOKUP($A41,'13. Mapa Títulos-Receita'!$A$8:$P$1000,6,FALSE),"") | V41: =IFERROR(VLOOKUP($A41,'13. Mapa Títulos-Receita'!$A$8:$P$1000,7,FALSE),"") | W41: =IFERROR(VLOOKUP($A41,'13. Mapa Títulos-Receita'!$A$8:$P$1000,8,FALSE),"") | X41: =IFERROR(VLOOKUP($A41,'13. Mapa Títulos-Receita'!$A$8:$P$1000,9,FALSE),"") | Y41: =IFERROR(VLOOKUP($A41,'13. Mapa Títulos-Receita'!$A$8:$P$1000,10,FALSE),"") | Z41: =IFERROR(VLOOKUP($A41,'13. Mapa Títulos-Receita'!$A$8:$P$1000,11,FALSE),"") | AA41: =IFERROR(VLOOKUP($A41,'13. Mapa Títulos-Receita'!$A$8:$P$1000,12,FALSE),"") | AB41: =IFERROR(VLOOKUP($A41,'13. Mapa Títulos-Receita'!$A$8:$P$1000,13,FALSE),"") | AC41: =IFERROR(VLOOKUP($A41,'13. Mapa Títulos-Receita'!$A$8:$P$1000,14,FALSE),"") | AD41: =IFERROR(VLOOKUP($A41,'13. Mapa Títulos-Receita'!$A$8:$P$1000,15,FALSE),"") | AE41: =IFERROR(VLOOKUP($A41,'13. Mapa Títulos-Receita'!$A$8:$P$1000,16,FALSE),"")
A42: CR-035 | B42: RETRO ESCAVAÇÕES | C42: RETRO ESCAVAÇÕES | D42: 46106 | E42: 46106 | H42: 1239 | I42: 0 | J42: Vencido | K42: =IF(J42="","",IF(OR(J42="Recebido",F42=""),MAX(0,F42-E42),MAX(0,$B$4-E42))) | L42: =IF(K42="","",IF(K42=0,"Em dia",IF(K42<=30,"1-30 dias",IF(K42<=60,"31-60 dias",IF(K42<=90,"61-90 dias",">90 dias"))))) | M42: Origem: CR mar/2026. Tipo original: Extra. Doc/NF: 79. aberto no fechamento de março Classificado como vencido pela data-base de 31/03. | N42: 46082 | O42: Receita extra | P42: =IF(C42="","",IF(ISNUMBER(SEARCH("PCMSO",C42)),"PCMSO",IF(OR(ISNUMBER(SEARCH("E-SOCIAL",C42)),ISNUMBER(SEARCH("PSICOSOCIAL",C42))),"eSocial / Psicossocial",IF(O42="Receita recorrente","Carteira recorrente","Projetos / Laudos / Avulsos")))) | Q42: =IF(P42="","",IF(P42="Carteira recorrente","Operação recorrente",IF(P42="PCMSO","Projetos PCMSO",IF(P42="eSocial / Psicossocial","Projetos eSocial/Psicossocial","Projetos / Laudos / Avulsos")))) | R42: =IF(C42="","",IF(ISNUMBER(SEARCH("PCMSO",C42)),"Título com PCMSO no nome",IF(OR(ISNUMBER(SEARCH("E-SOCIAL",C42)),ISNUMBER(SEARCH("PSICOSOCIAL",C42))),"Título com eSocial/Psicossocial no nome",IF(O42="Receita recorrente","Tipo DRE recorrente","Extra sem palavra-chave específica")))) | S42: =IFERROR(VLOOKUP($A42,'13. Mapa Títulos-Receita'!$A$8:$P$1000,4,FALSE),"") | T42: =IFERROR(VLOOKUP($A42,'13. Mapa Títulos-Receita'!$A$8:$P$1000,5,FALSE),"") | U42: =IFERROR(VLOOKUP($A42,'13. Mapa Títulos-Receita'!$A$8:$P$1000,6,FALSE),"") | V42: =IFERROR(VLOOKUP($A42,'13. Mapa Títulos-Receita'!$A$8:$P$1000,7,FALSE),"") | W42: =IFERROR(VLOOKUP($A42,'13. Mapa Títulos-Receita'!$A$8:$P$1000,8,FALSE),"") | X42: =IFERROR(VLOOKUP($A42,'13. Mapa Títulos-Receita'!$A$8:$P$1000,9,FALSE),"") | Y42: =IFERROR(VLOOKUP($A42,'13. Mapa Títulos-Receita'!$A$8:$P$1000,10,FALSE),"") | Z42: =IFERROR(VLOOKUP($A42,'13. Mapa Títulos-Receita'!$A$8:$P$1000,11,FALSE),"") | AA42: =IFERROR(VLOOKUP($A42,'13. Mapa Títulos-Receita'!$A$8:$P$1000,12,FALSE),"") | AB42: =IFERROR(VLOOKUP($A42,'13. Mapa Títulos-Receita'!$A$8:$P$1000,13,FALSE),"") | AC42: =IFERROR(VLOOKUP($A42,'13. Mapa Títulos-Receita'!$A$8:$P$1000,14,FALSE),"") | AD42: =IFERROR(VLOOKUP($A42,'13. Mapa Títulos-Receita'!$A$8:$P$1000,15,FALSE),"") | AE42: =IFERROR(VLOOKUP($A42,'13. Mapa Títulos-Receita'!$A$8:$P$1000,16,FALSE),"")
A43: CR-036 | B43: DPA - HUB / UNIDADE 593 | C43: DPA - HUB / UNIDADE 593 | D43: 46108 | E43: 46108 | H43: 800 | I43: 0 | J43: Vencido | K43: =IF(J43="","",IF(OR(J43="Recebido",F43=""),MAX(0,F43-E43),MAX(0,$B$4-E43))) | L43: =IF(K43="","",IF(K43=0,"Em dia",IF(K43<=30,"1-30 dias",IF(K43<=60,"31-60 dias",IF(K43<=90,"61-90 dias",">90 dias"))))) | M43: Origem: CR mar/2026. Tipo original: Extra. Doc/NF: 118. aberto no fechamento de março Classificado como vencido pela data-base de 31/03. | N43: 46082 | O43: Receita extra | P43: =IF(C43="","",IF(ISNUMBER(SEARCH("PCMSO",C43)),"PCMSO",IF(OR(ISNUMBER(SEARCH("E-SOCIAL",C43)),ISNUMBER(SEARCH("PSICOSOCIAL",C43))),"eSocial / Psicossocial",IF(O43="Receita recorrente","Carteira recorrente","Projetos / Laudos / Avulsos")))) | Q43: =IF(P43="","",IF(P43="Carteira recorrente","Operação recorrente",IF(P43="PCMSO","Projetos PCMSO",IF(P43="eSocial / Psicossocial","Projetos eSocial/Psicossocial","Projetos / Laudos / Avulsos")))) | R43: =IF(C43="","",IF(ISNUMBER(SEARCH("PCMSO",C43)),"Título com PCMSO no nome",IF(OR(ISNUMBER(SEARCH("E-SOCIAL",C43)),ISNUMBER(SEARCH("PSICOSOCIAL",C43))),"Título com eSocial/Psicossocial no nome",IF(O43="Receita recorrente","Tipo DRE recorrente","Extra sem palavra-chave específica")))) | S43: =IFERROR(VLOOKUP($A43,'13. Mapa Títulos-Receita'!$A$8:$P$1000,4,FALSE),"") | T43: =IFERROR(VLOOKUP($A43,'13. Mapa Títulos-Receita'!$A$8:$P$1000,5,FALSE),"") | U43: =IFERROR(VLOOKUP($A43,'13. Mapa Títulos-Receita'!$A$8:$P$1000,6,FALSE),"") | V43: =IFERROR(VLOOKUP($A43,'13. Mapa Títulos-Receita'!$A$8:$P$1000,7,FALSE),"") | W43: =IFERROR(VLOOKUP($A43,'13. Mapa Títulos-Receita'!$A$8:$P$1000,8,FALSE),"") | X43: =IFERROR(VLOOKUP($A43,'13. Mapa Títulos-Receita'!$A$8:$P$1000,9,FALSE),"") | Y43: =IFERROR(VLOOKUP($A43,'13. Mapa Títulos-Receita'!$A$8:$P$1000,10,FALSE),"") | Z43: =IFERROR(VLOOKUP($A43,'13. Mapa Títulos-Receita'!$A$8:$P$1000,11,FALSE),"") | AA43: =IFERROR(VLOOKUP($A43,'13. Mapa Títulos-Receita'!$A$8:$P$1000,12,FALSE),"") | AB43: =IFERROR(VLOOKUP($A43,'13. Mapa Títulos-Receita'!$A$8:$P$1000,13,FALSE),"") | AC43: =IFERROR(VLOOKUP($A43,'13. Mapa Títulos-Receita'!$A$8:$P$1000,14,FALSE),"") | AD43: =IFERROR(VLOOKUP($A43,'13. Mapa Títulos-Receita'!$A$8:$P$1000,15,FALSE),"") | AE43: =IFERROR(VLOOKUP($A43,'13. Mapa Títulos-Receita'!$A$8:$P$1000,16,FALSE),"")
A44: CR-037 | B44: A2B - PCMSO | C44: A2B - PCMSO | D44: 46111 | E44: 46111 | H44: 400 | I44: 0 | J44: Vencido | K44: =IF(J44="","",IF(OR(J44="Recebido",F44=""),MAX(0,F44-E44),MAX(0,$B$4-E44))) | L44: =IF(K44="","",IF(K44=0,"Em dia",IF(K44<=30,"1-30 dias",IF(K44<=60,"31-60 dias",IF(K44<=90,"61-90 dias",">90 dias"))))) | M44: Origem: CR mar/2026. Tipo original: Extra. Doc/NF: 123. aberto no fechamento de março Classificado como vencido pela data-base de 31/03. | N44: 46082 | O44: Receita extra | P44: =IF(C44="","",IF(ISNUMBER(SEARCH("PCMSO",C44)),"PCMSO",IF(OR(ISNUMBER(SEARCH("E-SOCIAL",C44)),ISNUMBER(SEARCH("PSICOSOCIAL",C44))),"eSocial / Psicossocial",IF(O44="Receita recorrente","Carteira recorrente","Projetos / Laudos / Avulsos")))) | Q44: =IF(P44="","",IF(P44="Carteira recorrente","Operação recorrente",IF(P44="PCMSO","Projetos PCMSO",IF(P44="eSocial / Psicossocial","Projetos eSocial/Psicossocial","Projetos / Laudos / Avulsos")))) | R44: =IF(C44="","",IF(ISNUMBER(SEARCH("PCMSO",C44)),"Título com PCMSO no nome",IF(OR(ISNUMBER(SEARCH("E-SOCIAL",C44)),ISNUMBER(SEARCH("PSICOSOCIAL",C44))),"Título com eSocial/Psicossocial no nome",IF(O44="Receita recorrente","Tipo DRE recorrente","Extra sem palavra-chave específica")))) | S44: =IFERROR(VLOOKUP($A44,'13. Mapa Títulos-Receita'!$A$8:$P$1000,4,FALSE),"") | T44: =IFERROR(VLOOKUP($A44,'13. Mapa Títulos-Receita'!$A$8:$P$1000,5,FALSE),"") | U44: =IFERROR(VLOOKUP($A44,'13. Mapa Títulos-Receita'!$A$8:$P$1000,6,FALSE),"") | V44: =IFERROR(VLOOKUP($A44,'13. Mapa Títulos-Receita'!$A$8:$P$1000,7,FALSE),"") | W44: =IFERROR(VLOOKUP($A44,'13. Mapa Títulos-Receita'!$A$8:$P$1000,8,FALSE),"") | X44: =IFERROR(VLOOKUP($A44,'13. Mapa Títulos-Receita'!$A$8:$P$1000,9,FALSE),"") | Y44: =IFERROR(VLOOKUP($A44,'13. Mapa Títulos-Receita'!$A$8:$P$1000,10,FALSE),"") | Z44: =IFERROR(VLOOKUP($A44,'13. Mapa Títulos-Receita'!$A$8:$P$1000,11,FALSE),"") | AA44: =IFERROR(VLOOKUP($A44,'13. Mapa Títulos-Receita'!$A$8:$P$1000,12,FALSE),"") | AB44: =IFERROR(VLOOKUP($A44,'13. Mapa Títulos-Receita'!$A$8:$P$1000,13,FALSE),"") | AC44: =IFERROR(VLOOKUP($A44,'13. Mapa Títulos-Receita'!$A$8:$P$1000,14,FALSE),"") | AD44: =IFERROR(VLOOKUP($A44,'13. Mapa Títulos-Receita'!$A$8:$P$1000,15,FALSE),"") | AE44: =IFERROR(VLOOKUP($A44,'13. Mapa Títulos-Receita'!$A$8:$P$1000,16,FALSE),"")
A45: CR-038 | B45: BOM JESUS LOCAÇÃO | C45: BOM JESUS LOCAÇÃO | D45: 46111 | E45: 46111 | H45: 1030 | I45: 0 | J45: Vencido | K45: =IF(J45="","",IF(OR(J45="Recebido",F45=""),MAX(0,F45-E45),MAX(0,$B$4-E45))) | L45: =IF(K45="","",IF(K45=0,"Em dia",IF(K45<=30,"1-30 dias",IF(K45<=60,"31-60 dias",IF(K45<=90,"61-90 dias",">90 dias"))))) | M45: Origem: CR mar/2026. Tipo original: Extra. Doc/NF: 122. aberto no fechamento de março Classificado como vencido pela data-base de 31/03. | N45: 46082 | O45: Receita extra | P45: =IF(C45="","",IF(ISNUMBER(SEARCH("PCMSO",C45)),"PCMSO",IF(OR(ISNUMBER(SEARCH("E-SOCIAL",C45)),ISNUMBER(SEARCH("PSICOSOCIAL",C45))),"eSocial / Psicossocial",IF(O45="Receita recorrente","Carteira recorrente","Projetos / Laudos / Avulsos")))) | Q45: =IF(P45="","",IF(P45="Carteira recorrente","Operação recorrente",IF(P45="PCMSO","Projetos PCMSO",IF(P45="eSocial / Psicossocial","Projetos eSocial/Psicossocial","Projetos / Laudos / Avulsos")))) | R45: =IF(C45="","",IF(ISNUMBER(SEARCH("PCMSO",C45)),"Título com PCMSO no nome",IF(OR(ISNUMBER(SEARCH("E-SOCIAL",C45)),ISNUMBER(SEARCH("PSICOSOCIAL",C45))),"Título com eSocial/Psicossocial no nome",IF(O45="Receita recorrente","Tipo DRE recorrente","Extra sem palavra-chave específica")))) | S45: =IFERROR(VLOOKUP($A45,'13. Mapa Títulos-Receita'!$A$8:$P$1000,4,FALSE),"") | T45: =IFERROR(VLOOKUP($A45,'13. Mapa Títulos-Receita'!$A$8:$P$1000,5,FALSE),"") | U45: =IFERROR(VLOOKUP($A45,'13. Mapa Títulos-Receita'!$A$8:$P$1000,6,FALSE),"") | V45: =IFERROR(VLOOKUP($A45,'13. Mapa Títulos-Receita'!$A$8:$P$1000,7,FALSE),"") | W45: =IFERROR(VLOOKUP($A45,'13. Mapa Títulos-Receita'!$A$8:$P$1000,8,FALSE),"") | X45: =IFERROR(VLOOKUP($A45,'13. Mapa Títulos-Receita'!$A$8:$P$1000,9,FALSE),"") | Y45: =IFERROR(VLOOKUP($A45,'13. Mapa Títulos-Receita'!$A$8:$P$1000,10,FALSE),"") | Z45: =IFERROR(VLOOKUP($A45,'13. Mapa Títulos-Receita'!$A$8:$P$1000,11,FALSE),"") | AA45: =IFERROR(VLOOKUP($A45,'13. Mapa Títulos-Receita'!$A$8:$P$1000,12,FALSE),"") | AB45: =IFERROR(VLOOKUP($A45,'13. Mapa Títulos-Receita'!$A$8:$P$1000,13,FALSE),"") | AC45: =IFERROR(VLOOKUP($A45,'13. Mapa Títulos-Receita'!$A$8:$P$1000,14,FALSE),"") | AD45: =IFERROR(VLOOKUP($A45,'13. Mapa Títulos-Receita'!$A$8:$P$1000,15,FALSE),"") | AE45: =IFERROR(VLOOKUP($A45,'13. Mapa Títulos-Receita'!$A$8:$P$1000,16,FALSE),"")
A46: CR-039 | B46: BOM JESUS EXTRAÇÃO | C46: BOM JESUS EXTRAÇÃO | D46: 46111 | E46: 46111 | H46: 1350 | I46: 0 | J46: Vencido | K46: =IF(J46="","",IF(OR(J46="Recebido",F46=""),MAX(0,F46-E46),MAX(0,$B$4-E46))) | L46: =IF(K46="","",IF(K46=0,"Em dia",IF(K46<=30,"1-30 dias",IF(K46<=60,"31-60 dias",IF(K46<=90,"61-90 dias",">90 dias"))))) | M46: Origem: CR mar/2026. Tipo original: Extra. Doc/NF: 126. aberto no fechamento de março Classificado como vencido pela data-base de 31/03. | N46: 46082 | O46: Receita extra | P46: =IF(C46="","",IF(ISNUMBER(SEARCH("PCMSO",C46)),"PCMSO",IF(OR(ISNUMBER(SEARCH("E-SOCIAL",C46)),ISNUMBER(SEARCH("PSICOSOCIAL",C46))),"eSocial / Psicossocial",IF(O46="Receita recorrente","Carteira recorrente","Projetos / Laudos / Avulsos")))) | Q46: =IF(P46="","",IF(P46="Carteira recorrente","Operação recorrente",IF(P46="PCMSO","Projetos PCMSO",IF(P46="eSocial / Psicossocial","Projetos eSocial/Psicossocial","Projetos / Laudos / Avulsos")))) | R46: =IF(C46="","",IF(ISNUMBER(SEARCH("PCMSO",C46)),"Título com PCMSO no nome",IF(OR(ISNUMBER(SEARCH("E-SOCIAL",C46)),ISNUMBER(SEARCH("PSICOSOCIAL",C46))),"Título com eSocial/Psicossocial no nome",IF(O46="Receita recorrente","Tipo DRE recorrente","Extra sem palavra-chave específica")))) | S46: =IFERROR(VLOOKUP($A46,'13. Mapa Títulos-Receita'!$A$8:$P$1000,4,FALSE),"") | T46: =IFERROR(VLOOKUP($A46,'13. Mapa Títulos-Receita'!$A$8:$P$1000,5,FALSE),"") | U46: =IFERROR(VLOOKUP($A46,'13. Mapa Títulos-Receita'!$A$8:$P$1000,6,FALSE),"") | V46: =IFERROR(VLOOKUP($A46,'13. Mapa Títulos-Receita'!$A$8:$P$1000,7,FALSE),"") | W46: =IFERROR(VLOOKUP($A46,'13. Mapa Títulos-Receita'!$A$8:$P$1000,8,FALSE),"") | X46: =IFERROR(VLOOKUP($A46,'13. Mapa Títulos-Receita'!$A$8:$P$1000,9,FALSE),"") | Y46: =IFERROR(VLOOKUP($A46,'13. Mapa Títulos-Receita'!$A$8:$P$1000,10,FALSE),"") | Z46: =IFERROR(VLOOKUP($A46,'13. Mapa Títulos-Receita'!$A$8:$P$1000,11,FALSE),"") | AA46: =IFERROR(VLOOKUP($A46,'13. Mapa Títulos-Receita'!$A$8:$P$1000,12,FALSE),"") | AB46: =IFERROR(VLOOKUP($A46,'13. Mapa Títulos-Receita'!$A$8:$P$1000,13,FALSE),"") | AC46: =IFERROR(VLOOKUP($A46,'13. Mapa Títulos-Receita'!$A$8:$P$1000,14,FALSE),"") | AD46: =IFERROR(VLOOKUP($A46,'13. Mapa Títulos-Receita'!$A$8:$P$1000,15,FALSE),"") | AE46: =IFERROR(VLOOKUP($A46,'13. Mapa Títulos-Receita'!$A$8:$P$1000,16,FALSE),"")
A47: CR-040 | B47: DPA - UBERABA / UNIDADE 18 | C47: DPA - UBERABA / UNIDADE 18 | D47: 46111 | E47: 46111 | H47: 1000 | I47: 0 | J47: Vencido | K47: =IF(J47="","",IF(OR(J47="Recebido",F47=""),MAX(0,F47-E47),MAX(0,$B$4-E47))) | L47: =IF(K47="","",IF(K47=0,"Em dia",IF(K47<=30,"1-30 dias",IF(K47<=60,"31-60 dias",IF(K47<=90,"61-90 dias",">90 dias"))))) | M47: Origem: CR mar/2026. Tipo original: Extra. Doc/NF: 120. aberto no fechamento de março Classificado como vencido pela data-base de 31/03. | N47: 46082 | O47: Receita extra | P47: =IF(C47="","",IF(ISNUMBER(SEARCH("PCMSO",C47)),"PCMSO",IF(OR(ISNUMBER(SEARCH("E-SOCIAL",C47)),ISNUMBER(SEARCH("PSICOSOCIAL",C47))),"eSocial / Psicossocial",IF(O47="Receita recorrente","Carteira recorrente","Projetos / Laudos / Avulsos")))) | Q47: =IF(P47="","",IF(P47="Carteira recorrente","Operação recorrente",IF(P47="PCMSO","Projetos PCMSO",IF(P47="eSocial / Psicossocial","Projetos eSocial/Psicossocial","Projetos / Laudos / Avulsos")))) | R47: =IF(C47="","",IF(ISNUMBER(SEARCH("PCMSO",C47)),"Título com PCMSO no nome",IF(OR(ISNUMBER(SEARCH("E-SOCIAL",C47)),ISNUMBER(SEARCH("PSICOSOCIAL",C47))),"Título com eSocial/Psicossocial no nome",IF(O47="Receita recorrente","Tipo DRE recorrente","Extra sem palavra-chave específica")))) | S47: =IFERROR(VLOOKUP($A47,'13. Mapa Títulos-Receita'!$A$8:$P$1000,4,FALSE),"") | T47: =IFERROR(VLOOKUP($A47,'13. Mapa Títulos-Receita'!$A$8:$P$1000,5,FALSE),"") | U47: =IFERROR(VLOOKUP($A47,'13. Mapa Títulos-Receita'!$A$8:$P$1000,6,FALSE),"") | V47: =IFERROR(VLOOKUP($A47,'13. Mapa Títulos-Receita'!$A$8:$P$1000,7,FALSE),"") | W47: =IFERROR(VLOOKUP($A47,'13. Mapa Títulos-Receita'!$A$8:$P$1000,8,FALSE),"") | X47: =IFERROR(VLOOKUP($A47,'13. Mapa Títulos-Receita'!$A$8:$P$1000,9,FALSE),"") | Y47: =IFERROR(VLOOKUP($A47,'13. Mapa Títulos-Receita'!$A$8:$P$1000,10,FALSE),"") | Z47: =IFERROR(VLOOKUP($A47,'13. Mapa Títulos-Receita'!$A$8:$P$1000,11,FALSE),"") | AA47: =IFERROR(VLOOKUP($A47,'13. Mapa Títulos-Receita'!$A$8:$P$1000,12,FALSE),"") | AB47: =IFERROR(VLOOKUP($A47,'13. Mapa Títulos-Receita'!$A$8:$P$1000,13,FALSE),"") | AC47: =IFERROR(VLOOKUP($A47,'13. Mapa Títulos-Receita'!$A$8:$P$1000,14,FALSE),"") | AD47: =IFERROR(VLOOKUP($A47,'13. Mapa Títulos-Receita'!$A$8:$P$1000,15,FALSE),"") | AE47: =IFERROR(VLOOKUP($A47,'13. Mapa Títulos-Receita'!$A$8:$P$1000,16,FALSE),"")
A48: CR-041 | B48: DPA - HUB / UNIDADE 261 | C48: DPA - HUB / UNIDADE 261 | D48: 46112 | E48: 46112 | H48: 800 | I48: 0 | J48: Aberto | K48: =IF(J48="","",IF(OR(J48="Recebido",F48=""),MAX(0,F48-E48),MAX(0,$B$4-E48))) | L48: =IF(K48="","",IF(K48=0,"Em dia",IF(K48<=30,"1-30 dias",IF(K48<=60,"31-60 dias",IF(K48<=90,"61-90 dias",">90 dias"))))) | M48: Origem: CR mar/2026. Tipo original: Extra. Doc/NF: 121. aberto no fechamento de março | N48: 46082 | O48: Receita extra | P48: =IF(C48="","",IF(ISNUMBER(SEARCH("PCMSO",C48)),"PCMSO",IF(OR(ISNUMBER(SEARCH("E-SOCIAL",C48)),ISNUMBER(SEARCH("PSICOSOCIAL",C48))),"eSocial / Psicossocial",IF(O48="Receita recorrente","Carteira recorrente","Projetos / Laudos / Avulsos")))) | Q48: =IF(P48="","",IF(P48="Carteira recorrente","Operação recorrente",IF(P48="PCMSO","Projetos PCMSO",IF(P48="eSocial / Psicossocial","Projetos eSocial/Psicossocial","Projetos / Laudos / Avulsos")))) | R48: =IF(C48="","",IF(ISNUMBER(SEARCH("PCMSO",C48)),"Título com PCMSO no nome",IF(OR(ISNUMBER(SEARCH("E-SOCIAL",C48)),ISNUMBER(SEARCH("PSICOSOCIAL",C48))),"Título com eSocial/Psicossocial no nome",IF(O48="Receita recorrente","Tipo DRE recorrente","Extra sem palavra-chave específica")))) | S48: =IFERROR(VLOOKUP($A48,'13. Mapa Títulos-Receita'!$A$8:$P$1000,4,FALSE),"") | T48: =IFERROR(VLOOKUP($A48,'13. Mapa Títulos-Receita'!$A$8:$P$1000,5,FALSE),"") | U48: =IFERROR(VLOOKUP($A48,'13. Mapa Títulos-Receita'!$A$8:$P$1000,6,FALSE),"") | V48: =IFERROR(VLOOKUP($A48,'13. Mapa Títulos-Receita'!$A$8:$P$1000,7,FALSE),"") | W48: =IFERROR(VLOOKUP($A48,'13. Mapa Títulos-Receita'!$A$8:$P$1000,8,FALSE),"") | X48: =IFERROR(VLOOKUP($A48,'13. Mapa Títulos-Receita'!$A$8:$P$1000,9,FALSE),"") | Y48: =IFERROR(VLOOKUP($A48,'13. Mapa Títulos-Receita'!$A$8:$P$1000,10,FALSE),"") | Z48: =IFERROR(VLOOKUP($A48,'13. Mapa Títulos-Receita'!$A$8:$P$1000,11,FALSE),"") | AA48: =IFERROR(VLOOKUP($A48,'13. Mapa Títulos-Receita'!$A$8:$P$1000,12,FALSE),"") | AB48: =IFERROR(VLOOKUP($A48,'13. Mapa Títulos-Receita'!$A$8:$P$1000,13,FALSE),"") | AC48: =IFERROR(VLOOKUP($A48,'13. Mapa Títulos-Receita'!$A$8:$P$1000,14,FALSE),"") | AD48: =IFERROR(VLOOKUP($A48,'13. Mapa Títulos-Receita'!$A$8:$P$1000,15,FALSE),"") | AE48: =IFERROR(VLOOKUP($A48,'13. Mapa Títulos-Receita'!$A$8:$P$1000,16,FALSE),"")
A49: CR-042 | B49: MATA DO PORTO | C49: MATA DO PORTO | D49: 46111 | E49: 46111 | H49: 858 | I49: 0 | J49: Vencido | K49: =IF(J49="","",IF(OR(J49="Recebido",F49=""),MAX(0,F49-E49),MAX(0,$B$4-E49))) | L49: =IF(K49="","",IF(K49=0,"Em dia",IF(K49<=30,"1-30 dias",IF(K49<=60,"31-60 dias",IF(K49<=90,"61-90 dias",">90 dias"))))) | M49: Origem: CR mar/2026. Tipo original: Extra. Doc/NF: 124. aberto no fechamento de março Classificado como vencido pela data-base de 31/03. | N49: 46082 | O49: Receita extra | P49: =IF(C49="","",IF(ISNUMBER(SEARCH("PCMSO",C49)),"PCMSO",IF(OR(ISNUMBER(SEARCH("E-SOCIAL",C49)),ISNUMBER(SEARCH("PSICOSOCIAL",C49))),"eSocial / Psicossocial",IF(O49="Receita recorrente","Carteira recorrente","Projetos / Laudos / Avulsos")))) | Q49: =IF(P49="","",IF(P49="Carteira recorrente","Operação recorrente",IF(P49="PCMSO","Projetos PCMSO",IF(P49="eSocial / Psicossocial","Projetos eSocial/Psicossocial","Projetos / Laudos / Avulsos")))) | R49: =IF(C49="","",IF(ISNUMBER(SEARCH("PCMSO",C49)),"Título com PCMSO no nome",IF(OR(ISNUMBER(SEARCH("E-SOCIAL",C49)),ISNUMBER(SEARCH("PSICOSOCIAL",C49))),"Título com eSocial/Psicossocial no nome",IF(O49="Receita recorrente","Tipo DRE recorrente","Extra sem palavra-chave específica")))) | S49: =IFERROR(VLOOKUP($A49,'13. Mapa Títulos-Receita'!$A$8:$P$1000,4,FALSE),"") | T49: =IFERROR(VLOOKUP($A49,'13. Mapa Títulos-Receita'!$A$8:$P$1000,5,FALSE),"") | U49: =IFERROR(VLOOKUP($A49,'13. Mapa Títulos-Receita'!$A$8:$P$1000,6,FALSE),"") | V49: =IFERROR(VLOOKUP($A49,'13. Mapa Títulos-Receita'!$A$8:$P$1000,7,FALSE),"") | W49: =IFERROR(VLOOKUP($A49,'13. Mapa Títulos-Receita'!$A$8:$P$1000,8,FALSE),"") | X49: =IFERROR(VLOOKUP($A49,'13. Mapa Títulos-Receita'!$A$8:$P$1000,9,FALSE),"") | Y49: =IFERROR(VLOOKUP($A49,'13. Mapa Títulos-Receita'!$A$8:$P$1000,10,FALSE),"") | Z49: =IFERROR(VLOOKUP($A49,'13. Mapa Títulos-Receita'!$A$8:$P$1000,11,FALSE),"") | AA49: =IFERROR(VLOOKUP($A49,'13. Mapa Títulos-Receita'!$A$8:$P$1000,12,FALSE),"") | AB49: =IFERROR(VLOOKUP($A49,'13. Mapa Títulos-Receita'!$A$8:$P$1000,13,FALSE),"") | AC49: =IFERROR(VLOOKUP($A49,'13. Mapa Títulos-Receita'!$A$8:$P$1000,14,FALSE),"") | AD49: =IFERROR(VLOOKUP($A49,'13. Mapa Títulos-Receita'!$A$8:$P$1000,15,FALSE),"") | AE49: =IFERROR(VLOOKUP($A49,'13. Mapa Títulos-Receita'!$A$8:$P$1000,16,FALSE),"")
A50: CR-043 | B50: GODOSAN | C50: GODOSAN (1/4) | D50: 46112 | E50: 46112 | G50: 1/4 | H50: 1692 | I50: 0 | J50: Aberto | K50: =IF(J50="","",IF(OR(J50="Recebido",F50=""),MAX(0,F50-E50),MAX(0,$B$4-E50))) | L50: =IF(K50="","",IF(K50=0,"Em dia",IF(K50<=30,"1-30 dias",IF(K50<=60,"31-60 dias",IF(K50<=90,"61-90 dias",">90 dias"))))) | M50: Origem: CR mar/2026. Tipo original: Extra. Doc/NF: S/N. vencimento não legível no PDF; alocado em 31/03 para reconciliar o resumo | N50: 46082 | O50: Receita extra | P50: =IF(C50="","",IF(ISNUMBER(SEARCH("PCMSO",C50)),"PCMSO",IF(OR(ISNUMBER(SEARCH("E-SOCIAL",C50)),ISNUMBER(SEARCH("PSICOSOCIAL",C50))),"eSocial / Psicossocial",IF(O50="Receita recorrente","Carteira recorrente","Projetos / Laudos / Avulsos")))) | Q50: =IF(P50="","",IF(P50="Carteira recorrente","Operação recorrente",IF(P50="PCMSO","Projetos PCMSO",IF(P50="eSocial / Psicossocial","Projetos eSocial/Psicossocial","Projetos / Laudos / Avulsos")))) | R50: =IF(C50="","",IF(ISNUMBER(SEARCH("PCMSO",C50)),"Título com PCMSO no nome",IF(OR(ISNUMBER(SEARCH("E-SOCIAL",C50)),ISNUMBER(SEARCH("PSICOSOCIAL",C50))),"Título com eSocial/Psicossocial no nome",IF(O50="Receita recorrente","Tipo DRE recorrente","Extra sem palavra-chave específica")))) | S50: =IFERROR(VLOOKUP($A50,'13. Mapa Títulos-Receita'!$A$8:$P$1000,4,FALSE),"") | T50: =IFERROR(VLOOKUP($A50,'13. Mapa Títulos-Receita'!$A$8:$P$1000,5,FALSE),"") | U50: =IFERROR(VLOOKUP($A50,'13. Mapa Títulos-Receita'!$A$8:$P$1000,6,FALSE),"") | V50: =IFERROR(VLOOKUP($A50,'13. Mapa Títulos-Receita'!$A$8:$P$1000,7,FALSE),"") | W50: =IFERROR(VLOOKUP($A50,'13. Mapa Títulos-Receita'!$A$8:$P$1000,8,FALSE),"") | X50: =IFERROR(VLOOKUP($A50,'13. Mapa Títulos-Receita'!$A$8:$P$1000,9,FALSE),"") | Y50: =IFERROR(VLOOKUP($A50,'13. Mapa Títulos-Receita'!$A$8:$P$1000,10,FALSE),"") | Z50: =IFERROR(VLOOKUP($A50,'13. Mapa Títulos-Receita'!$A$8:$P$1000,11,FALSE),"") | AA50: =IFERROR(VLOOKUP($A50,'13. Mapa Títulos-Receita'!$A$8:$P$1000,12,FALSE),"") | AB50: =IFERROR(VLOOKUP($A50,'13. Mapa Títulos-Receita'!$A$8:$P$1000,13,FALSE),"") | AC50: =IFERROR(VLOOKUP($A50,'13. Mapa Títulos-Receita'!$A$8:$P$1000,14,FALSE),"") | AD50: =IFERROR(VLOOKUP($A50,'13. Mapa Títulos-Receita'!$A$8:$P$1000,15,FALSE),"") | AE50: =IFERROR(VLOOKUP($A50,'13. Mapa Títulos-Receita'!$A$8:$P$1000,16,FALSE),"")
A51: CR-044 | B51: FERSAN | C51: FERSAN (1/4) | D51: 46112 | E51: 46112 | G51: 1/4 | H51: 1354.5 | I51: 0 | J51: Aberto | K51: =IF(J51="","",IF(OR(J51="Recebido",F51=""),MAX(0,F51-E51),MAX(0,$B$4-E51))) | L51: =IF(K51="","",IF(K51=0,"Em dia",IF(K51<=30,"1-30 dias",IF(K51<=60,"31-60 dias",IF(K51<=90,"61-90 dias",">90 dias"))))) | M51: Origem: CR mar/2026. Tipo original: Extra. Doc/NF: S/N. vencimento não legível no PDF; alocado em 31/03 para reconciliar o resumo | N51: 46082 | O51: Receita extra | P51: =IF(C51="","",IF(ISNUMBER(SEARCH("PCMSO",C51)),"PCMSO",IF(OR(ISNUMBER(SEARCH("E-SOCIAL",C51)),ISNUMBER(SEARCH("PSICOSOCIAL",C51))),"eSocial / Psicossocial",IF(O51="Receita recorrente","Carteira recorrente","Projetos / Laudos / Avulsos")))) | Q51: =IF(P51="","",IF(P51="Carteira recorrente","Operação recorrente",IF(P51="PCMSO","Projetos PCMSO",IF(P51="eSocial / Psicossocial","Projetos eSocial/Psicossocial","Projetos / Laudos / Avulsos")))) | R51: =IF(C51="","",IF(ISNUMBER(SEARCH("PCMSO",C51)),"Título com PCMSO no nome",IF(OR(ISNUMBER(SEARCH("E-SOCIAL",C51)),ISNUMBER(SEARCH("PSICOSOCIAL",C51))),"Título com eSocial/Psicossocial no nome",IF(O51="Receita recorrente","Tipo DRE recorrente","Extra sem palavra-chave específica")))) | S51: =IFERROR(VLOOKUP($A51,'13. Mapa Títulos-Receita'!$A$8:$P$1000,4,FALSE),"") | T51: =IFERROR(VLOOKUP($A51,'13. Mapa Títulos-Receita'!$A$8:$P$1000,5,FALSE),"") | U51: =IFERROR(VLOOKUP($A51,'13. Mapa Títulos-Receita'!$A$8:$P$1000,6,FALSE),"") | V51: =IFERROR(VLOOKUP($A51,'13. Mapa Títulos-Receita'!$A$8:$P$1000,7,FALSE),"") | W51: =IFERROR(VLOOKUP($A51,'13. Mapa Títulos-Receita'!$A$8:$P$1000,8,FALSE),"") | X51: =IFERROR(VLOOKUP($A51,'13. Mapa Títulos-Receita'!$A$8:$P$1000,9,FALSE),"") | Y51: =IFERROR(VLOOKUP($A51,'13. Mapa Títulos-Receita'!$A$8:$P$1000,10,FALSE),"") | Z51: =IFERROR(VLOOKUP($A51,'13. Mapa Títulos-Receita'!$A$8:$P$1000,11,FALSE),"") | AA51: =IFERROR(VLOOKUP($A51,'13. Mapa Títulos-Receita'!$A$8:$P$1000,12,FALSE),"") | AB51: =IFERROR(VLOOKUP($A51,'13. Mapa Títulos-Receita'!$A$8:$P$1000,13,FALSE),"") | AC51: =IFERROR(VLOOKUP($A51,'13. Mapa Títulos-Receita'!$A$8:$P$1000,14,FALSE),"") | AD51: =IFERROR(VLOOKUP($A51,'13. Mapa Títulos-Receita'!$A$8:$P$1000,15,FALSE),"") | AE51: =IFERROR(VLOOKUP($A51,'13. Mapa Títulos-Receita'!$A$8:$P$1000,16,FALSE),"")
K52: =IF(J52="","",IF(OR(J52="Recebido",F52=""),MAX(0,F52-E52),MAX(0,$B$4-E52))) | L52: =IF(K52="","",IF(K52=0,"Em dia",IF(K52<=30,"1-30 dias",IF(K52<=60,"31-60 dias",IF(K52<=90,"61-90 dias",">90 dias"))))) | P52: =IF(C52="","",IF(ISNUMBER(SEARCH("PCMSO",C52)),"PCMSO",IF(OR(ISNUMBER(SEARCH("E-SOCIAL",C52)),ISNUMBER(SEARCH("PSICOSOCIAL",C52))),"eSocial / Psicossocial",IF(O52="Receita recorrente","Carteira recorrente","Projetos / Laudos / Avulsos")))) | Q52: =IF(P52="","",IF(P52="Carteira recorrente","Operação recorrente",IF(P52="PCMSO","Projetos PCMSO",IF(P52="eSocial / Psicossocial","Projetos eSocial/Psicossocial","Projetos / Laudos / Avulsos")))) | R52: =IF(C52="","",IF(ISNUMBER(SEARCH("PCMSO",C52)),"Título com PCMSO no nome",IF(OR(ISNUMBER(SEARCH("E-SOCIAL",C52)),ISNUMBER(SEARCH("PSICOSOCIAL",C52))),"Título com eSocial/Psicossocial no nome",IF(O52="Receita recorrente","Tipo DRE recorrente","Extra sem palavra-chave específica"))))
K53: =IF(J53="","",IF(OR(J53="Recebido",F53=""),MAX(0,F53-E53),MAX(0,$B$4-E53))) | L53: =IF(K53="","",IF(K53=0,"Em dia",IF(K53<=30,"1-30 dias",IF(K53<=60,"31-60 dias",IF(K53<=90,"61-90 dias",">90 dias"))))) | P53: =IF(C53="","",IF(ISNUMBER(SEARCH("PCMSO",C53)),"PCMSO",IF(OR(ISNUMBER(SEARCH("E-SOCIAL",C53)),ISNUMBER(SEARCH("PSICOSOCIAL",C53))),"eSocial / Psicossocial",IF(O53="Receita recorrente","Carteira recorrente","Projetos / Laudos / Avulsos")))) | Q53: =IF(P53="","",IF(P53="Carteira recorrente","Operação recorrente",IF(P53="PCMSO","Projetos PCMSO",IF(P53="eSocial / Psicossocial","Projetos eSocial/Psicossocial","Projetos / Laudos / Avulsos")))) | R53: =IF(C53="","",IF(ISNUMBER(SEARCH("PCMSO",C53)),"Título com PCMSO no nome",IF(OR(ISNUMBER(SEARCH("E-SOCIAL",C53)),ISNUMBER(SEARCH("PSICOSOCIAL",C53))),"Título com eSocial/Psicossocial no nome",IF(O53="Receita recorrente","Tipo DRE recorrente","Extra sem palavra-chave específica"))))
K54: =IF(J54="","",IF(OR(J54="Recebido",F54=""),MAX(0,F54-E54),MAX(0,$B$4-E54))) | L54: =IF(K54="","",IF(K54=0,"Em dia",IF(K54<=30,"1-30 dias",IF(K54<=60,"31-60 dias",IF(K54<=90,"61-90 dias",">90 dias"))))) | P54: =IF(C54="","",IF(ISNUMBER(SEARCH("PCMSO",C54)),"PCMSO",IF(OR(ISNUMBER(SEARCH("E-SOCIAL",C54)),ISNUMBER(SEARCH("PSICOSOCIAL",C54))),"eSocial / Psicossocial",IF(O54="Receita recorrente","Carteira recorrente","Projetos / Laudos / Avulsos")))) | Q54: =IF(P54="","",IF(P54="Carteira recorrente","Operação recorrente",IF(P54="PCMSO","Projetos PCMSO",IF(P54="eSocial / Psicossocial","Projetos eSocial/Psicossocial","Projetos / Laudos / Avulsos")))) | R54: =IF(C54="","",IF(ISNUMBER(SEARCH("PCMSO",C54)),"Título com PCMSO no nome",IF(OR(ISNUMBER(SEARCH("E-SOCIAL",C54)),ISNUMBER(SEARCH("PSICOSOCIAL",C54))),"Título com eSocial/Psicossocial no nome",IF(O54="Receita recorrente","Tipo DRE recorrente","Extra sem palavra-chave específica"))))
K55: =IF(J55="","",IF(OR(J55="Recebido",F55=""),MAX(0,F55-E55),MAX(0,$B$4-E55))) | L55: =IF(K55="","",IF(K55=0,"Em dia",IF(K55<=30,"1-30 dias",IF(K55<=60,"31-60 dias",IF(K55<=90,"61-90 dias",">90 dias"))))) | P55: =IF(C55="","",IF(ISNUMBER(SEARCH("PCMSO",C55)),"PCMSO",IF(OR(ISNUMBER(SEARCH("E-SOCIAL",C55)),ISNUMBER(SEARCH("PSICOSOCIAL",C55))),"eSocial / Psicossocial",IF(O55="Receita recorrente","Carteira recorrente","Projetos / Laudos / Avulsos")))) | Q55: =IF(P55="","",IF(P55="Carteira recorrente","Operação recorrente",IF(P55="PCMSO","Projetos PCMSO",IF(P55="eSocial / Psicossocial","Projetos eSocial/Psicossocial","Projetos / Laudos / Avulsos")))) | R55: =IF(C55="","",IF(ISNUMBER(SEARCH("PCMSO",C55)),"Título com PCMSO no nome",IF(OR(ISNUMBER(SEARCH("E-SOCIAL",C55)),ISNUMBER(SEARCH("PSICOSOCIAL",C55))),"Título com eSocial/Psicossocial no nome",IF(O55="Receita recorrente","Tipo DRE recorrente","Extra sem palavra-chave específica"))))
K56: =IF(J56="","",IF(OR(J56="Recebido",F56=""),MAX(0,F56-E56),MAX(0,$B$4-E56))) | L56: =IF(K56="","",IF(K56=0,"Em dia",IF(K56<=30,"1-30 dias",IF(K56<=60,"31-60 dias",IF(K56<=90,"61-90 dias",">90 dias"))))) | P56: =IF(C56="","",IF(ISNUMBER(SEARCH("PCMSO",C56)),"PCMSO",IF(OR(ISNUMBER(SEARCH("E-SOCIAL",C56)),ISNUMBER(SEARCH("PSICOSOCIAL",C56))),"eSocial / Psicossocial",IF(O56="Receita recorrente","Carteira recorrente","Projetos / Laudos / Avulsos")))) | Q56: =IF(P56="","",IF(P56="Carteira recorrente","Operação recorrente",IF(P56="PCMSO","Projetos PCMSO",IF(P56="eSocial / Psicossocial","Projetos eSocial/Psicossocial","Projetos / Laudos / Avulsos")))) | R56: =IF(C56="","",IF(ISNUMBER(SEARCH("PCMSO",C56)),"Título com PCMSO no nome",IF(OR(ISNUMBER(SEARCH("E-SOCIAL",C56)),ISNUMBER(SEARCH("PSICOSOCIAL",C56))),"Título com eSocial/Psicossocial no nome",IF(O56="Receita recorrente","Tipo DRE recorrente","Extra sem palavra-chave específica"))))
K57: =IF(J57="","",IF(OR(J57="Recebido",F57=""),MAX(0,F57-E57),MAX(0,$B$4-E57))) | L57: =IF(K57="","",IF(K57=0,"Em dia",IF(K57<=30,"1-30 dias",IF(K57<=60,"31-60 dias",IF(K57<=90,"61-90 dias",">90 dias"))))) | P57: =IF(C57="","",IF(ISNUMBER(SEARCH("PCMSO",C57)),"PCMSO",IF(OR(ISNUMBER(SEARCH("E-SOCIAL",C57)),ISNUMBER(SEARCH("PSICOSOCIAL",C57))),"eSocial / Psicossocial",IF(O57="Receita recorrente","Carteira recorrente","Projetos / Laudos / Avulsos")))) | Q57: =IF(P57="","",IF(P57="Carteira recorrente","Operação recorrente",IF(P57="PCMSO","Projetos PCMSO",IF(P57="eSocial / Psicossocial","Projetos eSocial/Psicossocial","Projetos / Laudos / Avulsos")))) | R57: =IF(C57="","",IF(ISNUMBER(SEARCH("PCMSO",C57)),"Título com PCMSO no nome",IF(OR(ISNUMBER(SEARCH("E-SOCIAL",C57)),ISNUMBER(SEARCH("PSICOSOCIAL",C57))),"Título com eSocial/Psicossocial no nome",IF(O57="Receita recorrente","Tipo DRE recorrente","Extra sem palavra-chave específica"))))
A58: =IF(C58="","", "CR-"&TEXT(ROW()-7,"000")) | J58: =IF(H58="","",IF(I58>=H58,"Recebido",IF($B$4>E58,"Vencido","Aberto"))) | K58: =IF(J58="","",IF(OR(J58="Recebido",F58=""),MAX(0,F58-E58),MAX(0,$B$4-E58))) | L58: =IF(K58="","",IF(K58=0,"Em dia",IF(K58<=30,"1-30 dias",IF(K58<=60,"31-60 dias",IF(K58<=90,"61-90 dias",">90 dias"))))) | P58: =IF(C58="","",IF(ISNUMBER(SEARCH("PCMSO",C58)),"PCMSO",IF(OR(ISNUMBER(SEARCH("E-SOCIAL",C58)),ISNUMBER(SEARCH("PSICOSOCIAL",C58))),"eSocial / Psicossocial",IF(O58="Receita recorrente","Carteira recorrente","Projetos / Laudos / Avulsos")))) | Q58: =IF(P58="","",IF(P58="Carteira recorrente","Operação recorrente",IF(P58="PCMSO","Projetos PCMSO",IF(P58="eSocial / Psicossocial","Projetos eSocial/Psicossocial","Projetos / Laudos / Avulsos")))) | R58: =IF(C58="","",IF(ISNUMBER(SEARCH("PCMSO",C58)),"Título com PCMSO no nome",IF(OR(ISNUMBER(SEARCH("E-SOCIAL",C58)),ISNUMBER(SEARCH("PSICOSOCIAL",C58))),"Título com eSocial/Psicossocial no nome",IF(O58="Receita recorrente","Tipo DRE recorrente","Extra sem palavra-chave específica")))) | S58: =IFERROR(VLOOKUP($A58,'13. Mapa Títulos-Receita'!$A$8:$P$1000,4,FALSE),"") | T58: =IFERROR(VLOOKUP($A58,'13. Mapa Títulos-Receita'!$A$8:$P$1000,5,FALSE),"") | U58: =IFERROR(VLOOKUP($A58,'13. Mapa Títulos-Receita'!$A$8:$P$1000,6,FALSE),"") | V58: =IFERROR(VLOOKUP($A58,'13. Mapa Títulos-Receita'!$A$8:$P$1000,7,FALSE),"") | W58: =IFERROR(VLOOKUP($A58,'13. Mapa Títulos-Receita'!$A$8:$P$1000,8,FALSE),"") | X58: =IFERROR(VLOOKUP($A58,'13. Mapa Títulos-Receita'!$A$8:$P$1000,9,FALSE),"") | Y58: =IFERROR(VLOOKUP($A58,'13. Mapa Títulos-Receita'!$A$8:$P$1000,10,FALSE),"") | Z58: =IFERROR(VLOOKUP($A58,'13. Mapa Títulos-Receita'!$A$8:$P$1000,11,FALSE),"") | AA58: =IFERROR(VLOOKUP($A58,'13. Mapa Títulos-Receita'!$A$8:$P$1000,12,FALSE),"") | AB58: =IFERROR(VLOOKUP($A58,'13. Mapa Títulos-Receita'!$A$8:$P$1000,13,FALSE),"") | AC58: =IFERROR(VLOOKUP($A58,'13. Mapa Títulos-Receita'!$A$8:$P$1000,14,FALSE),"") | AD58: =IFERROR(VLOOKUP($A58,'13. Mapa Títulos-Receita'!$A$8:$P$1000,15,FALSE),"") | AE58: =IFERROR(VLOOKUP($A58,'13. Mapa Títulos-Receita'!$A$8:$P$1000,16,FALSE),"")
A59: =IF(C59="","", "CR-"&TEXT(ROW()-7,"000")) | J59: =IF(H59="","",IF(I59>=H59,"Recebido",IF($B$4>E59,"Vencido","Aberto"))) | K59: =IF(J59="","",IF(OR(J59="Recebido",F59=""),MAX(0,F59-E59),MAX(0,$B$4-E59))) | L59: =IF(K59="","",IF(K59=0,"Em dia",IF(K59<=30,"1-30 dias",IF(K59<=60,"31-60 dias",IF(K59<=90,"61-90 dias",">90 dias"))))) | P59: =IF(C59="","",IF(ISNUMBER(SEARCH("PCMSO",C59)),"PCMSO",IF(OR(ISNUMBER(SEARCH("E-SOCIAL",C59)),ISNUMBER(SEARCH("PSICOSOCIAL",C59))),"eSocial / Psicossocial",IF(O59="Receita recorrente","Carteira recorrente","Projetos / Laudos / Avulsos")))) | Q59: =IF(P59="","",IF(P59="Carteira recorrente","Operação recorrente",IF(P59="PCMSO","Projetos PCMSO",IF(P59="eSocial / Psicossocial","Projetos eSocial/Psicossocial","Projetos / Laudos / Avulsos")))) | R59: =IF(C59="","",IF(ISNUMBER(SEARCH("PCMSO",C59)),"Título com PCMSO no nome",IF(OR(ISNUMBER(SEARCH("E-SOCIAL",C59)),ISNUMBER(SEARCH("PSICOSOCIAL",C59))),"Título com eSocial/Psicossocial no nome",IF(O59="Receita recorrente","Tipo DRE recorrente","Extra sem palavra-chave específica")))) | S59: =IFERROR(VLOOKUP($A59,'13. Mapa Títulos-Receita'!$A$8:$P$1000,4,FALSE),"") | T59: =IFERROR(VLOOKUP($A59,'13. Mapa Títulos-Receita'!$A$8:$P$1000,5,FALSE),"") | U59: =IFERROR(VLOOKUP($A59,'13. Mapa Títulos-Receita'!$A$8:$P$1000,6,FALSE),"") | V59: =IFERROR(VLOOKUP($A59,'13. Mapa Títulos-Receita'!$A$8:$P$1000,7,FALSE),"") | W59: =IFERROR(VLOOKUP($A59,'13. Mapa Títulos-Receita'!$A$8:$P$1000,8,FALSE),"") | X59: =IFERROR(VLOOKUP($A59,'13. Mapa Títulos-Receita'!$A$8:$P$1000,9,FALSE),"") | Y59: =IFERROR(VLOOKUP($A59,'13. Mapa Títulos-Receita'!$A$8:$P$1000,10,FALSE),"") | Z59: =IFERROR(VLOOKUP($A59,'13. Mapa Títulos-Receita'!$A$8:$P$1000,11,FALSE),"") | AA59: =IFERROR(VLOOKUP($A59,'13. Mapa Títulos-Receita'!$A$8:$P$1000,12,FALSE),"") | AB59: =IFERROR(VLOOKUP($A59,'13. Mapa Títulos-Receita'!$A$8:$P$1000,13,FALSE),"") | AC59: =IFERROR(VLOOKUP($A59,'13. Mapa Títulos-Receita'!$A$8:$P$1000,14,FALSE),"") | AD59: =IFERROR(VLOOKUP($A59,'13. Mapa Títulos-Receita'!$A$8:$P$1000,15,FALSE),"") | AE59: =IFERROR(VLOOKUP($A59,'13. Mapa Títulos-Receita'!$A$8:$P$1000,16,FALSE),"")
A60: =IF(C60="","", "CR-"&TEXT(ROW()-7,"000"))
A61: =IF(C61="","", "CR-"&TEXT(ROW()-7,"000")) | J61: =IF(H61="","",IF(I61>=H61,"Recebido",IF($B$4>E61,"Vencido","Aberto"))) | K61: =IF(J61="","",IF(OR(J61="Recebido",F61=""),MAX(0,F61-E61),MAX(0,$B$4-E61))) | L61: =IF(K61="","",IF(K61=0,"Em dia",IF(K61<=30,"1-30 dias",IF(K61<=60,"31-60 dias",IF(K61<=90,"61-90 dias",">90 dias"))))) | P61: =IF(C61="","",IF(ISNUMBER(SEARCH("PCMSO",C61)),"PCMSO",IF(OR(ISNUMBER(SEARCH("E-SOCIAL",C61)),ISNUMBER(SEARCH("PSICOSOCIAL",C61))),"eSocial / Psicossocial",IF(O61="Receita recorrente","Carteira recorrente","Projetos / Laudos / Avulsos")))) | Q61: =IF(P61="","",IF(P61="Carteira recorrente","Operação recorrente",IF(P61="PCMSO","Projetos PCMSO",IF(P61="eSocial / Psicossocial","Projetos eSocial/Psicossocial","Projetos / Laudos / Avulsos")))) | R61: =IF(C61="","",IF(ISNUMBER(SEARCH("PCMSO",C61)),"Título com PCMSO no nome",IF(OR(ISNUMBER(SEARCH("E-SOCIAL",C61)),ISNUMBER(SEARCH("PSICOSOCIAL",C61))),"Título com eSocial/Psicossocial no nome",IF(O61="Receita recorrente","Tipo DRE recorrente","Extra sem palavra-chave específica")))) | S61: =IFERROR(VLOOKUP($A61,'13. Mapa Títulos-Receita'!$A$8:$P$1000,4,FALSE),"") | T61: =IFERROR(VLOOKUP($A61,'13. Mapa Títulos-Receita'!$A$8:$P$1000,5,FALSE),"") | U61: =IFERROR(VLOOKUP($A61,'13. Mapa Títulos-Receita'!$A$8:$P$1000,6,FALSE),"") | V61: =IFERROR(VLOOKUP($A61,'13. Mapa Títulos-Receita'!$A$8:$P$1000,7,FALSE),"") | W61: =IFERROR(VLOOKUP($A61,'13. Mapa Títulos-Receita'!$A$8:$P$1000,8,FALSE),"") | X61: =IFERROR(VLOOKUP($A61,'13. Mapa Títulos-Receita'!$A$8:$P$1000,9,FALSE),"") | Y61: =IFERROR(VLOOKUP($A61,'13. Mapa Títulos-Receita'!$A$8:$P$1000,10,FALSE),"") | Z61: =IFERROR(VLOOKUP($A61,'13. Mapa Títulos-Receita'!$A$8:$P$1000,11,FALSE),"") | AA61: =IFERROR(VLOOKUP($A61,'13. Mapa Títulos-Receita'!$A$8:$P$1000,12,FALSE),"") | AB61: =IFERROR(VLOOKUP($A61,'13. Mapa Títulos-Receita'!$A$8:$P$1000,13,FALSE),"") | AC61: =IFERROR(VLOOKUP($A61,'13. Mapa Títulos-Receita'!$A$8:$P$1000,14,FALSE),"") | AD61: =IFERROR(VLOOKUP($A61,'13. Mapa Títulos-Receita'!$A$8:$P$1000,15,FALSE),"") | AE61: =IFERROR(VLOOKUP($A61,'13. Mapa Títulos-Receita'!$A$8:$P$1000,16,FALSE),"")
A62: =IF(C62="","", "CR-"&TEXT(ROW()-7,"000")) | J62: =IF(H62="","",IF(I62>=H62,"Recebido",IF($B$4>E62,"Vencido","Aberto"))) | K62: =IF(J62="","",IF(OR(J62="Recebido",F62=""),MAX(0,F62-E62),MAX(0,$B$4-E62))) | L62: =IF(K62="","",IF(K62=0,"Em dia",IF(K62<=30,"1-30 dias",IF(K62<=60,"31-60 dias",IF(K62<=90,"61-90 dias",">90 dias"))))) | P62: =IF(C62="","",IF(ISNUMBER(SEARCH("PCMSO",C62)),"PCMSO",IF(OR(ISNUMBER(SEARCH("E-SOCIAL",C62)),ISNUMBER(SEARCH("PSICOSOCIAL",C62))),"eSocial / Psicossocial",IF(O62="Receita recorrente","Carteira recorrente","Projetos / Laudos / Avulsos")))) | Q62: =IF(P62="","",IF(P62="Carteira recorrente","Operação recorrente",IF(P62="PCMSO","Projetos PCMSO",IF(P62="eSocial / Psicossocial","Projetos eSocial/Psicossocial","Projetos / Laudos / Avulsos")))) | R62: =IF(C62="","",IF(ISNUMBER(SEARCH("PCMSO",C62)),"Título com PCMSO no nome",IF(OR(ISNUMBER(SEARCH("E-SOCIAL",C62)),ISNUMBER(SEARCH("PSICOSOCIAL",C62))),"Título com eSocial/Psicossocial no nome",IF(O62="Receita recorrente","Tipo DRE recorrente","Extra sem palavra-chave específica")))) | S62: =IFERROR(VLOOKUP($A62,'13. Mapa Títulos-Receita'!$A$8:$P$1000,4,FALSE),"") | T62: =IFERROR(VLOOKUP($A62,'13. Mapa Títulos-Receita'!$A$8:$P$1000,5,FALSE),"") | U62: =IFERROR(VLOOKUP($A62,'13. Mapa Títulos-Receita'!$A$8:$P$1000,6,FALSE),"") | V62: =IFERROR(VLOOKUP($A62,'13. Mapa Títulos-Receita'!$A$8:$P$1000,7,FALSE),"") | W62: =IFERROR(VLOOKUP($A62,'13. Mapa Títulos-Receita'!$A$8:$P$1000,8,FALSE),"") | X62: =IFERROR(VLOOKUP($A62,'13. Mapa Títulos-Receita'!$A$8:$P$1000,9,FALSE),"") | Y62: =IFERROR(VLOOKUP($A62,'13. Mapa Títulos-Receita'!$A$8:$P$1000,10,FALSE),"") | Z62: =IFERROR(VLOOKUP($A62,'13. Mapa Títulos-Receita'!$A$8:$P$1000,11,FALSE),"") | AA62: =IFERROR(VLOOKUP($A62,'13. Mapa Títulos-Receita'!$A$8:$P$1000,12,FALSE),"") | AB62: =IFERROR(VLOOKUP($A62,'13. Mapa Títulos-Receita'!$A$8:$P$1000,13,FALSE),"") | AC62: =IFERROR(VLOOKUP($A62,'13. Mapa Títulos-Receita'!$A$8:$P$1000,14,FALSE),"") | AD62: =IFERROR(VLOOKUP($A62,'13. Mapa Títulos-Receita'!$A$8:$P$1000,15,FALSE),"") | AE62: =IFERROR(VLOOKUP($A62,'13. Mapa Títulos-Receita'!$A$8:$P$1000,16,FALSE),"")
A63: =IF(C63="","", "CR-"&TEXT(ROW()-7,"000")) | J63: =IF(H63="","",IF(I63>=H63,"Recebido",IF($B$4>E63,"Vencido","Aberto"))) | K63: =IF(J63="","",IF(OR(J63="Recebido",F63=""),MAX(0,F63-E63),MAX(0,$B$4-E63))) | L63: =IF(K63="","",IF(K63=0,"Em dia",IF(K63<=30,"1-30 dias",IF(K63<=60,"31-60 dias",IF(K63<=90,"61-90 dias",">90 dias"))))) | P63: =IF(C63="","",IF(ISNUMBER(SEARCH("PCMSO",C63)),"PCMSO",IF(OR(ISNUMBER(SEARCH("E-SOCIAL",C63)),ISNUMBER(SEARCH("PSICOSOCIAL",C63))),"eSocial / Psicossocial",IF(O63="Receita recorrente","Carteira recorrente","Projetos / Laudos / Avulsos")))) | Q63: =IF(P63="","",IF(P63="Carteira recorrente","Operação recorrente",IF(P63="PCMSO","Projetos PCMSO",IF(P63="eSocial / Psicossocial","Projetos eSocial/Psicossocial","Projetos / Laudos / Avulsos")))) | R63: =IF(C63="","",IF(ISNUMBER(SEARCH("PCMSO",C63)),"Título com PCMSO no nome",IF(OR(ISNUMBER(SEARCH("E-SOCIAL",C63)),ISNUMBER(SEARCH("PSICOSOCIAL",C63))),"Título com eSocial/Psicossocial no nome",IF(O63="Receita recorrente","Tipo DRE recorrente","Extra sem palavra-chave específica")))) | S63: =IFERROR(VLOOKUP($A63,'13. Mapa Títulos-Receita'!$A$8:$P$1000,4,FALSE),"") | T63: =IFERROR(VLOOKUP($A63,'13. Mapa Títulos-Receita'!$A$8:$P$1000,5,FALSE),"") | U63: =IFERROR(VLOOKUP($A63,'13. Mapa Títulos-Receita'!$A$8:$P$1000,6,FALSE),"") | V63: =IFERROR(VLOOKUP($A63,'13. Mapa Títulos-Receita'!$A$8:$P$1000,7,FALSE),"") | W63: =IFERROR(VLOOKUP($A63,'13. Mapa Títulos-Receita'!$A$8:$P$1000,8,FALSE),"") | X63: =IFERROR(VLOOKUP($A63,'13. Mapa Títulos-Receita'!$A$8:$P$1000,9,FALSE),"") | Y63: =IFERROR(VLOOKUP($A63,'13. Mapa Títulos-Receita'!$A$8:$P$1000,10,FALSE),"") | Z63: =IFERROR(VLOOKUP($A63,'13. Mapa Títulos-Receita'!$A$8:$P$1000,11,FALSE),"") | AA63: =IFERROR(VLOOKUP($A63,'13. Mapa Títulos-Receita'!$A$8:$P$1000,12,FALSE),"") | AB63: =IFERROR(VLOOKUP($A63,'13. Mapa Títulos-Receita'!$A$8:$P$1000,13,FALSE),"") | AC63: =IFERROR(VLOOKUP($A63,'13. Mapa Títulos-Receita'!$A$8:$P$1000,14,FALSE),"") | AD63: =IFERROR(VLOOKUP($A63,'13. Mapa Títulos-Receita'!$A$8:$P$1000,15,FALSE),"") | AE63: =IFERROR(VLOOKUP($A63,'13. Mapa Títulos-Receita'!$A$8:$P$1000,16,FALSE),"")
A64: =IF(C64="","", "CR-"&TEXT(ROW()-7,"000")) | J64: =IF(H64="","",IF(I64>=H64,"Recebido",IF($B$4>E64,"Vencido","Aberto"))) | K64: =IF(J64="","",IF(OR(J64="Recebido",F64=""),MAX(0,F64-E64),MAX(0,$B$4-E64))) | L64: =IF(K64="","",IF(K64=0,"Em dia",IF(K64<=30,"1-30 dias",IF(K64<=60,"31-60 dias",IF(K64<=90,"61-90 dias",">90 dias"))))) | P64: =IF(C64="","",IF(ISNUMBER(SEARCH("PCMSO",C64)),"PCMSO",IF(OR(ISNUMBER(SEARCH("E-SOCIAL",C64)),ISNUMBER(SEARCH("PSICOSOCIAL",C64))),"eSocial / Psicossocial",IF(O64="Receita recorrente","Carteira recorrente","Projetos / Laudos / Avulsos")))) | Q64: =IF(P64="","",IF(P64="Carteira recorrente","Operação recorrente",IF(P64="PCMSO","Projetos PCMSO",IF(P64="eSocial / Psicossocial","Projetos eSocial/Psicossocial","Projetos / Laudos / Avulsos")))) | R64: =IF(C64="","",IF(ISNUMBER(SEARCH("PCMSO",C64)),"Título com PCMSO no nome",IF(OR(ISNUMBER(SEARCH("E-SOCIAL",C64)),ISNUMBER(SEARCH("PSICOSOCIAL",C64))),"Título com eSocial/Psicossocial no nome",IF(O64="Receita recorrente","Tipo DRE recorrente","Extra sem palavra-chave específica")))) | S64: =IFERROR(VLOOKUP($A64,'13. Mapa Títulos-Receita'!$A$8:$P$1000,4,FALSE),"") | T64: =IFERROR(VLOOKUP($A64,'13. Mapa Títulos-Receita'!$A$8:$P$1000,5,FALSE),"") | U64: =IFERROR(VLOOKUP($A64,'13. Mapa Títulos-Receita'!$A$8:$P$1000,6,FALSE),"") | V64: =IFERROR(VLOOKUP($A64,'13. Mapa Títulos-Receita'!$A$8:$P$1000,7,FALSE),"") | W64: =IFERROR(VLOOKUP($A64,'13. Mapa Títulos-Receita'!$A$8:$P$1000,8,FALSE),"") | X64: =IFERROR(VLOOKUP($A64,'13. Mapa Títulos-Receita'!$A$8:$P$1000,9,FALSE),"") | Y64: =IFERROR(VLOOKUP($A64,'13. Mapa Títulos-Receita'!$A$8:$P$1000,10,FALSE),"") | Z64: =IFERROR(VLOOKUP($A64,'13. Mapa Títulos-Receita'!$A$8:$P$1000,11,FALSE),"") | AA64: =IFERROR(VLOOKUP($A64,'13. Mapa Títulos-Receita'!$A$8:$P$1000,12,FALSE),"") | AB64: =IFERROR(VLOOKUP($A64,'13. Mapa Títulos-Receita'!$A$8:$P$1000,13,FALSE),"") | AC64: =IFERROR(VLOOKUP($A64,'13. Mapa Títulos-Receita'!$A$8:$P$1000,14,FALSE),"") | AD64: =IFERROR(VLOOKUP($A64,'13. Mapa Títulos-Receita'!$A$8:$P$1000,15,FALSE),"") | AE64: =IFERROR(VLOOKUP($A64,'13. Mapa Títulos-Receita'!$A$8:$P$1000,16,FALSE),"")
A65: =IF(C65="","", "CR-"&TEXT(ROW()-7,"000")) | J65: =IF(H65="","",IF(I65>=H65,"Recebido",IF($B$4>E65,"Vencido","Aberto"))) | K65: =IF(J65="","",IF(OR(J65="Recebido",F65=""),MAX(0,F65-E65),MAX(0,$B$4-E65))) | L65: =IF(K65="","",IF(K65=0,"Em dia",IF(K65<=30,"1-30 dias",IF(K65<=60,"31-60 dias",IF(K65<=90,"61-90 dias",">90 dias"))))) | P65: =IF(C65="","",IF(ISNUMBER(SEARCH("PCMSO",C65)),"PCMSO",IF(OR(ISNUMBER(SEARCH("E-SOCIAL",C65)),ISNUMBER(SEARCH("PSICOSOCIAL",C65))),"eSocial / Psicossocial",IF(O65="Receita recorrente","Carteira recorrente","Projetos / Laudos / Avulsos")))) | Q65: =IF(P65="","",IF(P65="Carteira recorrente","Operação recorrente",IF(P65="PCMSO","Projetos PCMSO",IF(P65="eSocial / Psicossocial","Projetos eSocial/Psicossocial","Projetos / Laudos / Avulsos")))) | R65: =IF(C65="","",IF(ISNUMBER(SEARCH("PCMSO",C65)),"Título com PCMSO no nome",IF(OR(ISNUMBER(SEARCH("E-SOCIAL",C65)),ISNUMBER(SEARCH("PSICOSOCIAL",C65))),"Título com eSocial/Psicossocial no nome",IF(O65="Receita recorrente","Tipo DRE recorrente","Extra sem palavra-chave específica")))) | S65: =IFERROR(VLOOKUP($A65,'13. Mapa Títulos-Receita'!$A$8:$P$1000,4,FALSE),"") | T65: =IFERROR(VLOOKUP($A65,'13. Mapa Títulos-Receita'!$A$8:$P$1000,5,FALSE),"") | U65: =IFERROR(VLOOKUP($A65,'13. Mapa Títulos-Receita'!$A$8:$P$1000,6,FALSE),"") | V65: =IFERROR(VLOOKUP($A65,'13. Mapa Títulos-Receita'!$A$8:$P$1000,7,FALSE),"") | W65: =IFERROR(VLOOKUP($A65,'13. Mapa Títulos-Receita'!$A$8:$P$1000,8,FALSE),"") | X65: =IFERROR(VLOOKUP($A65,'13. Mapa Títulos-Receita'!$A$8:$P$1000,9,FALSE),"") | Y65: =IFERROR(VLOOKUP($A65,'13. Mapa Títulos-Receita'!$A$8:$P$1000,10,FALSE),"") | Z65: =IFERROR(VLOOKUP($A65,'13. Mapa Títulos-Receita'!$A$8:$P$1000,11,FALSE),"") | AA65: =IFERROR(VLOOKUP($A65,'13. Mapa Títulos-Receita'!$A$8:$P$1000,12,FALSE),"") | AB65: =IFERROR(VLOOKUP($A65,'13. Mapa Títulos-Receita'!$A$8:$P$1000,13,FALSE),"") | AC65: =IFERROR(VLOOKUP($A65,'13. Mapa Títulos-Receita'!$A$8:$P$1000,14,FALSE),"") | AD65: =IFERROR(VLOOKUP($A65,'13. Mapa Títulos-Receita'!$A$8:$P$1000,15,FALSE),"") | AE65: =IFERROR(VLOOKUP($A65,'13. Mapa Títulos-Receita'!$A$8:$P$1000,16,FALSE),"")
A66: =IF(C66="","", "CR-"&TEXT(ROW()-7,"000")) | J66: =IF(H66="","",IF(I66>=H66,"Recebido",IF($B$4>E66,"Vencido","Aberto"))) | K66: =IF(J66="","",IF(OR(J66="Recebido",F66=""),MAX(0,F66-E66),MAX(0,$B$4-E66))) | L66: =IF(K66="","",IF(K66=0,"Em dia",IF(K66<=30,"1-30 dias",IF(K66<=60,"31-60 dias",IF(K66<=90,"61-90 dias",">90 dias"))))) | P66: =IF(C66="","",IF(ISNUMBER(SEARCH("PCMSO",C66)),"PCMSO",IF(OR(ISNUMBER(SEARCH("E-SOCIAL",C66)),ISNUMBER(SEARCH("PSICOSOCIAL",C66))),"eSocial / Psicossocial",IF(O66="Receita recorrente","Carteira recorrente","Projetos / Laudos / Avulsos")))) | Q66: =IF(P66="","",IF(P66="Carteira recorrente","Operação recorrente",IF(P66="PCMSO","Projetos PCMSO",IF(P66="eSocial / Psicossocial","Projetos eSocial/Psicossocial","Projetos / Laudos / Avulsos")))) | R66: =IF(C66="","",IF(ISNUMBER(SEARCH("PCMSO",C66)),"Título com PCMSO no nome",IF(OR(ISNUMBER(SEARCH("E-SOCIAL",C66)),ISNUMBER(SEARCH("PSICOSOCIAL",C66))),"Título com eSocial/Psicossocial no nome",IF(O66="Receita recorrente","Tipo DRE recorrente","Extra sem palavra-chave específica")))) | S66: =IFERROR(VLOOKUP($A66,'13. Mapa Títulos-Receita'!$A$8:$P$1000,4,FALSE),"") | T66: =IFERROR(VLOOKUP($A66,'13. Mapa Títulos-Receita'!$A$8:$P$1000,5,FALSE),"") | U66: =IFERROR(VLOOKUP($A66,'13. Mapa Títulos-Receita'!$A$8:$P$1000,6,FALSE),"") | V66: =IFERROR(VLOOKUP($A66,'13. Mapa Títulos-Receita'!$A$8:$P$1000,7,FALSE),"") | W66: =IFERROR(VLOOKUP($A66,'13. Mapa Títulos-Receita'!$A$8:$P$1000,8,FALSE),"") | X66: =IFERROR(VLOOKUP($A66,'13. Mapa Títulos-Receita'!$A$8:$P$1000,9,FALSE),"") | Y66: =IFERROR(VLOOKUP($A66,'13. Mapa Títulos-Receita'!$A$8:$P$1000,10,FALSE),"") | Z66: =IFERROR(VLOOKUP($A66,'13. Mapa Títulos-Receita'!$A$8:$P$1000,11,FALSE),"") | AA66: =IFERROR(VLOOKUP($A66,'13. Mapa Títulos-Receita'!$A$8:$P$1000,12,FALSE),"") | AB66: =IFERROR(VLOOKUP($A66,'13. Mapa Títulos-Receita'!$A$8:$P$1000,13,FALSE),"") | AC66: =IFERROR(VLOOKUP($A66,'13. Mapa Títulos-Receita'!$A$8:$P$1000,14,FALSE),"") | AD66: =IFERROR(VLOOKUP($A66,'13. Mapa Títulos-Receita'!$A$8:$P$1000,15,FALSE),"") | AE66: =IFERROR(VLOOKUP($A66,'13. Mapa Títulos-Receita'!$A$8:$P$1000,16,FALSE),"")
A67: =IF(C67="","", "CR-"&TEXT(ROW()-7,"000")) | J67: =IF(H67="","",IF(I67>=H67,"Recebido",IF($B$4>E67,"Vencido","Aberto"))) | K67: =IF(J67="","",IF(OR(J67="Recebido",F67=""),MAX(0,F67-E67),MAX(0,$B$4-E67))) | L67: =IF(K67="","",IF(K67=0,"Em dia",IF(K67<=30,"1-30 dias",IF(K67<=60,"31-60 dias",IF(K67<=90,"61-90 dias",">90 dias"))))) | P67: =IF(C67="","",IF(ISNUMBER(SEARCH("PCMSO",C67)),"PCMSO",IF(OR(ISNUMBER(SEARCH("E-SOCIAL",C67)),ISNUMBER(SEARCH("PSICOSOCIAL",C67))),"eSocial / Psicossocial",IF(O67="Receita recorrente","Carteira recorrente","Projetos / Laudos / Avulsos")))) | Q67: =IF(P67="","",IF(P67="Carteira recorrente","Operação recorrente",IF(P67="PCMSO","Projetos PCMSO",IF(P67="eSocial / Psicossocial","Projetos eSocial/Psicossocial","Projetos / Laudos / Avulsos")))) | R67: =IF(C67="","",IF(ISNUMBER(SEARCH("PCMSO",C67)),"Título com PCMSO no nome",IF(OR(ISNUMBER(SEARCH("E-SOCIAL",C67)),ISNUMBER(SEARCH("PSICOSOCIAL",C67))),"Título com eSocial/Psicossocial no nome",IF(O67="Receita recorrente","Tipo DRE recorrente","Extra sem palavra-chave específica")))) | S67: =IFERROR(VLOOKUP($A67,'13. Mapa Títulos-Receita'!$A$8:$P$1000,4,FALSE),"") | T67: =IFERROR(VLOOKUP($A67,'13. Mapa Títulos-Receita'!$A$8:$P$1000,5,FALSE),"") | U67: =IFERROR(VLOOKUP($A67,'13. Mapa Títulos-Receita'!$A$8:$P$1000,6,FALSE),"") | V67: =IFERROR(VLOOKUP($A67,'13. Mapa Títulos-Receita'!$A$8:$P$1000,7,FALSE),"") | W67: =IFERROR(VLOOKUP($A67,'13. Mapa Títulos-Receita'!$A$8:$P$1000,8,FALSE),"") | X67: =IFERROR(VLOOKUP($A67,'13. Mapa Títulos-Receita'!$A$8:$P$1000,9,FALSE),"") | Y67: =IFERROR(VLOOKUP($A67,'13. Mapa Títulos-Receita'!$A$8:$P$1000,10,FALSE),"") | Z67: =IFERROR(VLOOKUP($A67,'13. Mapa Títulos-Receita'!$A$8:$P$1000,11,FALSE),"") | AA67: =IFERROR(VLOOKUP($A67,'13. Mapa Títulos-Receita'!$A$8:$P$1000,12,FALSE),"") | AB67: =IFERROR(VLOOKUP($A67,'13. Mapa Títulos-Receita'!$A$8:$P$1000,13,FALSE),"") | AC67: =IFERROR(VLOOKUP($A67,'13. Mapa Títulos-Receita'!$A$8:$P$1000,14,FALSE),"") | AD67: =IFERROR(VLOOKUP($A67,'13. Mapa Títulos-Receita'!$A$8:$P$1000,15,FALSE),"") | AE67: =IFERROR(VLOOKUP($A67,'13. Mapa Títulos-Receita'!$A$8:$P$1000,16,FALSE),"")
A68: =IF(C68="","", "CR-"&TEXT(ROW()-7,"000")) | J68: =IF(H68="","",IF(I68>=H68,"Recebido",IF($B$4>E68,"Vencido","Aberto"))) | K68: =IF(J68="","",IF(OR(J68="Recebido",F68=""),MAX(0,F68-E68),MAX(0,$B$4-E68))) | L68: =IF(K68="","",IF(K68=0,"Em dia",IF(K68<=30,"1-30 dias",IF(K68<=60,"31-60 dias",IF(K68<=90,"61-90 dias",">90 dias"))))) | P68: =IF(C68="","",IF(ISNUMBER(SEARCH("PCMSO",C68)),"PCMSO",IF(OR(ISNUMBER(SEARCH("E-SOCIAL",C68)),ISNUMBER(SEARCH("PSICOSOCIAL",C68))),"eSocial / Psicossocial",IF(O68="Receita recorrente","Carteira recorrente","Projetos / Laudos / Avulsos")))) | Q68: =IF(P68="","",IF(P68="Carteira recorrente","Operação recorrente",IF(P68="PCMSO","Projetos PCMSO",IF(P68="eSocial / Psicossocial","Projetos eSocial/Psicossocial","Projetos / Laudos / Avulsos")))) | R68: =IF(C68="","",IF(ISNUMBER(SEARCH("PCMSO",C68)),"Título com PCMSO no nome",IF(OR(ISNUMBER(SEARCH("E-SOCIAL",C68)),ISNUMBER(SEARCH("PSICOSOCIAL",C68))),"Título com eSocial/Psicossocial no nome",IF(O68="Receita recorrente","Tipo DRE recorrente","Extra sem palavra-chave específica")))) | S68: =IFERROR(VLOOKUP($A68,'13. Mapa Títulos-Receita'!$A$8:$P$1000,4,FALSE),"") | T68: =IFERROR(VLOOKUP($A68,'13. Mapa Títulos-Receita'!$A$8:$P$1000,5,FALSE),"") | U68: =IFERROR(VLOOKUP($A68,'13. Mapa Títulos-Receita'!$A$8:$P$1000,6,FALSE),"") | V68: =IFERROR(VLOOKUP($A68,'13. Mapa Títulos-Receita'!$A$8:$P$1000,7,FALSE),"") | W68: =IFERROR(VLOOKUP($A68,'13. Mapa Títulos-Receita'!$A$8:$P$1000,8,FALSE),"") | X68: =IFERROR(VLOOKUP($A68,'13. Mapa Títulos-Receita'!$A$8:$P$1000,9,FALSE),"") | Y68: =IFERROR(VLOOKUP($A68,'13. Mapa Títulos-Receita'!$A$8:$P$1000,10,FALSE),"") | Z68: =IFERROR(VLOOKUP($A68,'13. Mapa Títulos-Receita'!$A$8:$P$1000,11,FALSE),"") | AA68: =IFERROR(VLOOKUP($A68,'13. Mapa Títulos-Receita'!$A$8:$P$1000,12,FALSE),"") | AB68: =IFERROR(VLOOKUP($A68,'13. Mapa Títulos-Receita'!$A$8:$P$1000,13,FALSE),"") | AC68: =IFERROR(VLOOKUP($A68,'13. Mapa Títulos-Receita'!$A$8:$P$1000,14,FALSE),"") | AD68: =IFERROR(VLOOKUP($A68,'13. Mapa Títulos-Receita'!$A$8:$P$1000,15,FALSE),"") | AE68: =IFERROR(VLOOKUP($A68,'13. Mapa Títulos-Receita'!$A$8:$P$1000,16,FALSE),"")
A69: =IF(C69="","", "CR-"&TEXT(ROW()-7,"000")) | J69: =IF(H69="","",IF(I69>=H69,"Recebido",IF($B$4>E69,"Vencido","Aberto"))) | K69: =IF(J69="","",IF(OR(J69="Recebido",F69=""),MAX(0,F69-E69),MAX(0,$B$4-E69))) | L69: =IF(K69="","",IF(K69=0,"Em dia",IF(K69<=30,"1-30 dias",IF(K69<=60,"31-60 dias",IF(K69<=90,"61-90 dias",">90 dias"))))) | P69: =IF(C69="","",IF(ISNUMBER(SEARCH("PCMSO",C69)),"PCMSO",IF(OR(ISNUMBER(SEARCH("E-SOCIAL",C69)),ISNUMBER(SEARCH("PSICOSOCIAL",C69))),"eSocial / Psicossocial",IF(O69="Receita recorrente","Carteira recorrente","Projetos / Laudos / Avulsos")))) | Q69: =IF(P69="","",IF(P69="Carteira recorrente","Operação recorrente",IF(P69="PCMSO","Projetos PCMSO",IF(P69="eSocial / Psicossocial","Projetos eSocial/Psicossocial","Projetos / Laudos / Avulsos")))) | R69: =IF(C69="","",IF(ISNUMBER(SEARCH("PCMSO",C69)),"Título com PCMSO no nome",IF(OR(ISNUMBER(SEARCH("E-SOCIAL",C69)),ISNUMBER(SEARCH("PSICOSOCIAL",C69))),"Título com eSocial/Psicossocial no nome",IF(O69="Receita recorrente","Tipo DRE recorrente","Extra sem palavra-chave específica")))) | S69: =IFERROR(VLOOKUP($A69,'13. Mapa Títulos-Receita'!$A$8:$P$1000,4,FALSE),"") | T69: =IFERROR(VLOOKUP($A69,'13. Mapa Títulos-Receita'!$A$8:$P$1000,5,FALSE),"") | U69: =IFERROR(VLOOKUP($A69,'13. Mapa Títulos-Receita'!$A$8:$P$1000,6,FALSE),"") | V69: =IFERROR(VLOOKUP($A69,'13. Mapa Títulos-Receita'!$A$8:$P$1000,7,FALSE),"") | W69: =IFERROR(VLOOKUP($A69,'13. Mapa Títulos-Receita'!$A$8:$P$1000,8,FALSE),"") | X69: =IFERROR(VLOOKUP($A69,'13. Mapa Títulos-Receita'!$A$8:$P$1000,9,FALSE),"") | Y69: =IFERROR(VLOOKUP($A69,'13. Mapa Títulos-Receita'!$A$8:$P$1000,10,FALSE),"") | Z69: =IFERROR(VLOOKUP($A69,'13. Mapa Títulos-Receita'!$A$8:$P$1000,11,FALSE),"") | AA69: =IFERROR(VLOOKUP($A69,'13. Mapa Títulos-Receita'!$A$8:$P$1000,12,FALSE),"") | AB69: =IFERROR(VLOOKUP($A69,'13. Mapa Títulos-Receita'!$A$8:$P$1000,13,FALSE),"") | AC69: =IFERROR(VLOOKUP($A69,'13. Mapa Títulos-Receita'!$A$8:$P$1000,14,FALSE),"") | AD69: =IFERROR(VLOOKUP($A69,'13. Mapa Títulos-Receita'!$A$8:$P$1000,15,FALSE),"") | AE69: =IFERROR(VLOOKUP($A69,'13. Mapa Títulos-Receita'!$A$8:$P$1000,16,FALSE),"")
A70: =IF(C70="","", "CR-"&TEXT(ROW()-7,"000")) | J70: =IF(H70="","",IF(I70>=H70,"Recebido",IF($B$4>E70,"Vencido","Aberto"))) | K70: =IF(J70="","",IF(OR(J70="Recebido",F70=""),MAX(0,F70-E70),MAX(0,$B$4-E70))) | L70: =IF(K70="","",IF(K70=0,"Em dia",IF(K70<=30,"1-30 dias",IF(K70<=60,"31-60 dias",IF(K70<=90,"61-90 dias",">90 dias"))))) | P70: =IF(C70="","",IF(ISNUMBER(SEARCH("PCMSO",C70)),"PCMSO",IF(OR(ISNUMBER(SEARCH("E-SOCIAL",C70)),ISNUMBER(SEARCH("PSICOSOCIAL",C70))),"eSocial / Psicossocial",IF(O70="Receita recorrente","Carteira recorrente","Projetos / Laudos / Avulsos")))) | Q70: =IF(P70="","",IF(P70="Carteira recorrente","Operação recorrente",IF(P70="PCMSO","Projetos PCMSO",IF(P70="eSocial / Psicossocial","Projetos eSocial/Psicossocial","Projetos / Laudos / Avulsos")))) | R70: =IF(C70="","",IF(ISNUMBER(SEARCH("PCMSO",C70)),"Título com PCMSO no nome",IF(OR(ISNUMBER(SEARCH("E-SOCIAL",C70)),ISNUMBER(SEARCH("PSICOSOCIAL",C70))),"Título com eSocial/Psicossocial no nome",IF(O70="Receita recorrente","Tipo DRE recorrente","Extra sem palavra-chave específica")))) | S70: =IFERROR(VLOOKUP($A70,'13. Mapa Títulos-Receita'!$A$8:$P$1000,4,FALSE),"") | T70: =IFERROR(VLOOKUP($A70,'13. Mapa Títulos-Receita'!$A$8:$P$1000,5,FALSE),"") | U70: =IFERROR(VLOOKUP($A70,'13. Mapa Títulos-Receita'!$A$8:$P$1000,6,FALSE),"") | V70: =IFERROR(VLOOKUP($A70,'13. Mapa Títulos-Receita'!$A$8:$P$1000,7,FALSE),"") | W70: =IFERROR(VLOOKUP($A70,'13. Mapa Títulos-Receita'!$A$8:$P$1000,8,FALSE),"") | X70: =IFERROR(VLOOKUP($A70,'13. Mapa Títulos-Receita'!$A$8:$P$1000,9,FALSE),"") | Y70: =IFERROR(VLOOKUP($A70,'13. Mapa Títulos-Receita'!$A$8:$P$1000,10,FALSE),"") | Z70: =IFERROR(VLOOKUP($A70,'13. Mapa Títulos-Receita'!$A$8:$P$1000,11,FALSE),"") | AA70: =IFERROR(VLOOKUP($A70,'13. Mapa Títulos-Receita'!$A$8:$P$1000,12,FALSE),"") | AB70: =IFERROR(VLOOKUP($A70,'13. Mapa Títulos-Receita'!$A$8:$P$1000,13,FALSE),"") | AC70: =IFERROR(VLOOKUP($A70,'13. Mapa Títulos-Receita'!$A$8:$P$1000,14,FALSE),"") | AD70: =IFERROR(VLOOKUP($A70,'13. Mapa Títulos-Receita'!$A$8:$P$1000,15,FALSE),"") | AE70: =IFERROR(VLOOKUP($A70,'13. Mapa Títulos-Receita'!$A$8:$P$1000,16,FALSE),"")
A71: =IF(C71="","", "CR-"&TEXT(ROW()-7,"000")) | J71: =IF(H71="","",IF(I71>=H71,"Recebido",IF($B$4>E71,"Vencido","Aberto"))) | K71: =IF(J71="","",IF(OR(J71="Recebido",F71=""),MAX(0,F71-E71),MAX(0,$B$4-E71))) | L71: =IF(K71="","",IF(K71=0,"Em dia",IF(K71<=30,"1-30 dias",IF(K71<=60,"31-60 dias",IF(K71<=90,"61-90 dias",">90 dias"))))) | P71: =IF(C71="","",IF(ISNUMBER(SEARCH("PCMSO",C71)),"PCMSO",IF(OR(ISNUMBER(SEARCH("E-SOCIAL",C71)),ISNUMBER(SEARCH("PSICOSOCIAL",C71))),"eSocial / Psicossocial",IF(O71="Receita recorrente","Carteira recorrente","Projetos / Laudos / Avulsos")))) | Q71: =IF(P71="","",IF(P71="Carteira recorrente","Operação recorrente",IF(P71="PCMSO","Projetos PCMSO",IF(P71="eSocial / Psicossocial","Projetos eSocial/Psicossocial","Projetos / Laudos / Avulsos")))) | R71: =IF(C71="","",IF(ISNUMBER(SEARCH("PCMSO",C71)),"Título com PCMSO no nome",IF(OR(ISNUMBER(SEARCH("E-SOCIAL",C71)),ISNUMBER(SEARCH("PSICOSOCIAL",C71))),"Título com eSocial/Psicossocial no nome",IF(O71="Receita recorrente","Tipo DRE recorrente","Extra sem palavra-chave específica")))) | S71: =IFERROR(VLOOKUP($A71,'13. Mapa Títulos-Receita'!$A$8:$P$1000,4,FALSE),"") | T71: =IFERROR(VLOOKUP($A71,'13. Mapa Títulos-Receita'!$A$8:$P$1000,5,FALSE),"") | U71: =IFERROR(VLOOKUP($A71,'13. Mapa Títulos-Receita'!$A$8:$P$1000,6,FALSE),"") | V71: =IFERROR(VLOOKUP($A71,'13. Mapa Títulos-Receita'!$A$8:$P$1000,7,FALSE),"") | W71: =IFERROR(VLOOKUP($A71,'13. Mapa Títulos-Receita'!$A$8:$P$1000,8,FALSE),"") | X71: =IFERROR(VLOOKUP($A71,'13. Mapa Títulos-Receita'!$A$8:$P$1000,9,FALSE),"") | Y71: =IFERROR(VLOOKUP($A71,'13. Mapa Títulos-Receita'!$A$8:$P$1000,10,FALSE),"") | Z71: =IFERROR(VLOOKUP($A71,'13. Mapa Títulos-Receita'!$A$8:$P$1000,11,FALSE),"") | AA71: =IFERROR(VLOOKUP($A71,'13. Mapa Títulos-Receita'!$A$8:$P$1000,12,FALSE),"") | AB71: =IFERROR(VLOOKUP($A71,'13. Mapa Títulos-Receita'!$A$8:$P$1000,13,FALSE),"") | AC71: =IFERROR(VLOOKUP($A71,'13. Mapa Títulos-Receita'!$A$8:$P$1000,14,FALSE),"") | AD71: =IFERROR(VLOOKUP($A71,'13. Mapa Títulos-Receita'!$A$8:$P$1000,15,FALSE),"") | AE71: =IFERROR(VLOOKUP($A71,'13. Mapa Títulos-Receita'!$A$8:$P$1000,16,FALSE),"")
A72: =IF(C72="","", "CR-"&TEXT(ROW()-7,"000")) | J72: =IF(H72="","",IF(I72>=H72,"Recebido",IF($B$4>E72,"Vencido","Aberto"))) | K72: =IF(J72="","",IF(OR(J72="Recebido",F72=""),MAX(0,F72-E72),MAX(0,$B$4-E72))) | L72: =IF(K72="","",IF(K72=0,"Em dia",IF(K72<=30,"1-30 dias",IF(K72<=60,"31-60 dias",IF(K72<=90,"61-90 dias",">90 dias"))))) | P72: =IF(C72="","",IF(ISNUMBER(SEARCH("PCMSO",C72)),"PCMSO",IF(OR(ISNUMBER(SEARCH("E-SOCIAL",C72)),ISNUMBER(SEARCH("PSICOSOCIAL",C72))),"eSocial / Psicossocial",IF(O72="Receita recorrente","Carteira recorrente","Projetos / Laudos / Avulsos")))) | Q72: =IF(P72="","",IF(P72="Carteira recorrente","Operação recorrente",IF(P72="PCMSO","Projetos PCMSO",IF(P72="eSocial / Psicossocial","Projetos eSocial/Psicossocial","Projetos / Laudos / Avulsos")))) | R72: =IF(C72="","",IF(ISNUMBER(SEARCH("PCMSO",C72)),"Título com PCMSO no nome",IF(OR(ISNUMBER(SEARCH("E-SOCIAL",C72)),ISNUMBER(SEARCH("PSICOSOCIAL",C72))),"Título com eSocial/Psicossocial no nome",IF(O72="Receita recorrente","Tipo DRE recorrente","Extra sem palavra-chave específica")))) | S72: =IFERROR(VLOOKUP($A72,'13. Mapa Títulos-Receita'!$A$8:$P$1000,4,FALSE),"") | T72: =IFERROR(VLOOKUP($A72,'13. Mapa Títulos-Receita'!$A$8:$P$1000,5,FALSE),"") | U72: =IFERROR(VLOOKUP($A72,'13. Mapa Títulos-Receita'!$A$8:$P$1000,6,FALSE),"") | V72: =IFERROR(VLOOKUP($A72,'13. Mapa Títulos-Receita'!$A$8:$P$1000,7,FALSE),"") | W72: =IFERROR(VLOOKUP($A72,'13. Mapa Títulos-Receita'!$A$8:$P$1000,8,FALSE),"") | X72: =IFERROR(VLOOKUP($A72,'13. Mapa Títulos-Receita'!$A$8:$P$1000,9,FALSE),"") | Y72: =IFERROR(VLOOKUP($A72,'13. Mapa Títulos-Receita'!$A$8:$P$1000,10,FALSE),"") | Z72: =IFERROR(VLOOKUP($A72,'13. Mapa Títulos-Receita'!$A$8:$P$1000,11,FALSE),"") | AA72: =IFERROR(VLOOKUP($A72,'13. Mapa Títulos-Receita'!$A$8:$P$1000,12,FALSE),"") | AB72: =IFERROR(VLOOKUP($A72,'13. Mapa Títulos-Receita'!$A$8:$P$1000,13,FALSE),"") | AC72: =IFERROR(VLOOKUP($A72,'13. Mapa Títulos-Receita'!$A$8:$P$1000,14,FALSE),"") | AD72: =IFERROR(VLOOKUP($A72,'13. Mapa Títulos-Receita'!$A$8:$P$1000,15,FALSE),"") | AE72: =IFERROR(VLOOKUP($A72,'13. Mapa Títulos-Receita'!$A$8:$P$1000,16,FALSE),"")
... A1000: =IF(C1000="","", "CR-"&TEXT(ROW()-7,"000")) | J1000: =IF(H1000="","",IF(I1000>=H1000,"Recebido",IF($B$4>E1000,"Vencido","Aberto"))) | K1000: =IF(J1000="","",IF(OR(J1000="Recebido",F1000=""),MAX(0,F1000-E1000),MAX(0,$B$4-E1000))) | L1000: =IF(K1000="","",IF(K1000=0,"Em dia",IF(K1000<=30,"1-30 dias",IF(K1000<=60,"31-60 dias",IF(K1000<=90,"61-90 dias",">90 dias"))))) | P1000: =IF(C1000="","",IF(ISNUMBER(SEARCH("PCMSO",C1000)),"PCMSO",IF(OR(ISNUMBER(SEARCH("E-SOCIAL",C1000)),ISNUMBER(SEARCH("PSICOSOCIAL",C1000))),"eSocial / Psicossocial",IF(O1000="Receita recorrente","Carteira recorrente","Projetos / Laudos / Avulsos")))) | Q1000: =IF(P1000="","",IF(P1000="Carteira recorrente","Operação recorrente",IF(P1000="PCMSO","Projetos PCMSO",IF(P1000="eSocial / Psicossocial","Projetos eSocial/Psicossocial","Projetos / Laudos / Avulsos")))) | R1000: =IF(C1000="","",IF(ISNUMBER(SEARCH("PCMSO",C1000)),"Título com PCMSO no nome",IF(OR(ISNUMBER(SEARCH("E-SOCIAL",C1000)),ISNUMBER(SEARCH("PSICOSOCIAL",C1000))),"Título com eSocial/Psicossocial no nome",IF(O1000="Receita recorrente","Tipo DRE recorrente","Extra sem palavra-chave específica")))) | S1000: =IFERROR(VLOOKUP($A1000,'13. Mapa Títulos-Receita'!$A$8:$P$1000,4,FALSE),"") | T1000: =IFERROR(VLOOKUP($A1000,'13. Mapa Títulos-Receita'!$A$8:$P$1000,5,FALSE),"") | U1000: =IFERROR(VLOOKUP($A1000,'13. Mapa Títulos-Receita'!$A$8:$P$1000,6,FALSE),"") | V1000: =IFERROR(VLOOKUP($A1000,'13. Mapa Títulos-Receita'!$A$8:$P$1000,7,FALSE),"") | W1000: =IFERROR(VLOOKUP($A1000,'13. Mapa Títulos-Receita'!$A$8:$P$1000,8,FALSE),"") | X1000: =IFERROR(VLOOKUP($A1000,'13. Mapa Títulos-Receita'!$A$8:$P$1000,9,FALSE),"") | Y1000: =IFERROR(VLOOKUP($A1000,'13. Mapa Títulos-Receita'!$A$8:$P$1000,10,FALSE),"") | Z1000: =IFERROR(VLOOKUP($A1000,'13. Mapa Títulos-Receita'!$A$8:$P$1000,11,FALSE),"") | AA1000: =IFERROR(VLOOKUP($A1000,'13. Mapa Títulos-Receita'!$A$8:$P$1000,12,FALSE),"") | AB1000: =IFERROR(VLOOKUP($A1000,'13. Mapa Títulos-Receita'!$A$8:$P$1000,13,FALSE),"") | AC1000: =IFERROR(VLOOKUP($A1000,'13. Mapa Títulos-Receita'!$A$8:$P$1000,14,FALSE),"") | AD1000: =IFERROR(VLOOKUP($A1000,'13. Mapa Títulos-Receita'!$A$8:$P$1000,15,FALSE),"") | AE1000: =IFERROR(VLOOKUP($A1000,'13. Mapa Títulos-Receita'!$A$8:$P$1000,16,FALSE),"")
A1001: RESUMO DO BLOCO 2
A1002: Títulos lançados | B1002: =COUNTIF(C8:C1000,"<>")
A1003: Carteira nominal | B1003: =SUM(H8:H1000)
A1004: Recebido | B1004: =SUM(I8:I1000)
A1005: Em aberto | B1005: =SUMIFS(H8:H1000,J8:J1000,"<>Recebido",J8:J1000,"<>Cancelado")
A1006: Vencido | B1006: =SUMIFS(H8:H1000,J8:J1000,"Vencido")

Sheet 3. Contas a Pagar
A1: 3. CONTAS A PAGAR — OBRIGAÇÕES E SAÍDAS
A2: Cada linha representa uma obrigação. Agora o CP também está amarrado à Base_Custos com centro de custo real, grupo gerencial e natureza gerencial.
A4: BASE OPERACIONAL
A5: ID gasto | B5: Competência | C5: Fornecedor | D5: Categoria | E5: Centro de custo real | F5: Emissão | G5: Vencimento | H5: Pagamento | I5: Valor | J5: Status | K5: Tipo | L5: Observação | M5: Grupo gerencial (CSV) | N5: Natureza gerencial | O5: % estrutura base | P5: Vínculo c/ base | Q5: Nota gerencial | R5: Linha DRE | S5: Nível DRE | T5: Alocação p/ linha de serviço | U5: Critério alocação serviço
A6: CP-001 | B6: =IF(F6="","",DATE(YEAR(F6),MONTH(F6),1)) | C6: VISA VALE | D6: Despesa fixa | E6: =IF(C6="","",IFERROR(INDEX('6. Base de Custos'!$M$8:$M$42,MATCH(C6,'6. Base de Custos'!$L$8:$L$42,0)),"Não classificado")) | F6: 46083 | G6: 46083 | H6: 46112 | I6: 891.46 | J6: Pago | K6: Fixo | L6: Origem: CP mar/2026. Data de pagamento não informada no PDF; alocada em 31/03 como proxy mensal. | M6: =IF(C6="","",IFERROR(INDEX('6. Base de Custos'!$N$8:$N$42,MATCH(C6,'6. Base de Custos'!$L$8:$L$42,0)),"Não classificado")) | N6: =IF(C6="","",IFERROR(INDEX('6. Base de Custos'!$O$8:$O$42,MATCH(C6,'6. Base de Custos'!$L$8:$L$42,0)),"Revisar")) | O6: =IF(M6="","",IFERROR(VLOOKUP(M6,'6. Base de Custos'!$H$12:$J$18,3,FALSE),0)) | P6: =IF(C6="","",IFERROR(INDEX('6. Base de Custos'!$P$8:$P$42,MATCH(C6,'6. Base de Custos'!$L$8:$L$42,0)),"Revisar")) | Q6: =IF(C6="","",IFERROR(INDEX('6. Base de Custos'!$Q$8:$Q$42,MATCH(C6,'6. Base de Custos'!$L$8:$L$42,0)),"")) | R6: (-) Despesas comerciais e deslocamento | S6: Despesa operacional | T6: =IF(C6="","",IF(R6="(-) Custos diretos dos serviços",IF(ISNUMBER(SEARCH("PCMSO",C6)),"PCMSO",IF(OR(ISNUMBER(SEARCH("SGS",C6)),ISNUMBER(SEARCH("CASTRO NAVES",C6))),"Projetos / Laudos / Avulsos","Projetos / Laudos / Avulsos")),"Rateio pela receita bruta")) | U6: =IF(C6="","",IF(R6="(-) Custos diretos dos serviços","Direto por fornecedor/natureza do gasto","Rateio proporcional à receita bruta da linha de serviço"))
A7: CP-002 | B7: =IF(F7="","",DATE(YEAR(F7),MONTH(F7),1)) | C7: FAXINEIRA | D7: Despesa fixa | E7: =IF(C7="","",IFERROR(INDEX('6. Base de Custos'!$M$8:$M$42,MATCH(C7,'6. Base de Custos'!$L$8:$L$42,0)),"Não classificado")) | F7: 46086 | G7: 46086 | H7: 46112 | I7: 375 | J7: Pago | K7: Fixo | L7: Origem: CP mar/2026. Data de pagamento não informada no PDF; alocada em 31/03 como proxy mensal. | M7: =IF(C7="","",IFERROR(INDEX('6. Base de Custos'!$N$8:$N$42,MATCH(C7,'6. Base de Custos'!$L$8:$L$42,0)),"Não classificado")) | N7: =IF(C7="","",IFERROR(INDEX('6. Base de Custos'!$O$8:$O$42,MATCH(C7,'6. Base de Custos'!$L$8:$L$42,0)),"Revisar")) | O7: =IF(M7="","",IFERROR(VLOOKUP(M7,'6. Base de Custos'!$H$12:$J$18,3,FALSE),0)) | P7: =IF(C7="","",IFERROR(INDEX('6. Base de Custos'!$P$8:$P$42,MATCH(C7,'6. Base de Custos'!$L$8:$L$42,0)),"Revisar")) | Q7: =IF(C7="","",IFERROR(INDEX('6. Base de Custos'!$Q$8:$Q$42,MATCH(C7,'6. Base de Custos'!$L$8:$L$42,0)),"")) | R7: (-) Despesas com pessoal e equipe | S7: Despesa operacional | T7: =IF(C7="","",IF(R7="(-) Custos diretos dos serviços",IF(ISNUMBER(SEARCH("PCMSO",C7)),"PCMSO",IF(OR(ISNUMBER(SEARCH("SGS",C7)),ISNUMBER(SEARCH("CASTRO NAVES",C7))),"Projetos / Laudos / Avulsos","Projetos / Laudos / Avulsos")),"Rateio pela receita bruta")) | U7: =IF(C7="","",IF(R7="(-) Custos diretos dos serviços","Direto por fornecedor/natureza do gasto","Rateio proporcional à receita bruta da linha de serviço"))
A8: CP-003 | B8: =IF(F8="","",DATE(YEAR(F8),MONTH(F8),1)) | C8: FERNANDA | D8: Despesa fixa | E8: =IF(C8="","",IFERROR(INDEX('6. Base de Custos'!$M$8:$M$42,MATCH(C8,'6. Base de Custos'!$L$8:$L$42,0)),"Não classificado")) | F8: 46086 | G8: 46086 | H8: 46112 | I8: 3008.07 | J8: Pago | K8: Fixo | L8: Origem: CP mar/2026. Data de pagamento não informada no PDF; alocada em 31/03 como proxy mensal. | M8: =IF(C8="","",IFERROR(INDEX('6. Base de Custos'!$N$8:$N$42,MATCH(C8,'6. Base de Custos'!$L$8:$L$42,0)),"Não classificado")) | N8: =IF(C8="","",IFERROR(INDEX('6. Base de Custos'!$O$8:$O$42,MATCH(C8,'6. Base de Custos'!$L$8:$L$42,0)),"Revisar")) | O8: =IF(M8="","",IFERROR(VLOOKUP(M8,'6. Base de Custos'!$H$12:$J$18,3,FALSE),0)) | P8: =IF(C8="","",IFERROR(INDEX('6. Base de Custos'!$P$8:$P$42,MATCH(C8,'6. Base de Custos'!$L$8:$L$42,0)),"Revisar")) | Q8: =IF(C8="","",IFERROR(INDEX('6. Base de Custos'!$Q$8:$Q$42,MATCH(C8,'6. Base de Custos'!$L$8:$L$42,0)),"")) | R8: (-) Despesas com pessoal e equipe | S8: Despesa operacional | T8: =IF(C8="","",IF(R8="(-) Custos diretos dos serviços",IF(ISNUMBER(SEARCH("PCMSO",C8)),"PCMSO",IF(OR(ISNUMBER(SEARCH("SGS",C8)),ISNUMBER(SEARCH("CASTRO NAVES",C8))),"Projetos / Laudos / Avulsos","Projetos / Laudos / Avulsos")),"Rateio pela receita bruta")) | U8: =IF(C8="","",IF(R8="(-) Custos diretos dos serviços","Direto por fornecedor/natureza do gasto","Rateio proporcional à receita bruta da linha de serviço"))
A9: CP-004 | B9: =IF(F9="","",DATE(YEAR(F9),MONTH(F9),1)) | C9: EDMILSON | D9: Despesa fixa | E9: =IF(C9="","",IFERROR(INDEX('6. Base de Custos'!$M$8:$M$42,MATCH(C9,'6. Base de Custos'!$L$8:$L$42,0)),"Não classificado")) | F9: 46085 | G9: 46085 | H9: 46112 | I9: 3008.07 | J9: Pago | K9: Fixo | L9: Origem: CP mar/2026. Data de pagamento não informada no PDF; alocada em 31/03 como proxy mensal. | M9: =IF(C9="","",IFERROR(INDEX('6. Base de Custos'!$N$8:$N$42,MATCH(C9,'6. Base de Custos'!$L$8:$L$42,0)),"Não classificado")) | N9: =IF(C9="","",IFERROR(INDEX('6. Base de Custos'!$O$8:$O$42,MATCH(C9,'6. Base de Custos'!$L$8:$L$42,0)),"Revisar")) | O9: =IF(M9="","",IFERROR(VLOOKUP(M9,'6. Base de Custos'!$H$12:$J$18,3,FALSE),0)) | P9: =IF(C9="","",IFERROR(INDEX('6. Base de Custos'!$P$8:$P$42,MATCH(C9,'6. Base de Custos'!$L$8:$L$42,0)),"Revisar")) | Q9: =IF(C9="","",IFERROR(INDEX('6. Base de Custos'!$Q$8:$Q$42,MATCH(C9,'6. Base de Custos'!$L$8:$L$42,0)),"")) | R9: (-) Despesas com pessoal e equipe | S9: Despesa operacional | T9: =IF(C9="","",IF(R9="(-) Custos diretos dos serviços",IF(ISNUMBER(SEARCH("PCMSO",C9)),"PCMSO",IF(OR(ISNUMBER(SEARCH("SGS",C9)),ISNUMBER(SEARCH("CASTRO NAVES",C9))),"Projetos / Laudos / Avulsos","Projetos / Laudos / Avulsos")),"Rateio pela receita bruta")) | U9: =IF(C9="","",IF(R9="(-) Custos diretos dos serviços","Direto por fornecedor/natureza do gasto","Rateio proporcional à receita bruta da linha de serviço"))
A10: CP-005 | B10: =IF(F10="","",DATE(YEAR(F10),MONTH(F10),1)) | C10: GASOLINA - FERNANDA | D10: Despesa fixa | E10: =IF(C10="","",IFERROR(INDEX('6. Base de Custos'!$M$8:$M$42,MATCH(C10,'6. Base de Custos'!$L$8:$L$42,0)),"Não classificado")) | F10: 46086 | G10: 46086 | H10: 46112 | I10: 250.8 | J10: Pago | K10: Fixo | L10: Origem: CP mar/2026. Data de pagamento não informada no PDF; alocada em 31/03 como proxy mensal. | M10: =IF(C10="","",IFERROR(INDEX('6. Base de Custos'!$N$8:$N$42,MATCH(C10,'6. Base de Custos'!$L$8:$L$42,0)),"Não classificado")) | N10: =IF(C10="","",IFERROR(INDEX('6. Base de Custos'!$O$8:$O$42,MATCH(C10,'6. Base de Custos'!$L$8:$L$42,0)),"Revisar")) | O10: =IF(M10="","",IFERROR(VLOOKUP(M10,'6. Base de Custos'!$H$12:$J$18,3,FALSE),0)) | P10: =IF(C10="","",IFERROR(INDEX('6. Base de Custos'!$P$8:$P$42,MATCH(C10,'6. Base de Custos'!$L$8:$L$42,0)),"Revisar")) | Q10: =IF(C10="","",IFERROR(INDEX('6. Base de Custos'!$Q$8:$Q$42,MATCH(C10,'6. Base de Custos'!$L$8:$L$42,0)),"")) | R10: (-) Despesas comerciais e deslocamento | S10: Despesa operacional | T10: =IF(C10="","",IF(R10="(-) Custos diretos dos serviços",IF(ISNUMBER(SEARCH("PCMSO",C10)),"PCMSO",IF(OR(ISNUMBER(SEARCH("SGS",C10)),ISNUMBER(SEARCH("CASTRO NAVES",C10))),"Projetos / Laudos / Avulsos","Projetos / Laudos / Avulsos")),"Rateio pela receita bruta")) | U10: =IF(C10="","",IF(R10="(-) Custos diretos dos serviços","Direto por fornecedor/natureza do gasto","Rateio proporcional à receita bruta da linha de serviço"))
A11: CP-006 | B11: =IF(F11="","",DATE(YEAR(F11),MONTH(F11),1)) | C11: ENGENHEIRO KLEBER | D11: Despesa fixa | E11: =IF(C11="","",IFERROR(INDEX('6. Base de Custos'!$M$8:$M$42,MATCH(C11,'6. Base de Custos'!$L$8:$L$42,0)),"Não classificado")) | F11: 46086 | G11: 46086 | H11: 46112 | I11: 4300 | J11: Pago | K11: Fixo | L11: Origem: CP mar/2026. Data de pagamento não informada no PDF; alocada em 31/03 como proxy mensal. | M11: =IF(C11="","",IFERROR(INDEX('6. Base de Custos'!$N$8:$N$42,MATCH(C11,'6. Base de Custos'!$L$8:$L$42,0)),"Não classificado")) | N11: =IF(C11="","",IFERROR(INDEX('6. Base de Custos'!$O$8:$O$42,MATCH(C11,'6. Base de Custos'!$L$8:$L$42,0)),"Revisar")) | O11: =IF(M11="","",IFERROR(VLOOKUP(M11,'6. Base de Custos'!$H$12:$J$18,3,FALSE),0)) | P11: =IF(C11="","",IFERROR(INDEX('6. Base de Custos'!$P$8:$P$42,MATCH(C11,'6. Base de Custos'!$L$8:$L$42,0)),"Revisar")) | Q11: =IF(C11="","",IFERROR(INDEX('6. Base de Custos'!$Q$8:$Q$42,MATCH(C11,'6. Base de Custos'!$L$8:$L$42,0)),"")) | R11: (-) Despesas com pessoal e equipe | S11: Despesa operacional | T11: =IF(C11="","",IF(R11="(-) Custos diretos dos serviços",IF(ISNUMBER(SEARCH("PCMSO",C11)),"PCMSO",IF(OR(ISNUMBER(SEARCH("SGS",C11)),ISNUMBER(SEARCH("CASTRO NAVES",C11))),"Projetos / Laudos / Avulsos","Projetos / Laudos / Avulsos")),"Rateio pela receita bruta")) | U11: =IF(C11="","",IF(R11="(-) Custos diretos dos serviços","Direto por fornecedor/natureza do gasto","Rateio proporcional à receita bruta da linha de serviço"))
A12: CP-007 | B12: =IF(F12="","",DATE(YEAR(F12),MONTH(F12),1)) | C12: DMAE | D12: Despesa fixa | E12: =IF(C12="","",IFERROR(INDEX('6. Base de Custos'!$M$8:$M$42,MATCH(C12,'6. Base de Custos'!$L$8:$L$42,0)),"Não classificado")) | F12: 46086 | G12: 46086 | H12: 46112 | I12: 157.04 | J12: Pago | K12: Fixo | L12: Origem: CP mar/2026. Data de pagamento não informada no PDF; alocada em 31/03 como proxy mensal. | M12: =IF(C12="","",IFERROR(INDEX('6. Base de Custos'!$N$8:$N$42,MATCH(C12,'6. Base de Custos'!$L$8:$L$42,0)),"Não classificado")) | N12: =IF(C12="","",IFERROR(INDEX('6. Base de Custos'!$O$8:$O$42,MATCH(C12,'6. Base de Custos'!$L$8:$L$42,0)),"Revisar")) | O12: =IF(M12="","",IFERROR(VLOOKUP(M12,'6. Base de Custos'!$H$12:$J$18,3,FALSE),0)) | P12: =IF(C12="","",IFERROR(INDEX('6. Base de Custos'!$P$8:$P$42,MATCH(C12,'6. Base de Custos'!$L$8:$L$42,0)),"Revisar")) | Q12: =IF(C12="","",IFERROR(INDEX('6. Base de Custos'!$Q$8:$Q$42,MATCH(C12,'6. Base de Custos'!$L$8:$L$42,0)),"")) | R12: (-) Despesas operacionais e infraestrutura | S12: Despesa operacional | T12: =IF(C12="","",IF(R12="(-) Custos diretos dos serviços",IF(ISNUMBER(SEARCH("PCMSO",C12)),"PCMSO",IF(OR(ISNUMBER(SEARCH("SGS",C12)),ISNUMBER(SEARCH("CASTRO NAVES",C12))),"Projetos / Laudos / Avulsos","Projetos / Laudos / Avulsos")),"Rateio pela receita bruta")) | U12: =IF(C12="","",IF(R12="(-) Custos diretos dos serviços","Direto por fornecedor/natureza do gasto","Rateio proporcional à receita bruta da linha de serviço"))
A13: CP-008 | B13: =IF(F13="","",DATE(YEAR(F13),MONTH(F13),1)) | C13: MERCADO OPEN | D13: Despesa fixa | E13: =IF(C13="","",IFERROR(INDEX('6. Base de Custos'!$M$8:$M$42,MATCH(C13,'6. Base de Custos'!$L$8:$L$42,0)),"Não classificado")) | F13: 46086 | G13: 46086 | H13: 46112 | I13: 404 | J13: Pago | K13: Fixo | L13: Origem: CP mar/2026. Data de pagamento não informada no PDF; alocada em 31/03 como proxy mensal. | M13: =IF(C13="","",IFERROR(INDEX('6. Base de Custos'!$N$8:$N$42,MATCH(C13,'6. Base de Custos'!$L$8:$L$42,0)),"Não classificado")) | N13: =IF(C13="","",IFERROR(INDEX('6. Base de Custos'!$O$8:$O$42,MATCH(C13,'6. Base de Custos'!$L$8:$L$42,0)),"Revisar")) | O13: =IF(M13="","",IFERROR(VLOOKUP(M13,'6. Base de Custos'!$H$12:$J$18,3,FALSE),0)) | P13: =IF(C13="","",IFERROR(INDEX('6. Base de Custos'!$P$8:$P$42,MATCH(C13,'6. Base de Custos'!$L$8:$L$42,0)),"Revisar")) | Q13: =IF(C13="","",IFERROR(INDEX('6. Base de Custos'!$Q$8:$Q$42,MATCH(C13,'6. Base de Custos'!$L$8:$L$42,0)),"")) | R13: (-) Despesas operacionais e infraestrutura | S13: Despesa operacional | T13: =IF(C13="","",IF(R13="(-) Custos diretos dos serviços",IF(ISNUMBER(SEARCH("PCMSO",C13)),"PCMSO",IF(OR(ISNUMBER(SEARCH("SGS",C13)),ISNUMBER(SEARCH("CASTRO NAVES",C13))),"Projetos / Laudos / Avulsos","Projetos / Laudos / Avulsos")),"Rateio pela receita bruta")) | U13: =IF(C13="","",IF(R13="(-) Custos diretos dos serviços","Direto por fornecedor/natureza do gasto","Rateio proporcional à receita bruta da linha de serviço"))
A14: CP-009 | B14: =IF(F14="","",DATE(YEAR(F14),MONTH(F14),1)) | C14: CEMIG | D14: Despesa fixa | E14: =IF(C14="","",IFERROR(INDEX('6. Base de Custos'!$M$8:$M$42,MATCH(C14,'6. Base de Custos'!$L$8:$L$42,0)),"Não classificado")) | F14: 46089 | G14: 46089 | H14: 46112 | I14: 56.27 | J14: Pago | K14: Fixo | L14: Origem: CP mar/2026. Data de pagamento não informada no PDF; alocada em 31/03 como proxy mensal. | M14: =IF(C14="","",IFERROR(INDEX('6. Base de Custos'!$N$8:$N$42,MATCH(C14,'6. Base de Custos'!$L$8:$L$42,0)),"Não classificado")) | N14: =IF(C14="","",IFERROR(INDEX('6. Base de Custos'!$O$8:$O$42,MATCH(C14,'6. Base de Custos'!$L$8:$L$42,0)),"Revisar")) | O14: =IF(M14="","",IFERROR(VLOOKUP(M14,'6. Base de Custos'!$H$12:$J$18,3,FALSE),0)) | P14: =IF(C14="","",IFERROR(INDEX('6. Base de Custos'!$P$8:$P$42,MATCH(C14,'6. Base de Custos'!$L$8:$L$42,0)),"Revisar")) | Q14: =IF(C14="","",IFERROR(INDEX('6. Base de Custos'!$Q$8:$Q$42,MATCH(C14,'6. Base de Custos'!$L$8:$L$42,0)),"")) | R14: (-) Despesas operacionais e infraestrutura | S14: Despesa operacional | T14: =IF(C14="","",IF(R14="(-) Custos diretos dos serviços",IF(ISNUMBER(SEARCH("PCMSO",C14)),"PCMSO",IF(OR(ISNUMBER(SEARCH("SGS",C14)),ISNUMBER(SEARCH("CASTRO NAVES",C14))),"Projetos / Laudos / Avulsos","Projetos / Laudos / Avulsos")),"Rateio pela receita bruta")) | U14: =IF(C14="","",IF(R14="(-) Custos diretos dos serviços","Direto por fornecedor/natureza do gasto","Rateio proporcional à receita bruta da linha de serviço"))
A15: CP-010 | B15: =IF(F15="","",DATE(YEAR(F15),MONTH(F15),1)) | C15: CEMIG | D15: Despesa fixa | E15: =IF(C15="","",IFERROR(INDEX('6. Base de Custos'!$M$8:$M$42,MATCH(C15,'6. Base de Custos'!$L$8:$L$42,0)),"Não classificado")) | F15: 46089 | G15: 46089 | H15: 46112 | I15: 165.32 | J15: Pago | K15: Fixo | L15: Origem: CP mar/2026. Data de pagamento não informada no PDF; alocada em 31/03 como proxy mensal. | M15: =IF(C15="","",IFERROR(INDEX('6. Base de Custos'!$N$8:$N$42,MATCH(C15,'6. Base de Custos'!$L$8:$L$42,0)),"Não classificado")) | N15: =IF(C15="","",IFERROR(INDEX('6. Base de Custos'!$O$8:$O$42,MATCH(C15,'6. Base de Custos'!$L$8:$L$42,0)),"Revisar")) | O15: =IF(M15="","",IFERROR(VLOOKUP(M15,'6. Base de Custos'!$H$12:$J$18,3,FALSE),0)) | P15: =IF(C15="","",IFERROR(INDEX('6. Base de Custos'!$P$8:$P$42,MATCH(C15,'6. Base de Custos'!$L$8:$L$42,0)),"Revisar")) | Q15: =IF(C15="","",IFERROR(INDEX('6. Base de Custos'!$Q$8:$Q$42,MATCH(C15,'6. Base de Custos'!$L$8:$L$42,0)),"")) | R15: (-) Despesas operacionais e infraestrutura | S15: Despesa operacional | T15: =IF(C15="","",IF(R15="(-) Custos diretos dos serviços",IF(ISNUMBER(SEARCH("PCMSO",C15)),"PCMSO",IF(OR(ISNUMBER(SEARCH("SGS",C15)),ISNUMBER(SEARCH("CASTRO NAVES",C15))),"Projetos / Laudos / Avulsos","Projetos / Laudos / Avulsos")),"Rateio pela receita bruta")) | U15: =IF(C15="","",IF(R15="(-) Custos diretos dos serviços","Direto por fornecedor/natureza do gasto","Rateio proporcional à receita bruta da linha de serviço"))
A16: CP-011 | B16: =IF(F16="","",DATE(YEAR(F16),MONTH(F16),1)) | C16: CONTADORA | D16: Despesa fixa | E16: =IF(C16="","",IFERROR(INDEX('6. Base de Custos'!$M$8:$M$42,MATCH(C16,'6. Base de Custos'!$L$8:$L$42,0)),"Não classificado")) | F16: 46091 | G16: 46091 | H16: 46112 | I16: 1621 | J16: Pago | K16: Fixo | L16: Origem: CP mar/2026. Data de pagamento não informada no PDF; alocada em 31/03 como proxy mensal. | M16: =IF(C16="","",IFERROR(INDEX('6. Base de Custos'!$N$8:$N$42,MATCH(C16,'6. Base de Custos'!$L$8:$L$42,0)),"Não classificado")) | N16: =IF(C16="","",IFERROR(INDEX('6. Base de Custos'!$O$8:$O$42,MATCH(C16,'6. Base de Custos'!$L$8:$L$42,0)),"Revisar")) | O16: =IF(M16="","",IFERROR(VLOOKUP(M16,'6. Base de Custos'!$H$12:$J$18,3,FALSE),0)) | P16: =IF(C16="","",IFERROR(INDEX('6. Base de Custos'!$P$8:$P$42,MATCH(C16,'6. Base de Custos'!$L$8:$L$42,0)),"Revisar")) | Q16: =IF(C16="","",IFERROR(INDEX('6. Base de Custos'!$Q$8:$Q$42,MATCH(C16,'6. Base de Custos'!$L$8:$L$42,0)),"")) | R16: (-) Despesas com tecnologia e contábil | S16: Despesa operacional | T16: =IF(C16="","",IF(R16="(-) Custos diretos dos serviços",IF(ISNUMBER(SEARCH("PCMSO",C16)),"PCMSO",IF(OR(ISNUMBER(SEARCH("SGS",C16)),ISNUMBER(SEARCH("CASTRO NAVES",C16))),"Projetos / Laudos / Avulsos","Projetos / Laudos / Avulsos")),"Rateio pela receita bruta")) | U16: =IF(C16="","",IF(R16="(-) Custos diretos dos serviços","Direto por fornecedor/natureza do gasto","Rateio proporcional à receita bruta da linha de serviço"))
A17: CP-012 | B17: =IF(F17="","",DATE(YEAR(F17),MONTH(F17),1)) | C17: SISTEMA ESO | D17: Despesa fixa | E17: =IF(C17="","",IFERROR(INDEX('6. Base de Custos'!$M$8:$M$42,MATCH(C17,'6. Base de Custos'!$L$8:$L$42,0)),"Não classificado")) | F17: 46091 | G17: 46091 | H17: 46112 | I17: 600 | J17: Pago | K17: Fixo | L17: Origem: CP mar/2026. Data de pagamento não informada no PDF; alocada em 31/03 como proxy mensal. | M17: =IF(C17="","",IFERROR(INDEX('6. Base de Custos'!$N$8:$N$42,MATCH(C17,'6. Base de Custos'!$L$8:$L$42,0)),"Não classificado")) | N17: =IF(C17="","",IFERROR(INDEX('6. Base de Custos'!$O$8:$O$42,MATCH(C17,'6. Base de Custos'!$L$8:$L$42,0)),"Revisar")) | O17: =IF(M17="","",IFERROR(VLOOKUP(M17,'6. Base de Custos'!$H$12:$J$18,3,FALSE),0)) | P17: =IF(C17="","",IFERROR(INDEX('6. Base de Custos'!$P$8:$P$42,MATCH(C17,'6. Base de Custos'!$L$8:$L$42,0)),"Revisar")) | Q17: =IF(C17="","",IFERROR(INDEX('6. Base de Custos'!$Q$8:$Q$42,MATCH(C17,'6. Base de Custos'!$L$8:$L$42,0)),"")) | R17: (-) Despesas com tecnologia e contábil | S17: Despesa operacional | T17: =IF(C17="","",IF(R17="(-) Custos diretos dos serviços",IF(ISNUMBER(SEARCH("PCMSO",C17)),"PCMSO",IF(OR(ISNUMBER(SEARCH("SGS",C17)),ISNUMBER(SEARCH("CASTRO NAVES",C17))),"Projetos / Laudos / Avulsos","Projetos / Laudos / Avulsos")),"Rateio pela receita bruta")) | U17: =IF(C17="","",IF(R17="(-) Custos diretos dos serviços","Direto por fornecedor/natureza do gasto","Rateio proporcional à receita bruta da linha de serviço"))
... A38: CP-033 | B38: =IF(F38="","",DATE(YEAR(F38),MONTH(F38),1)) | C38: ARTE FINAL - TROCA DA CENTRAL (3/4) | D38: Despesa variável | E38: =IF(C38="","",IFERROR(INDEX('6. Base de Custos'!$M$8:$M$42,MATCH(C38,'6. Base de Custos'!$L$8:$L$42,0)),"Não classificado")) | F38: 46103 | G38: 46103 | H38: 46112 | I38: 345 | J38: Pago | K38: Variável | L38: Origem: CP mar/2026. Data de pagamento não informada no PDF; alocada em 31/03 como proxy mensal. | M38: =IF(C38="","",IFERROR(INDEX('6. Base de Custos'!$N$8:$N$42,MATCH(C38,'6. Base de Custos'!$L$8:$L$42,0)),"Não classificado")) | N38: =IF(C38="","",IFERROR(INDEX('6. Base de Custos'!$O$8:$O$42,MATCH(C38,'6. Base de Custos'!$L$8:$L$42,0)),"Revisar")) | O38: =IF(M38="","",IFERROR(VLOOKUP(M38,'6. Base de Custos'!$H$12:$J$18,3,FALSE),0)) | P38: =IF(C38="","",IFERROR(INDEX('6. Base de Custos'!$P$8:$P$42,MATCH(C38,'6. Base de Custos'!$L$8:$L$42,0)),"Revisar")) | Q38: =IF(C38="","",IFERROR(INDEX('6. Base de Custos'!$Q$8:$Q$42,MATCH(C38,'6. Base de Custos'!$L$8:$L$42,0)),"")) | R38: (-) Despesas operacionais e infraestrutura | S38: Despesa operacional | T38: =IF(C38="","",IF(R38="(-) Custos diretos dos serviços",IF(ISNUMBER(SEARCH("PCMSO",C38)),"PCMSO",IF(OR(ISNUMBER(SEARCH("SGS",C38)),ISNUMBER(SEARCH("CASTRO NAVES",C38))),"Projetos / Laudos / Avulsos","Projetos / Laudos / Avulsos")),"Rateio pela receita bruta")) | U38: =IF(C38="","",IF(R38="(-) Custos diretos dos serviços","Direto por fornecedor/natureza do gasto","Rateio proporcional à receita bruta da linha de serviço"))
A39: CP-034 | B39: =IF(F39="","",DATE(YEAR(F39),MONTH(F39),1)) | C39: IPTU(1/6) | D39: Despesa variável | E39: =IF(C39="","",IFERROR(INDEX('6. Base de Custos'!$M$8:$M$42,MATCH(C39,'6. Base de Custos'!$L$8:$L$42,0)),"Não classificado")) | F39: 46112 | G39: 46112 | I39: 174.01 | J39: Aberto | K39: Variável | L39: Origem: CP mar/2026. | M39: =IF(C39="","",IFERROR(INDEX('6. Base de Custos'!$N$8:$N$42,MATCH(C39,'6. Base de Custos'!$L$8:$L$42,0)),"Não classificado")) | N39: =IF(C39="","",IFERROR(INDEX('6. Base de Custos'!$O$8:$O$42,MATCH(C39,'6. Base de Custos'!$L$8:$L$42,0)),"Revisar")) | O39: =IF(M39="","",IFERROR(VLOOKUP(M39,'6. Base de Custos'!$H$12:$J$18,3,FALSE),0)) | P39: =IF(C39="","",IFERROR(INDEX('6. Base de Custos'!$P$8:$P$42,MATCH(C39,'6. Base de Custos'!$L$8:$L$42,0)),"Revisar")) | Q39: =IF(C39="","",IFERROR(INDEX('6. Base de Custos'!$Q$8:$Q$42,MATCH(C39,'6. Base de Custos'!$L$8:$L$42,0)),"")) | R39: (-) Encargos trabalhistas e tributos operacionais | S39: Despesa operacional | T39: =IF(C39="","",IF(R39="(-) Custos diretos dos serviços",IF(ISNUMBER(SEARCH("PCMSO",C39)),"PCMSO",IF(OR(ISNUMBER(SEARCH("SGS",C39)),ISNUMBER(SEARCH("CASTRO NAVES",C39))),"Projetos / Laudos / Avulsos","Projetos / Laudos / Avulsos")),"Rateio pela receita bruta")) | U39: =IF(C39="","",IF(R39="(-) Custos diretos dos serviços","Direto por fornecedor/natureza do gasto","Rateio proporcional à receita bruta da linha de serviço"))
A40: CP-035 | B40: =IF(F40="","",DATE(YEAR(F40),MONTH(F40),1)) | C40: CASTRO NAVES | D40: Despesa variável | E40: =IF(C40="","",IFERROR(INDEX('6. Base de Custos'!$M$8:$M$42,MATCH(C40,'6. Base de Custos'!$L$8:$L$42,0)),"Não classificado")) | F40: 46112 | G40: 46112 | H40: 46112 | I40: 0 | J40: Pago | K40: Variável | L40: Origem: CP mar/2026. Data de pagamento não informada no PDF; alocada em 31/03 como proxy mensal. valor não informado no PDF | M40: =IF(C40="","",IFERROR(INDEX('6. Base de Custos'!$N$8:$N$42,MATCH(C40,'6. Base de Custos'!$L$8:$L$42,0)),"Não classificado")) | N40: =IF(C40="","",IFERROR(INDEX('6. Base de Custos'!$O$8:$O$42,MATCH(C40,'6. Base de Custos'!$L$8:$L$42,0)),"Revisar")) | O40: =IF(M40="","",IFERROR(VLOOKUP(M40,'6. Base de Custos'!$H$12:$J$18,3,FALSE),0)) | P40: =IF(C40="","",IFERROR(INDEX('6. Base de Custos'!$P$8:$P$42,MATCH(C40,'6. Base de Custos'!$L$8:$L$42,0)),"Revisar")) | Q40: =IF(C40="","",IFERROR(INDEX('6. Base de Custos'!$Q$8:$Q$42,MATCH(C40,'6. Base de Custos'!$L$8:$L$42,0)),"")) | R40: (-) Custos diretos dos serviços | S40: Custo direto | T40: =IF(C40="","",IF(R40="(-) Custos diretos dos serviços",IF(ISNUMBER(SEARCH("PCMSO",C40)),"PCMSO",IF(OR(ISNUMBER(SEARCH("SGS",C40)),ISNUMBER(SEARCH("CASTRO NAVES",C40))),"Projetos / Laudos / Avulsos","Projetos / Laudos / Avulsos")),"Rateio pela receita bruta")) | U40: =IF(C40="","",IF(R40="(-) Custos diretos dos serviços","Direto por fornecedor/natureza do gasto","Rateio proporcional à receita bruta da linha de serviço"))
A41: CP-036 | B41: =IF(F41="","",DATE(YEAR(F41),MONTH(F41),1)) | C41: TX DE FUNCIONAMENTO (1/2) | D41: Despesa variável | E41: =IF(C41="","",IFERROR(INDEX('6. Base de Custos'!$M$8:$M$42,MATCH(C41,'6. Base de Custos'!$L$8:$L$42,0)),"Não classificado")) | F41: 46112 | G41: 46112 | I41: 194.79 | J41: Aberto | K41: Variável | L41: Origem: CP mar/2026. | M41: =IF(C41="","",IFERROR(INDEX('6. Base de Custos'!$N$8:$N$42,MATCH(C41,'6. Base de Custos'!$L$8:$L$42,0)),"Não classificado")) | N41: =IF(C41="","",IFERROR(INDEX('6. Base de Custos'!$O$8:$O$42,MATCH(C41,'6. Base de Custos'!$L$8:$L$42,0)),"Revisar")) | O41: =IF(M41="","",IFERROR(VLOOKUP(M41,'6. Base de Custos'!$H$12:$J$18,3,FALSE),0)) | P41: =IF(C41="","",IFERROR(INDEX('6. Base de Custos'!$P$8:$P$42,MATCH(C41,'6. Base de Custos'!$L$8:$L$42,0)),"Revisar")) | Q41: =IF(C41="","",IFERROR(INDEX('6. Base de Custos'!$Q$8:$Q$42,MATCH(C41,'6. Base de Custos'!$L$8:$L$42,0)),"")) | R41: (-) Encargos trabalhistas e tributos operacionais | S41: Despesa operacional | T41: =IF(C41="","",IF(R41="(-) Custos diretos dos serviços",IF(ISNUMBER(SEARCH("PCMSO",C41)),"PCMSO",IF(OR(ISNUMBER(SEARCH("SGS",C41)),ISNUMBER(SEARCH("CASTRO NAVES",C41))),"Projetos / Laudos / Avulsos","Projetos / Laudos / Avulsos")),"Rateio pela receita bruta")) | U41: =IF(C41="","",IF(R41="(-) Custos diretos dos serviços","Direto por fornecedor/natureza do gasto","Rateio proporcional à receita bruta da linha de serviço"))
B42: =IF(F42="","",DATE(YEAR(F42),MONTH(F42),1)) | E42: =IF(C42="","",IFERROR(INDEX('6. Base de Custos'!$M$8:$M$42,MATCH(C42,'6. Base de Custos'!$L$8:$L$42,0)),"Não classificado")) | M42: =IF(C42="","",IFERROR(INDEX('6. Base de Custos'!$N$8:$N$42,MATCH(C42,'6. Base de Custos'!$L$8:$L$42,0)),"Não classificado")) | N42: =IF(C42="","",IFERROR(INDEX('6. Base de Custos'!$O$8:$O$42,MATCH(C42,'6. Base de Custos'!$L$8:$L$42,0)),"Revisar")) | O42: =IF(M42="","",IFERROR(VLOOKUP(M42,'6. Base de Custos'!$H$12:$J$18,3,FALSE),0)) | P42: =IF(C42="","",IFERROR(INDEX('6. Base de Custos'!$P$8:$P$42,MATCH(C42,'6. Base de Custos'!$L$8:$L$42,0)),"Revisar")) | Q42: =IF(C42="","",IFERROR(INDEX('6. Base de Custos'!$Q$8:$Q$42,MATCH(C42,'6. Base de Custos'!$L$8:$L$42,0)),"")) | T42: =IF(C42="","",IF(R42="(-) Custos diretos dos serviços",IF(ISNUMBER(SEARCH("PCMSO",C42)),"PCMSO",IF(OR(ISNUMBER(SEARCH("SGS",C42)),ISNUMBER(SEARCH("CASTRO NAVES",C42))),"Projetos / Laudos / Avulsos","Projetos / Laudos / Avulsos")),"Rateio pela receita bruta")) | U42: =IF(C42="","",IF(R42="(-) Custos diretos dos serviços","Direto por fornecedor/natureza do gasto","Rateio proporcional à receita bruta da linha de serviço"))
B43: =IF(F43="","",DATE(YEAR(F43),MONTH(F43),1)) | E43: =IF(C43="","",IFERROR(INDEX('6. Base de Custos'!$M$8:$M$42,MATCH(C43,'6. Base de Custos'!$L$8:$L$42,0)),"Não classificado")) | M43: =IF(C43="","",IFERROR(INDEX('6. Base de Custos'!$N$8:$N$42,MATCH(C43,'6. Base de Custos'!$L$8:$L$42,0)),"Não classificado")) | N43: =IF(C43="","",IFERROR(INDEX('6. Base de Custos'!$O$8:$O$42,MATCH(C43,'6. Base de Custos'!$L$8:$L$42,0)),"Revisar")) | O43: =IF(M43="","",IFERROR(VLOOKUP(M43,'6. Base de Custos'!$H$12:$J$18,3,FALSE),0)) | P43: =IF(C43="","",IFERROR(INDEX('6. Base de Custos'!$P$8:$P$42,MATCH(C43,'6. Base de Custos'!$L$8:$L$42,0)),"Revisar")) | Q43: =IF(C43="","",IFERROR(INDEX('6. Base de Custos'!$Q$8:$Q$42,MATCH(C43,'6. Base de Custos'!$L$8:$L$42,0)),"")) | T43: =IF(C43="","",IF(R43="(-) Custos diretos dos serviços",IF(ISNUMBER(SEARCH("PCMSO",C43)),"PCMSO",IF(OR(ISNUMBER(SEARCH("SGS",C43)),ISNUMBER(SEARCH("CASTRO NAVES",C43))),"Projetos / Laudos / Avulsos","Projetos / Laudos / Avulsos")),"Rateio pela receita bruta")) | U43: =IF(C43="","",IF(R43="(-) Custos diretos dos serviços","Direto por fornecedor/natureza do gasto","Rateio proporcional à receita bruta da linha de serviço"))
B44: =IF(F44="","",DATE(YEAR(F44),MONTH(F44),1)) | E44: =IF(C44="","",IFERROR(INDEX('6. Base de Custos'!$M$8:$M$42,MATCH(C44,'6. Base de Custos'!$L$8:$L$42,0)),"Não classificado")) | M44: =IF(C44="","",IFERROR(INDEX('6. Base de Custos'!$N$8:$N$42,MATCH(C44,'6. Base de Custos'!$L$8:$L$42,0)),"Não classificado")) | N44: =IF(C44="","",IFERROR(INDEX('6. Base de Custos'!$O$8:$O$42,MATCH(C44,'6. Base de Custos'!$L$8:$L$42,0)),"Revisar")) | O44: =IF(M44="","",IFERROR(VLOOKUP(M44,'6. Base de Custos'!$H$12:$J$18,3,FALSE),0)) | P44: =IF(C44="","",IFERROR(INDEX('6. Base de Custos'!$P$8:$P$42,MATCH(C44,'6. Base de Custos'!$L$8:$L$42,0)),"Revisar")) | Q44: =IF(C44="","",IFERROR(INDEX('6. Base de Custos'!$Q$8:$Q$42,MATCH(C44,'6. Base de Custos'!$L$8:$L$42,0)),"")) | T44: =IF(C44="","",IF(R44="(-) Custos diretos dos serviços",IF(ISNUMBER(SEARCH("PCMSO",C44)),"PCMSO",IF(OR(ISNUMBER(SEARCH("SGS",C44)),ISNUMBER(SEARCH("CASTRO NAVES",C44))),"Projetos / Laudos / Avulsos","Projetos / Laudos / Avulsos")),"Rateio pela receita bruta")) | U44: =IF(C44="","",IF(R44="(-) Custos diretos dos serviços","Direto por fornecedor/natureza do gasto","Rateio proporcional à receita bruta da linha de serviço"))
B45: =IF(F45="","",DATE(YEAR(F45),MONTH(F45),1)) | E45: =IF(C45="","",IFERROR(INDEX('6. Base de Custos'!$M$8:$M$42,MATCH(C45,'6. Base de Custos'!$L$8:$L$42,0)),"Não classificado")) | M45: =IF(C45="","",IFERROR(INDEX('6. Base de Custos'!$N$8:$N$42,MATCH(C45,'6. Base de Custos'!$L$8:$L$42,0)),"Não classificado")) | N45: =IF(C45="","",IFERROR(INDEX('6. Base de Custos'!$O$8:$O$42,MATCH(C45,'6. Base de Custos'!$L$8:$L$42,0)),"Revisar")) | O45: =IF(M45="","",IFERROR(VLOOKUP(M45,'6. Base de Custos'!$H$12:$J$18,3,FALSE),0)) | P45: =IF(C45="","",IFERROR(INDEX('6. Base de Custos'!$P$8:$P$42,MATCH(C45,'6. Base de Custos'!$L$8:$L$42,0)),"Revisar")) | Q45: =IF(C45="","",IFERROR(INDEX('6. Base de Custos'!$Q$8:$Q$42,MATCH(C45,'6. Base de Custos'!$L$8:$L$42,0)),"")) | T45: =IF(C45="","",IF(R45="(-) Custos diretos dos serviços",IF(ISNUMBER(SEARCH("PCMSO",C45)),"PCMSO",IF(OR(ISNUMBER(SEARCH("SGS",C45)),ISNUMBER(SEARCH("CASTRO NAVES",C45))),"Projetos / Laudos / Avulsos","Projetos / Laudos / Avulsos")),"Rateio pela receita bruta")) | U45: =IF(C45="","",IF(R45="(-) Custos diretos dos serviços","Direto por fornecedor/natureza do gasto","Rateio proporcional à receita bruta da linha de serviço"))
B46: =IF(F46="","",DATE(YEAR(F46),MONTH(F46),1)) | E46: =IF(C46="","",IFERROR(INDEX('6. Base de Custos'!$M$8:$M$42,MATCH(C46,'6. Base de Custos'!$L$8:$L$42,0)),"Não classificado")) | M46: =IF(C46="","",IFERROR(INDEX('6. Base de Custos'!$N$8:$N$42,MATCH(C46,'6. Base de Custos'!$L$8:$L$42,0)),"Não classificado")) | N46: =IF(C46="","",IFERROR(INDEX('6. Base de Custos'!$O$8:$O$42,MATCH(C46,'6. Base de Custos'!$L$8:$L$42,0)),"Revisar")) | O46: =IF(M46="","",IFERROR(VLOOKUP(M46,'6. Base de Custos'!$H$12:$J$18,3,FALSE),0)) | P46: =IF(C46="","",IFERROR(INDEX('6. Base de Custos'!$P$8:$P$42,MATCH(C46,'6. Base de Custos'!$L$8:$L$42,0)),"Revisar")) | Q46: =IF(C46="","",IFERROR(INDEX('6. Base de Custos'!$Q$8:$Q$42,MATCH(C46,'6. Base de Custos'!$L$8:$L$42,0)),"")) | T46: =IF(C46="","",IF(R46="(-) Custos diretos dos serviços",IF(ISNUMBER(SEARCH("PCMSO",C46)),"PCMSO",IF(OR(ISNUMBER(SEARCH("SGS",C46)),ISNUMBER(SEARCH("CASTRO NAVES",C46))),"Projetos / Laudos / Avulsos","Projetos / Laudos / Avulsos")),"Rateio pela receita bruta")) | U46: =IF(C46="","",IF(R46="(-) Custos diretos dos serviços","Direto por fornecedor/natureza do gasto","Rateio proporcional à receita bruta da linha de serviço"))
B47: =IF(F47="","",DATE(YEAR(F47),MONTH(F47),1)) | E47: =IF(C47="","",IFERROR(INDEX('6. Base de Custos'!$M$8:$M$42,MATCH(C47,'6. Base de Custos'!$L$8:$L$42,0)),"Não classificado")) | M47: =IF(C47="","",IFERROR(INDEX('6. Base de Custos'!$N$8:$N$42,MATCH(C47,'6. Base de Custos'!$L$8:$L$42,0)),"Não classificado")) | N47: =IF(C47="","",IFERROR(INDEX('6. Base de Custos'!$O$8:$O$42,MATCH(C47,'6. Base de Custos'!$L$8:$L$42,0)),"Revisar")) | O47: =IF(M47="","",IFERROR(VLOOKUP(M47,'6. Base de Custos'!$H$12:$J$18,3,FALSE),0)) | P47: =IF(C47="","",IFERROR(INDEX('6. Base de Custos'!$P$8:$P$42,MATCH(C47,'6. Base de Custos'!$L$8:$L$42,0)),"Revisar")) | Q47: =IF(C47="","",IFERROR(INDEX('6. Base de Custos'!$Q$8:$Q$42,MATCH(C47,'6. Base de Custos'!$L$8:$L$42,0)),"")) | T47: =IF(C47="","",IF(R47="(-) Custos diretos dos serviços",IF(ISNUMBER(SEARCH("PCMSO",C47)),"PCMSO",IF(OR(ISNUMBER(SEARCH("SGS",C47)),ISNUMBER(SEARCH("CASTRO NAVES",C47))),"Projetos / Laudos / Avulsos","Projetos / Laudos / Avulsos")),"Rateio pela receita bruta")) | U47: =IF(C47="","",IF(R47="(-) Custos diretos dos serviços","Direto por fornecedor/natureza do gasto","Rateio proporcional à receita bruta da linha de serviço"))
B48: =IF(F48="","",DATE(YEAR(F48),MONTH(F48),1)) | E48: =IF(C48="","",IFERROR(INDEX('6. Base de Custos'!$M$8:$M$42,MATCH(C48,'6. Base de Custos'!$L$8:$L$42,0)),"Não classificado")) | M48: =IF(C48="","",IFERROR(INDEX('6. Base de Custos'!$N$8:$N$42,MATCH(C48,'6. Base de Custos'!$L$8:$L$42,0)),"Não classificado")) | N48: =IF(C48="","",IFERROR(INDEX('6. Base de Custos'!$O$8:$O$42,MATCH(C48,'6. Base de Custos'!$L$8:$L$42,0)),"Revisar")) | O48: =IF(M48="","",IFERROR(VLOOKUP(M48,'6. Base de Custos'!$H$12:$J$18,3,FALSE),0)) | P48: =IF(C48="","",IFERROR(INDEX('6. Base de Custos'!$P$8:$P$42,MATCH(C48,'6. Base de Custos'!$L$8:$L$42,0)),"Revisar")) | Q48: =IF(C48="","",IFERROR(INDEX('6. Base de Custos'!$Q$8:$Q$42,MATCH(C48,'6. Base de Custos'!$L$8:$L$42,0)),"")) | T48: =IF(C48="","",IF(R48="(-) Custos diretos dos serviços",IF(ISNUMBER(SEARCH("PCMSO",C48)),"PCMSO",IF(OR(ISNUMBER(SEARCH("SGS",C48)),ISNUMBER(SEARCH("CASTRO NAVES",C48))),"Projetos / Laudos / Avulsos","Projetos / Laudos / Avulsos")),"Rateio pela receita bruta")) | U48: =IF(C48="","",IF(R48="(-) Custos diretos dos serviços","Direto por fornecedor/natureza do gasto","Rateio proporcional à receita bruta da linha de serviço"))
B49: =IF(F49="","",DATE(YEAR(F49),MONTH(F49),1)) | E49: =IF(C49="","",IFERROR(INDEX('6. Base de Custos'!$M$8:$M$42,MATCH(C49,'6. Base de Custos'!$L$8:$L$42,0)),"Não classificado")) | M49: =IF(C49="","",IFERROR(INDEX('6. Base de Custos'!$N$8:$N$42,MATCH(C49,'6. Base de Custos'!$L$8:$L$42,0)),"Não classificado")) | N49: =IF(C49="","",IFERROR(INDEX('6. Base de Custos'!$O$8:$O$42,MATCH(C49,'6. Base de Custos'!$L$8:$L$42,0)),"Revisar")) | O49: =IF(M49="","",IFERROR(VLOOKUP(M49,'6. Base de Custos'!$H$12:$J$18,3,FALSE),0)) | P49: =IF(C49="","",IFERROR(INDEX('6. Base de Custos'!$P$8:$P$42,MATCH(C49,'6. Base de Custos'!$L$8:$L$42,0)),"Revisar")) | Q49: =IF(C49="","",IFERROR(INDEX('6. Base de Custos'!$Q$8:$Q$42,MATCH(C49,'6. Base de Custos'!$L$8:$L$42,0)),"")) | T49: =IF(C49="","",IF(R49="(-) Custos diretos dos serviços",IF(ISNUMBER(SEARCH("PCMSO",C49)),"PCMSO",IF(OR(ISNUMBER(SEARCH("SGS",C49)),ISNUMBER(SEARCH("CASTRO NAVES",C49))),"Projetos / Laudos / Avulsos","Projetos / Laudos / Avulsos")),"Rateio pela receita bruta")) | U49: =IF(C49="","",IF(R49="(-) Custos diretos dos serviços","Direto por fornecedor/natureza do gasto","Rateio proporcional à receita bruta da linha de serviço"))
B50: =IF(F50="","",DATE(YEAR(F50),MONTH(F50),1)) | E50: =IF(C50="","",IFERROR(INDEX('6. Base de Custos'!$M$8:$M$42,MATCH(C50,'6. Base de Custos'!$L$8:$L$42,0)),"Não classificado")) | M50: =IF(C50="","",IFERROR(INDEX('6. Base de Custos'!$N$8:$N$42,MATCH(C50,'6. Base de Custos'!$L$8:$L$42,0)),"Não classificado")) | N50: =IF(C50="","",IFERROR(INDEX('6. Base de Custos'!$O$8:$O$42,MATCH(C50,'6. Base de Custos'!$L$8:$L$42,0)),"Revisar")) | O50: =IF(M50="","",IFERROR(VLOOKUP(M50,'6. Base de Custos'!$H$12:$J$18,3,FALSE),0)) | P50: =IF(C50="","",IFERROR(INDEX('6. Base de Custos'!$P$8:$P$42,MATCH(C50,'6. Base de Custos'!$L$8:$L$42,0)),"Revisar")) | Q50: =IF(C50="","",IFERROR(INDEX('6. Base de Custos'!$Q$8:$Q$42,MATCH(C50,'6. Base de Custos'!$L$8:$L$42,0)),"")) | T50: =IF(C50="","",IF(R50="(-) Custos diretos dos serviços",IF(ISNUMBER(SEARCH("PCMSO",C50)),"PCMSO",IF(OR(ISNUMBER(SEARCH("SGS",C50)),ISNUMBER(SEARCH("CASTRO NAVES",C50))),"Projetos / Laudos / Avulsos","Projetos / Laudos / Avulsos")),"Rateio pela receita bruta")) | U50: =IF(C50="","",IF(R50="(-) Custos diretos dos serviços","Direto por fornecedor/natureza do gasto","Rateio proporcional à receita bruta da linha de serviço"))
B51: =IF(F51="","",DATE(YEAR(F51),MONTH(F51),1)) | E51: =IF(C51="","",IFERROR(INDEX('6. Base de Custos'!$M$8:$M$42,MATCH(C51,'6. Base de Custos'!$L$8:$L$42,0)),"Não classificado")) | M51: =IF(C51="","",IFERROR(INDEX('6. Base de Custos'!$N$8:$N$42,MATCH(C51,'6. Base de Custos'!$L$8:$L$42,0)),"Não classificado")) | N51: =IF(C51="","",IFERROR(INDEX('6. Base de Custos'!$O$8:$O$42,MATCH(C51,'6. Base de Custos'!$L$8:$L$42,0)),"Revisar")) | O51: =IF(M51="","",IFERROR(VLOOKUP(M51,'6. Base de Custos'!$H$12:$J$18,3,FALSE),0)) | P51: =IF(C51="","",IFERROR(INDEX('6. Base de Custos'!$P$8:$P$42,MATCH(C51,'6. Base de Custos'!$L$8:$L$42,0)),"Revisar")) | Q51: =IF(C51="","",IFERROR(INDEX('6. Base de Custos'!$Q$8:$Q$42,MATCH(C51,'6. Base de Custos'!$L$8:$L$42,0)),"")) | T51: =IF(C51="","",IF(R51="(-) Custos diretos dos serviços",IF(ISNUMBER(SEARCH("PCMSO",C51)),"PCMSO",IF(OR(ISNUMBER(SEARCH("SGS",C51)),ISNUMBER(SEARCH("CASTRO NAVES",C51))),"Projetos / Laudos / Avulsos","Projetos / Laudos / Avulsos")),"Rateio pela receita bruta")) | U51: =IF(C51="","",IF(R51="(-) Custos diretos dos serviços","Direto por fornecedor/natureza do gasto","Rateio proporcional à receita bruta da linha de serviço"))
B52: =IF(F52="","",DATE(YEAR(F52),MONTH(F52),1)) | E52: =IF(C52="","",IFERROR(INDEX('6. Base de Custos'!$M$8:$M$42,MATCH(C52,'6. Base de Custos'!$L$8:$L$42,0)),"Não classificado")) | M52: =IF(C52="","",IFERROR(INDEX('6. Base de Custos'!$N$8:$N$42,MATCH(C52,'6. Base de Custos'!$L$8:$L$42,0)),"Não classificado")) | N52: =IF(C52="","",IFERROR(INDEX('6. Base de Custos'!$O$8:$O$42,MATCH(C52,'6. Base de Custos'!$L$8:$L$42,0)),"Revisar")) | O52: =IF(M52="","",IFERROR(VLOOKUP(M52,'6. Base de Custos'!$H$12:$J$18,3,FALSE),0)) | P52: =IF(C52="","",IFERROR(INDEX('6. Base de Custos'!$P$8:$P$42,MATCH(C52,'6. Base de Custos'!$L$8:$L$42,0)),"Revisar")) | Q52: =IF(C52="","",IFERROR(INDEX('6. Base de Custos'!$Q$8:$Q$42,MATCH(C52,'6. Base de Custos'!$L$8:$L$42,0)),"")) | T52: =IF(C52="","",IF(R52="(-) Custos diretos dos serviços",IF(ISNUMBER(SEARCH("PCMSO",C52)),"PCMSO",IF(OR(ISNUMBER(SEARCH("SGS",C52)),ISNUMBER(SEARCH("CASTRO NAVES",C52))),"Projetos / Laudos / Avulsos","Projetos / Laudos / Avulsos")),"Rateio pela receita bruta")) | U52: =IF(C52="","",IF(R52="(-) Custos diretos dos serviços","Direto por fornecedor/natureza do gasto","Rateio proporcional à receita bruta da linha de serviço"))
B53: =IF(F53="","",DATE(YEAR(F53),MONTH(F53),1)) | E53: =IF(C53="","",IFERROR(INDEX('6. Base de Custos'!$M$8:$M$42,MATCH(C53,'6. Base de Custos'!$L$8:$L$42,0)),"Não classificado")) | M53: =IF(C53="","",IFERROR(INDEX('6. Base de Custos'!$N$8:$N$42,MATCH(C53,'6. Base de Custos'!$L$8:$L$42,0)),"Não classificado")) | N53: =IF(C53="","",IFERROR(INDEX('6. Base de Custos'!$O$8:$O$42,MATCH(C53,'6. Base de Custos'!$L$8:$L$42,0)),"Revisar")) | O53: =IF(M53="","",IFERROR(VLOOKUP(M53,'6. Base de Custos'!$H$12:$J$18,3,FALSE),0)) | P53: =IF(C53="","",IFERROR(INDEX('6. Base de Custos'!$P$8:$P$42,MATCH(C53,'6. Base de Custos'!$L$8:$L$42,0)),"Revisar")) | Q53: =IF(C53="","",IFERROR(INDEX('6. Base de Custos'!$Q$8:$Q$42,MATCH(C53,'6. Base de Custos'!$L$8:$L$42,0)),"")) | T53: =IF(C53="","",IF(R53="(-) Custos diretos dos serviços",IF(ISNUMBER(SEARCH("PCMSO",C53)),"PCMSO",IF(OR(ISNUMBER(SEARCH("SGS",C53)),ISNUMBER(SEARCH("CASTRO NAVES",C53))),"Projetos / Laudos / Avulsos","Projetos / Laudos / Avulsos")),"Rateio pela receita bruta")) | U53: =IF(C53="","",IF(R53="(-) Custos diretos dos serviços","Direto por fornecedor/natureza do gasto","Rateio proporcional à receita bruta da linha de serviço"))
... B55: =IF(F55="","",DATE(YEAR(F55),MONTH(F55),1)) | E55: =IF(C55="","",IFERROR(INDEX('6. Base de Custos'!$M$8:$M$42,MATCH(C55,'6. Base de Custos'!$L$8:$L$42,0)),"Não classificado")) | M55: =IF(C55="","",IFERROR(INDEX('6. Base de Custos'!$N$8:$N$42,MATCH(C55,'6. Base de Custos'!$L$8:$L$42,0)),"Não classificado")) | N55: =IF(C55="","",IFERROR(INDEX('6. Base de Custos'!$O$8:$O$42,MATCH(C55,'6. Base de Custos'!$L$8:$L$42,0)),"Revisar")) | O55: =IF(M55="","",IFERROR(VLOOKUP(M55,'6. Base de Custos'!$H$12:$J$18,3,FALSE),0)) | P55: =IF(C55="","",IFERROR(INDEX('6. Base de Custos'!$P$8:$P$42,MATCH(C55,'6. Base de Custos'!$L$8:$L$42,0)),"Revisar")) | Q55: =IF(C55="","",IFERROR(INDEX('6. Base de Custos'!$Q$8:$Q$42,MATCH(C55,'6. Base de Custos'!$L$8:$L$42,0)),"")) | T55: =IF(C55="","",IF(R55="(-) Custos diretos dos serviços",IF(ISNUMBER(SEARCH("PCMSO",C55)),"PCMSO",IF(OR(ISNUMBER(SEARCH("SGS",C55)),ISNUMBER(SEARCH("CASTRO NAVES",C55))),"Projetos / Laudos / Avulsos","Projetos / Laudos / Avulsos")),"Rateio pela receita bruta")) | U55: =IF(C55="","",IF(R55="(-) Custos diretos dos serviços","Direto por fornecedor/natureza do gasto","Rateio proporcional à receita bruta da linha de serviço"))
A56: =IF(C56="","", "CP-"&TEXT(ROW()-5,"000")) | B56: =IF(F56="","",DATE(YEAR(F56),MONTH(F56),1)) | E56: =IF(C56="","",IFERROR(INDEX('6. Base de Custos'!$M$8:$M$42,MATCH(C56,'6. Base de Custos'!$L$8:$L$42,0)),"Não classificado")) | M56: =IF(C56="","",IFERROR(INDEX('6. Base de Custos'!$N$8:$N$42,MATCH(C56,'6. Base de Custos'!$L$8:$L$42,0)),"Não classificado")) | N56: =IF(C56="","",IFERROR(INDEX('6. Base de Custos'!$O$8:$O$42,MATCH(C56,'6. Base de Custos'!$L$8:$L$42,0)),"Revisar")) | O56: =IF(M56="","",IFERROR(VLOOKUP(M56,'6. Base de Custos'!$H$12:$J$18,3,FALSE),0)) | P56: =IF(C56="","",IFERROR(INDEX('6. Base de Custos'!$P$8:$P$42,MATCH(C56,'6. Base de Custos'!$L$8:$L$42,0)),"Revisar")) | Q56: =IF(C56="","",IFERROR(INDEX('6. Base de Custos'!$Q$8:$Q$42,MATCH(C56,'6. Base de Custos'!$L$8:$L$42,0)),"")) | R56: =IF(C56="","",IFERROR(VLOOKUP(M56&"|"&N56,'17. Mapa DRE CP'!$E$5:$H$100,2,FALSE),"Revisar")) | S56: =IF(C56="","",IFERROR(VLOOKUP(M56&"|"&N56,'17. Mapa DRE CP'!$E$5:$H$100,3,FALSE),"Revisar")) | T56: =IF(C56="","",IF(R56="(-) Custos diretos dos serviços",IF(ISNUMBER(SEARCH("PCMSO",C56)),"PCMSO",IF(OR(ISNUMBER(SEARCH("SGS",C56)),ISNUMBER(SEARCH("CASTRO NAVES",C56))),"Projetos / Laudos / Avulsos","Projetos / Laudos / Avulsos")),"Rateio pela receita bruta")) | U56: =IF(C56="","",IF(R56="(-) Custos diretos dos serviços","Direto por fornecedor/natureza do gasto","Rateio proporcional à receita bruta da linha de serviço"))
A57: =IF(C57="","", "CP-"&TEXT(ROW()-5,"000")) | B57: =IF(F57="","",DATE(YEAR(F57),MONTH(F57),1)) | E57: =IF(C57="","",IFERROR(INDEX('6. Base de Custos'!$M$8:$M$42,MATCH(C57,'6. Base de Custos'!$L$8:$L$42,0)),"Não classificado")) | M57: =IF(C57="","",IFERROR(INDEX('6. Base de Custos'!$N$8:$N$42,MATCH(C57,'6. Base de Custos'!$L$8:$L$42,0)),"Não classificado")) | N57: =IF(C57="","",IFERROR(INDEX('6. Base de Custos'!$O$8:$O$42,MATCH(C57,'6. Base de Custos'!$L$8:$L$42,0)),"Revisar")) | O57: =IF(M57="","",IFERROR(VLOOKUP(M57,'6. Base de Custos'!$H$12:$J$18,3,FALSE),0)) | P57: =IF(C57="","",IFERROR(INDEX('6. Base de Custos'!$P$8:$P$42,MATCH(C57,'6. Base de Custos'!$L$8:$L$42,0)),"Revisar")) | Q57: =IF(C57="","",IFERROR(INDEX('6. Base de Custos'!$Q$8:$Q$42,MATCH(C57,'6. Base de Custos'!$L$8:$L$42,0)),"")) | R57: =IF(C57="","",IFERROR(VLOOKUP(M57&"|"&N57,'17. Mapa DRE CP'!$E$5:$H$100,2,FALSE),"Revisar")) | S57: =IF(C57="","",IFERROR(VLOOKUP(M57&"|"&N57,'17. Mapa DRE CP'!$E$5:$H$100,3,FALSE),"Revisar")) | T57: =IF(C57="","",IF(R57="(-) Custos diretos dos serviços",IF(ISNUMBER(SEARCH("PCMSO",C57)),"PCMSO",IF(OR(ISNUMBER(SEARCH("SGS",C57)),ISNUMBER(SEARCH("CASTRO NAVES",C57))),"Projetos / Laudos / Avulsos","Projetos / Laudos / Avulsos")),"Rateio pela receita bruta")) | U57: =IF(C57="","",IF(R57="(-) Custos diretos dos serviços","Direto por fornecedor/natureza do gasto","Rateio proporcional à receita bruta da linha de serviço"))
A58: =IF(C58="","", "CP-"&TEXT(ROW()-5,"000")) | M58: =IF(C58="","",IFERROR(INDEX('6. Base de Custos'!$N$8:$N$42,MATCH(C58,'6. Base de Custos'!$L$8:$L$42,0)),"Não classificado")) | R58: =IF(C58="","",IFERROR(VLOOKUP(M58&"|"&N58,'17. Mapa DRE CP'!$E$5:$H$100,2,FALSE),"Revisar")) | S58: =IF(C58="","",IFERROR(VLOOKUP(M58&"|"&N58,'17. Mapa DRE CP'!$E$5:$H$100,3,FALSE),"Revisar")) | T58: =IF(C58="","",IF(R58="(-) Custos diretos dos serviços",IF(ISNUMBER(SEARCH("PCMSO",C58)),"PCMSO",IF(OR(ISNUMBER(SEARCH("SGS",C58)),ISNUMBER(SEARCH("CASTRO NAVES",C58))),"Projetos / Laudos / Avulsos","Projetos / Laudos / Avulsos")),"Rateio pela receita bruta")) | U58: =IF(C58="","",IF(R58="(-) Custos diretos dos serviços","Direto por fornecedor/natureza do gasto","Rateio proporcional à receita bruta da linha de serviço"))
A59: =IF(C59="","", "CP-"&TEXT(ROW()-5,"000")) | B59: =IF(F59="","",DATE(YEAR(F59),MONTH(F59),1)) | E59: =IF(C59="","",IFERROR(INDEX('6. Base de Custos'!$M$8:$M$42,MATCH(C59,'6. Base de Custos'!$L$8:$L$42,0)),"Não classificado")) | M59: =IF(C59="","",IFERROR(INDEX('6. Base de Custos'!$N$8:$N$42,MATCH(C59,'6. Base de Custos'!$L$8:$L$42,0)),"Não classificado")) | N59: =IF(C59="","",IFERROR(INDEX('6. Base de Custos'!$O$8:$O$42,MATCH(C59,'6. Base de Custos'!$L$8:$L$42,0)),"Revisar")) | O59: =IF(M59="","",IFERROR(VLOOKUP(M59,'6. Base de Custos'!$H$12:$J$18,3,FALSE),0)) | P59: =IF(C59="","",IFERROR(INDEX('6. Base de Custos'!$P$8:$P$42,MATCH(C59,'6. Base de Custos'!$L$8:$L$42,0)),"Revisar")) | Q59: =IF(C59="","",IFERROR(INDEX('6. Base de Custos'!$Q$8:$Q$42,MATCH(C59,'6. Base de Custos'!$L$8:$L$42,0)),"")) | R59: =IF(C59="","",IFERROR(VLOOKUP(M59&"|"&N59,'17. Mapa DRE CP'!$E$5:$H$100,2,FALSE),"Revisar")) | S59: =IF(C59="","",IFERROR(VLOOKUP(M59&"|"&N59,'17. Mapa DRE CP'!$E$5:$H$100,3,FALSE),"Revisar")) | T59: =IF(C59="","",IF(R59="(-) Custos diretos dos serviços",IF(ISNUMBER(SEARCH("PCMSO",C59)),"PCMSO",IF(OR(ISNUMBER(SEARCH("SGS",C59)),ISNUMBER(SEARCH("CASTRO NAVES",C59))),"Projetos / Laudos / Avulsos","Projetos / Laudos / Avulsos")),"Rateio pela receita bruta")) | U59: =IF(C59="","",IF(R59="(-) Custos diretos dos serviços","Direto por fornecedor/natureza do gasto","Rateio proporcional à receita bruta da linha de serviço"))
A60: =IF(C60="","", "CP-"&TEXT(ROW()-5,"000")) | B60: =IF(F60="","",DATE(YEAR(F60),MONTH(F60),1)) | E60: =IF(C60="","",IFERROR(INDEX('6. Base de Custos'!$M$8:$M$42,MATCH(C60,'6. Base de Custos'!$L$8:$L$42,0)),"Não classificado")) | M60: =IF(C60="","",IFERROR(INDEX('6. Base de Custos'!$N$8:$N$42,MATCH(C60,'6. Base de Custos'!$L$8:$L$42,0)),"Não classificado")) | N60: =IF(C60="","",IFERROR(INDEX('6. Base de Custos'!$O$8:$O$42,MATCH(C60,'6. Base de Custos'!$L$8:$L$42,0)),"Revisar")) | O60: =IF(M60="","",IFERROR(VLOOKUP(M60,'6. Base de Custos'!$H$12:$J$18,3,FALSE),0)) | P60: =IF(C60="","",IFERROR(INDEX('6. Base de Custos'!$P$8:$P$42,MATCH(C60,'6. Base de Custos'!$L$8:$L$42,0)),"Revisar")) | Q60: =IF(C60="","",IFERROR(INDEX('6. Base de Custos'!$Q$8:$Q$42,MATCH(C60,'6. Base de Custos'!$L$8:$L$42,0)),"")) | R60: =IF(C60="","",IFERROR(VLOOKUP(M60&"|"&N60,'17. Mapa DRE CP'!$E$5:$H$100,2,FALSE),"Revisar")) | S60: =IF(C60="","",IFERROR(VLOOKUP(M60&"|"&N60,'17. Mapa DRE CP'!$E$5:$H$100,3,FALSE),"Revisar")) | T60: =IF(C60="","",IF(R60="(-) Custos diretos dos serviços",IF(ISNUMBER(SEARCH("PCMSO",C60)),"PCMSO",IF(OR(ISNUMBER(SEARCH("SGS",C60)),ISNUMBER(SEARCH("CASTRO NAVES",C60))),"Projetos / Laudos / Avulsos","Projetos / Laudos / Avulsos")),"Rateio pela receita bruta")) | U60: =IF(C60="","",IF(R60="(-) Custos diretos dos serviços","Direto por fornecedor/natureza do gasto","Rateio proporcional à receita bruta da linha de serviço"))
A61: =IF(C61="","", "CP-"&TEXT(ROW()-5,"000")) | B61: =IF(F61="","",DATE(YEAR(F61),MONTH(F61),1)) | E61: =IF(C61="","",IFERROR(INDEX('6. Base de Custos'!$M$8:$M$42,MATCH(C61,'6. Base de Custos'!$L$8:$L$42,0)),"Não classificado")) | M61: =IF(C61="","",IFERROR(INDEX('6. Base de Custos'!$N$8:$N$42,MATCH(C61,'6. Base de Custos'!$L$8:$L$42,0)),"Não classificado")) | N61: =IF(C61="","",IFERROR(INDEX('6. Base de Custos'!$O$8:$O$42,MATCH(C61,'6. Base de Custos'!$L$8:$L$42,0)),"Revisar")) | O61: =IF(M61="","",IFERROR(VLOOKUP(M61,'6. Base de Custos'!$H$12:$J$18,3,FALSE),0)) | P61: =IF(C61="","",IFERROR(INDEX('6. Base de Custos'!$P$8:$P$42,MATCH(C61,'6. Base de Custos'!$L$8:$L$42,0)),"Revisar")) | Q61: =IF(C61="","",IFERROR(INDEX('6. Base de Custos'!$Q$8:$Q$42,MATCH(C61,'6. Base de Custos'!$L$8:$L$42,0)),"")) | R61: =IF(C61="","",IFERROR(VLOOKUP(M61&"|"&N61,'17. Mapa DRE CP'!$E$5:$H$100,2,FALSE),"Revisar")) | S61: =IF(C61="","",IFERROR(VLOOKUP(M61&"|"&N61,'17. Mapa DRE CP'!$E$5:$H$100,3,FALSE),"Revisar")) | T61: =IF(C61="","",IF(R61="(-) Custos diretos dos serviços",IF(ISNUMBER(SEARCH("PCMSO",C61)),"PCMSO",IF(OR(ISNUMBER(SEARCH("SGS",C61)),ISNUMBER(SEARCH("CASTRO NAVES",C61))),"Projetos / Laudos / Avulsos","Projetos / Laudos / Avulsos")),"Rateio pela receita bruta")) | U61: =IF(C61="","",IF(R61="(-) Custos diretos dos serviços","Direto por fornecedor/natureza do gasto","Rateio proporcional à receita bruta da linha de serviço"))
A62: =IF(C62="","", "CP-"&TEXT(ROW()-5,"000")) | B62: =IF(F62="","",DATE(YEAR(F62),MONTH(F62),1)) | E62: =IF(C62="","",IFERROR(INDEX('6. Base de Custos'!$M$8:$M$42,MATCH(C62,'6. Base de Custos'!$L$8:$L$42,0)),"Não classificado")) | M62: =IF(C62="","",IFERROR(INDEX('6. Base de Custos'!$N$8:$N$42,MATCH(C62,'6. Base de Custos'!$L$8:$L$42,0)),"Não classificado")) | N62: =IF(C62="","",IFERROR(INDEX('6. Base de Custos'!$O$8:$O$42,MATCH(C62,'6. Base de Custos'!$L$8:$L$42,0)),"Revisar")) | O62: =IF(M62="","",IFERROR(VLOOKUP(M62,'6. Base de Custos'!$H$12:$J$18,3,FALSE),0)) | P62: =IF(C62="","",IFERROR(INDEX('6. Base de Custos'!$P$8:$P$42,MATCH(C62,'6. Base de Custos'!$L$8:$L$42,0)),"Revisar")) | Q62: =IF(C62="","",IFERROR(INDEX('6. Base de Custos'!$Q$8:$Q$42,MATCH(C62,'6. Base de Custos'!$L$8:$L$42,0)),"")) | R62: =IF(C62="","",IFERROR(VLOOKUP(M62&"|"&N62,'17. Mapa DRE CP'!$E$5:$H$100,2,FALSE),"Revisar")) | S62: =IF(C62="","",IFERROR(VLOOKUP(M62&"|"&N62,'17. Mapa DRE CP'!$E$5:$H$100,3,FALSE),"Revisar")) | T62: =IF(C62="","",IF(R62="(-) Custos diretos dos serviços",IF(ISNUMBER(SEARCH("PCMSO",C62)),"PCMSO",IF(OR(ISNUMBER(SEARCH("SGS",C62)),ISNUMBER(SEARCH("CASTRO NAVES",C62))),"Projetos / Laudos / Avulsos","Projetos / Laudos / Avulsos")),"Rateio pela receita bruta")) | U62: =IF(C62="","",IF(R62="(-) Custos diretos dos serviços","Direto por fornecedor/natureza do gasto","Rateio proporcional à receita bruta da linha de serviço"))
A63: =IF(C63="","", "CP-"&TEXT(ROW()-5,"000")) | B63: =IF(F63="","",DATE(YEAR(F63),MONTH(F63),1)) | E63: =IF(C63="","",IFERROR(INDEX('6. Base de Custos'!$M$8:$M$42,MATCH(C63,'6. Base de Custos'!$L$8:$L$42,0)),"Não classificado")) | M63: =IF(C63="","",IFERROR(INDEX('6. Base de Custos'!$N$8:$N$42,MATCH(C63,'6. Base de Custos'!$L$8:$L$42,0)),"Não classificado")) | N63: =IF(C63="","",IFERROR(INDEX('6. Base de Custos'!$O$8:$O$42,MATCH(C63,'6. Base de Custos'!$L$8:$L$42,0)),"Revisar")) | O63: =IF(M63="","",IFERROR(VLOOKUP(M63,'6. Base de Custos'!$H$12:$J$18,3,FALSE),0)) | P63: =IF(C63="","",IFERROR(INDEX('6. Base de Custos'!$P$8:$P$42,MATCH(C63,'6. Base de Custos'!$L$8:$L$42,0)),"Revisar")) | Q63: =IF(C63="","",IFERROR(INDEX('6. Base de Custos'!$Q$8:$Q$42,MATCH(C63,'6. Base de Custos'!$L$8:$L$42,0)),"")) | R63: =IF(C63="","",IFERROR(VLOOKUP(M63&"|"&N63,'17. Mapa DRE CP'!$E$5:$H$100,2,FALSE),"Revisar")) | S63: =IF(C63="","",IFERROR(VLOOKUP(M63&"|"&N63,'17. Mapa DRE CP'!$E$5:$H$100,3,FALSE),"Revisar")) | T63: =IF(C63="","",IF(R63="(-) Custos diretos dos serviços",IF(ISNUMBER(SEARCH("PCMSO",C63)),"PCMSO",IF(OR(ISNUMBER(SEARCH("SGS",C63)),ISNUMBER(SEARCH("CASTRO NAVES",C63))),"Projetos / Laudos / Avulsos","Projetos / Laudos / Avulsos")),"Rateio pela receita bruta")) | U63: =IF(C63="","",IF(R63="(-) Custos diretos dos serviços","Direto por fornecedor/natureza do gasto","Rateio proporcional à receita bruta da linha de serviço"))
A64: =IF(C64="","", "CP-"&TEXT(ROW()-5,"000")) | E64: =IF(C64="","",IFERROR(INDEX('6. Base de Custos'!$M$8:$M$42,MATCH(C64,'6. Base de Custos'!$L$8:$L$42,0)),"Não classificado")) | M64: =IF(C64="","",IFERROR(INDEX('6. Base de Custos'!$N$8:$N$42,MATCH(C64,'6. Base de Custos'!$L$8:$L$42,0)),"Não classificado")) | N64: =IF(C64="","",IFERROR(INDEX('6. Base de Custos'!$O$8:$O$42,MATCH(C64,'6. Base de Custos'!$L$8:$L$42,0)),"Revisar")) | O64: =IF(M64="","",IFERROR(VLOOKUP(M64,'6. Base de Custos'!$H$12:$J$18,3,FALSE),0)) | P64: =IF(C64="","",IFERROR(INDEX('6. Base de Custos'!$P$8:$P$42,MATCH(C64,'6. Base de Custos'!$L$8:$L$42,0)),"Revisar")) | Q64: =IF(C64="","",IFERROR(INDEX('6. Base de Custos'!$Q$8:$Q$42,MATCH(C64,'6. Base de Custos'!$L$8:$L$42,0)),"")) | R64: =IF(C64="","",IFERROR(VLOOKUP(M64&"|"&N64,'17. Mapa DRE CP'!$E$5:$H$100,2,FALSE),"Revisar")) | S64: =IF(C64="","",IFERROR(VLOOKUP(M64&"|"&N64,'17. Mapa DRE CP'!$E$5:$H$100,3,FALSE),"Revisar")) | T64: =IF(C64="","",IF(R64="(-) Custos diretos dos serviços",IF(ISNUMBER(SEARCH("PCMSO",C64)),"PCMSO",IF(OR(ISNUMBER(SEARCH("SGS",C64)),ISNUMBER(SEARCH("CASTRO NAVES",C64))),"Projetos / Laudos / Avulsos","Projetos / Laudos / Avulsos")),"Rateio pela receita bruta")) | U64: =IF(C64="","",IF(R64="(-) Custos diretos dos serviços","Direto por fornecedor/natureza do gasto","Rateio proporcional à receita bruta da linha de serviço"))
A65: =IF(C65="","", "CP-"&TEXT(ROW()-5,"000")) | B65: =IF(F65="","",DATE(YEAR(F65),MONTH(F65),1)) | E65: =IF(C65="","",IFERROR(INDEX('6. Base de Custos'!$M$8:$M$42,MATCH(C65,'6. Base de Custos'!$L$8:$L$42,0)),"Não classificado")) | M65: =IF(C65="","",IFERROR(INDEX('6. Base de Custos'!$N$8:$N$42,MATCH(C65,'6. Base de Custos'!$L$8:$L$42,0)),"Não classificado")) | N65: =IF(C65="","",IFERROR(INDEX('6. Base de Custos'!$O$8:$O$42,MATCH(C65,'6. Base de Custos'!$L$8:$L$42,0)),"Revisar")) | O65: =IF(M65="","",IFERROR(VLOOKUP(M65,'6. Base de Custos'!$H$12:$J$18,3,FALSE),0)) | P65: =IF(C65="","",IFERROR(INDEX('6. Base de Custos'!$P$8:$P$42,MATCH(C65,'6. Base de Custos'!$L$8:$L$42,0)),"Revisar")) | Q65: =IF(C65="","",IFERROR(INDEX('6. Base de Custos'!$Q$8:$Q$42,MATCH(C65,'6. Base de Custos'!$L$8:$L$42,0)),"")) | R65: =IF(C65="","",IFERROR(VLOOKUP(M65&"|"&N65,'17. Mapa DRE CP'!$E$5:$H$100,2,FALSE),"Revisar")) | S65: =IF(C65="","",IFERROR(VLOOKUP(M65&"|"&N65,'17. Mapa DRE CP'!$E$5:$H$100,3,FALSE),"Revisar")) | T65: =IF(C65="","",IF(R65="(-) Custos diretos dos serviços",IF(ISNUMBER(SEARCH("PCMSO",C65)),"PCMSO",IF(OR(ISNUMBER(SEARCH("SGS",C65)),ISNUMBER(SEARCH("CASTRO NAVES",C65))),"Projetos / Laudos / Avulsos","Projetos / Laudos / Avulsos")),"Rateio pela receita bruta")) | U65: =IF(C65="","",IF(R65="(-) Custos diretos dos serviços","Direto por fornecedor/natureza do gasto","Rateio proporcional à receita bruta da linha de serviço"))
A66: =IF(C66="","", "CP-"&TEXT(ROW()-5,"000")) | B66: =IF(F66="","",DATE(YEAR(F66),MONTH(F66),1)) | E66: =IF(C66="","",IFERROR(INDEX('6. Base de Custos'!$M$8:$M$42,MATCH(C66,'6. Base de Custos'!$L$8:$L$42,0)),"Não classificado")) | M66: =IF(C66="","",IFERROR(INDEX('6. Base de Custos'!$N$8:$N$42,MATCH(C66,'6. Base de Custos'!$L$8:$L$42,0)),"Não classificado")) | N66: =IF(C66="","",IFERROR(INDEX('6. Base de Custos'!$O$8:$O$42,MATCH(C66,'6. Base de Custos'!$L$8:$L$42,0)),"Revisar")) | O66: =IF(M66="","",IFERROR(VLOOKUP(M66,'6. Base de Custos'!$H$12:$J$18,3,FALSE),0)) | P66: =IF(C66="","",IFERROR(INDEX('6. Base de Custos'!$P$8:$P$42,MATCH(C66,'6. Base de Custos'!$L$8:$L$42,0)),"Revisar")) | Q66: =IF(C66="","",IFERROR(INDEX('6. Base de Custos'!$Q$8:$Q$42,MATCH(C66,'6. Base de Custos'!$L$8:$L$42,0)),"")) | R66: =IF(C66="","",IFERROR(VLOOKUP(M66&"|"&N66,'17. Mapa DRE CP'!$E$5:$H$100,2,FALSE),"Revisar")) | S66: =IF(C66="","",IFERROR(VLOOKUP(M66&"|"&N66,'17. Mapa DRE CP'!$E$5:$H$100,3,FALSE),"Revisar")) | T66: =IF(C66="","",IF(R66="(-) Custos diretos dos serviços",IF(ISNUMBER(SEARCH("PCMSO",C66)),"PCMSO",IF(OR(ISNUMBER(SEARCH("SGS",C66)),ISNUMBER(SEARCH("CASTRO NAVES",C66))),"Projetos / Laudos / Avulsos","Projetos / Laudos / Avulsos")),"Rateio pela receita bruta")) | U66: =IF(C66="","",IF(R66="(-) Custos diretos dos serviços","Direto por fornecedor/natureza do gasto","Rateio proporcional à receita bruta da linha de serviço"))
A67: =IF(C67="","", "CP-"&TEXT(ROW()-5,"000")) | B67: =IF(F67="","",DATE(YEAR(F67),MONTH(F67),1)) | E67: =IF(C67="","",IFERROR(INDEX('6. Base de Custos'!$M$8:$M$42,MATCH(C67,'6. Base de Custos'!$L$8:$L$42,0)),"Não classificado")) | M67: =IF(C67="","",IFERROR(INDEX('6. Base de Custos'!$N$8:$N$42,MATCH(C67,'6. Base de Custos'!$L$8:$L$42,0)),"Não classificado")) | N67: =IF(C67="","",IFERROR(INDEX('6. Base de Custos'!$O$8:$O$42,MATCH(C67,'6. Base de Custos'!$L$8:$L$42,0)),"Revisar")) | O67: =IF(M67="","",IFERROR(VLOOKUP(M67,'6. Base de Custos'!$H$12:$J$18,3,FALSE),0)) | P67: =IF(C67="","",IFERROR(INDEX('6. Base de Custos'!$P$8:$P$42,MATCH(C67,'6. Base de Custos'!$L$8:$L$42,0)),"Revisar")) | Q67: =IF(C67="","",IFERROR(INDEX('6. Base de Custos'!$Q$8:$Q$42,MATCH(C67,'6. Base de Custos'!$L$8:$L$42,0)),"")) | R67: =IF(C67="","",IFERROR(VLOOKUP(M67&"|"&N67,'17. Mapa DRE CP'!$E$5:$H$100,2,FALSE),"Revisar")) | S67: =IF(C67="","",IFERROR(VLOOKUP(M67&"|"&N67,'17. Mapa DRE CP'!$E$5:$H$100,3,FALSE),"Revisar")) | T67: =IF(C67="","",IF(R67="(-) Custos diretos dos serviços",IF(ISNUMBER(SEARCH("PCMSO",C67)),"PCMSO",IF(OR(ISNUMBER(SEARCH("SGS",C67)),ISNUMBER(SEARCH("CASTRO NAVES",C67))),"Projetos / Laudos / Avulsos","Projetos / Laudos / Avulsos")),"Rateio pela receita bruta")) | U67: =IF(C67="","",IF(R67="(-) Custos diretos dos serviços","Direto por fornecedor/natureza do gasto","Rateio proporcional à receita bruta da linha de serviço"))
A68: =IF(C68="","", "CP-"&TEXT(ROW()-5,"000")) | B68: =IF(F68="","",DATE(YEAR(F68),MONTH(F68),1)) | E68: =IF(C68="","",IFERROR(INDEX('6. Base de Custos'!$M$8:$M$42,MATCH(C68,'6. Base de Custos'!$L$8:$L$42,0)),"Não classificado")) | M68: =IF(C68="","",IFERROR(INDEX('6. Base de Custos'!$N$8:$N$42,MATCH(C68,'6. Base de Custos'!$L$8:$L$42,0)),"Não classificado")) | N68: =IF(C68="","",IFERROR(INDEX('6. Base de Custos'!$O$8:$O$42,MATCH(C68,'6. Base de Custos'!$L$8:$L$42,0)),"Revisar")) | O68: =IF(M68="","",IFERROR(VLOOKUP(M68,'6. Base de Custos'!$H$12:$J$18,3,FALSE),0)) | P68: =IF(C68="","",IFERROR(INDEX('6. Base de Custos'!$P$8:$P$42,MATCH(C68,'6. Base de Custos'!$L$8:$L$42,0)),"Revisar")) | Q68: =IF(C68="","",IFERROR(INDEX('6. Base de Custos'!$Q$8:$Q$42,MATCH(C68,'6. Base de Custos'!$L$8:$L$42,0)),"")) | R68: =IF(C68="","",IFERROR(VLOOKUP(M68&"|"&N68,'17. Mapa DRE CP'!$E$5:$H$100,2,FALSE),"Revisar")) | S68: =IF(C68="","",IFERROR(VLOOKUP(M68&"|"&N68,'17. Mapa DRE CP'!$E$5:$H$100,3,FALSE),"Revisar")) | T68: =IF(C68="","",IF(R68="(-) Custos diretos dos serviços",IF(ISNUMBER(SEARCH("PCMSO",C68)),"PCMSO",IF(OR(ISNUMBER(SEARCH("SGS",C68)),ISNUMBER(SEARCH("CASTRO NAVES",C68))),"Projetos / Laudos / Avulsos","Projetos / Laudos / Avulsos")),"Rateio pela receita bruta")) | U68: =IF(C68="","",IF(R68="(-) Custos diretos dos serviços","Direto por fornecedor/natureza do gasto","Rateio proporcional à receita bruta da linha de serviço"))
A69: =IF(C69="","", "CP-"&TEXT(ROW()-5,"000")) | B69: =IF(F69="","",DATE(YEAR(F69),MONTH(F69),1)) | E69: =IF(C69="","",IFERROR(INDEX('6. Base de Custos'!$M$8:$M$42,MATCH(C69,'6. Base de Custos'!$L$8:$L$42,0)),"Não classificado")) | M69: =IF(C69="","",IFERROR(INDEX('6. Base de Custos'!$N$8:$N$42,MATCH(C69,'6. Base de Custos'!$L$8:$L$42,0)),"Não classificado")) | N69: =IF(C69="","",IFERROR(INDEX('6. Base de Custos'!$O$8:$O$42,MATCH(C69,'6. Base de Custos'!$L$8:$L$42,0)),"Revisar")) | O69: =IF(M69="","",IFERROR(VLOOKUP(M69,'6. Base de Custos'!$H$12:$J$18,3,FALSE),0)) | P69: =IF(C69="","",IFERROR(INDEX('6. Base de Custos'!$P$8:$P$42,MATCH(C69,'6. Base de Custos'!$L$8:$L$42,0)),"Revisar")) | Q69: =IF(C69="","",IFERROR(INDEX('6. Base de Custos'!$Q$8:$Q$42,MATCH(C69,'6. Base de Custos'!$L$8:$L$42,0)),"")) | R69: =IF(C69="","",IFERROR(VLOOKUP(M69&"|"&N69,'17. Mapa DRE CP'!$E$5:$H$100,2,FALSE),"Revisar")) | S69: =IF(C69="","",IFERROR(VLOOKUP(M69&"|"&N69,'17. Mapa DRE CP'!$E$5:$H$100,3,FALSE),"Revisar")) | T69: =IF(C69="","",IF(R69="(-) Custos diretos dos serviços",IF(ISNUMBER(SEARCH("PCMSO",C69)),"PCMSO",IF(OR(ISNUMBER(SEARCH("SGS",C69)),ISNUMBER(SEARCH("CASTRO NAVES",C69))),"Projetos / Laudos / Avulsos","Projetos / Laudos / Avulsos")),"Rateio pela receita bruta")) | U69: =IF(C69="","",IF(R69="(-) Custos diretos dos serviços","Direto por fornecedor/natureza do gasto","Rateio proporcional à receita bruta da linha de serviço"))
A70: =IF(C70="","", "CP-"&TEXT(ROW()-5,"000")) | B70: =IF(F70="","",DATE(YEAR(F70),MONTH(F70),1)) | E70: =IF(C70="","",IFERROR(INDEX('6. Base de Custos'!$M$8:$M$42,MATCH(C70,'6. Base de Custos'!$L$8:$L$42,0)),"Não classificado")) | M70: =IF(C70="","",IFERROR(INDEX('6. Base de Custos'!$N$8:$N$42,MATCH(C70,'6. Base de Custos'!$L$8:$L$42,0)),"Não classificado")) | N70: =IF(C70="","",IFERROR(INDEX('6. Base de Custos'!$O$8:$O$42,MATCH(C70,'6. Base de Custos'!$L$8:$L$42,0)),"Revisar")) | O70: =IF(M70="","",IFERROR(VLOOKUP(M70,'6. Base de Custos'!$H$12:$J$18,3,FALSE),0)) | P70: =IF(C70="","",IFERROR(INDEX('6. Base de Custos'!$P$8:$P$42,MATCH(C70,'6. Base de Custos'!$L$8:$L$42,0)),"Revisar")) | Q70: =IF(C70="","",IFERROR(INDEX('6. Base de Custos'!$Q$8:$Q$42,MATCH(C70,'6. Base de Custos'!$L$8:$L$42,0)),"")) | R70: =IF(C70="","",IFERROR(VLOOKUP(M70&"|"&N70,'17. Mapa DRE CP'!$E$5:$H$100,2,FALSE),"Revisar")) | S70: =IF(C70="","",IFERROR(VLOOKUP(M70&"|"&N70,'17. Mapa DRE CP'!$E$5:$H$100,3,FALSE),"Revisar")) | T70: =IF(C70="","",IF(R70="(-) Custos diretos dos serviços",IF(ISNUMBER(SEARCH("PCMSO",C70)),"PCMSO",IF(OR(ISNUMBER(SEARCH("SGS",C70)),ISNUMBER(SEARCH("CASTRO NAVES",C70))),"Projetos / Laudos / Avulsos","Projetos / Laudos / Avulsos")),"Rateio pela receita bruta")) | U70: =IF(C70="","",IF(R70="(-) Custos diretos dos serviços","Direto por fornecedor/natureza do gasto","Rateio proporcional à receita bruta da linha de serviço"))
